Workbook

Sheet Q1
A1: Date | B1: Product | C1: Region | D1: SalesRep | E1: Customer | F1: Units | G1: sales | H1: Discount
A2: 40553 | B2: Carlota | C2: East | D2: Pham | E2: AA | F2: 63 | G2: 1449 | H2: 693
A3: 40544 | B3: Quad | C3: East | D3: Sioux | E3: AA | F3: 16 | G3: 432 | H3: 232 | L3: Class II Questions 1) Product and region wise maximum sales. 2) Region wise percentage and average discount. 3) Copy the data whose sales are greater than 1000 and discount less than 500. 4) Copy the data whose region is East. 5) Split the product column by starting 3 letters. 6) Highlight the units greater than 20 and less than 50. 7) Create data for January date. 8)Replace AA with RAM in Customer column. 9) Create charts for the following. a) Average Units by Customer and by SalesRip. b) Percentage of Discount by Region. c) Minimum and maximum Sales by Product and Customer. 10) Calculate the total for for Sales and Units
A4: 40561 | B4: Sunshine | C4: East | D4: Franks | E4: AA | F4: 24 | G4: 456 | H4: 192
A5: 40606 | B5: Sunshine | C5: East | D5: Franks | E5: AA | F5: 24 | G5: 456 | H5: 192
A6: 40572 | B6: Bellen | C6: East | D6: Chin | E6: AST | F6: 50 | G6: 1100 | H6: 500
A7: 40565 | B7: Bellen | C7: West | D7: Pham | E7: AST | F7: 53 | G7: 1166 | H7: 530
A8: 40610 | B8: Bellen | C8: West | D8: Pham | E8: AST | F8: 53 | G8: 1166 | H8: 530
A9: 40545 | B9: Quad | C9: West | D9: Pham | E9: AST | F9: 30 | G9: 810 | H9: 435
A10: 40558 | B10: Sunset | C10: East | D10: Gault | E10: AST | F10: 63 | G10: 1323 | H10: 583
A11: 40561 | B11: Sunshine | C11: West | D11: Sioux | E11: AST | F11: 8 | G11: 152 | H11: 64
A12: 40591 | B12: Sunshine | C12: West | D12: Sioux | E12: AST | F12: 8 | G12: 152 | H12: 64
A13: 40567 | B13: Carlota | C13: MidWest | D13: Franks | E13: BBT | F13: 13 | G13: 299 | H13: 143
A14: 40612 | B14: Carlota | C14: MidWest | D14: Franks | E14: BBT | F14: 13 | G14: 299 | H14: 143
A15: 40554 | B15: Quad | C15: East | D15: Smith | E15: BBT | F15: 49 | G15: 1323 | H15: 711
... A136: 40571 | B136: Sunset | C136: East | D136: Smith | E136: ZAT | F136: 36 | G136: 756 | H136: 333
F137: =SUM(F2:F136) -> 4587 | G137: =SUM(G1:G136) -> 107605

Sheet 1,2,3,4 ans
A1: Date | B1: Product | C1: Region | D1: SalesRep | E1: Customer | F1: Units | G1: sales | H1: Discount
A2: 40553 | B2: Carlota | C2: East | D2: Pham | E2: AA | F2: 63 | G2: 1449 | H2: 693 | K2: 1) Product and region wise maximum sales. | W2: 3) Copy the data whose sales are greater than 1000 and discount less than 500.
A3: 40544 | B3: Quad | C3: East | D3: Sioux | E3: AA | F3: 16 | G3: 432 | H3: 232 | K3: Max of sales | L3: Region
A4: 40561 | B4: Sunshine | C4: East | D4: Franks | E4: AA | F4: 24 | G4: 456 | H4: 192 | K4: Product | L4: East | M4: MidWest | N4: South | O4: West | P4: Grand Total | S4: Date | T4: Product | U4: Region | V4: SalesRep | W4: Customer | X4: Units | Y4: sales | Z4: Discount
A5: 40606 | B5: Sunshine | C5: East | D5: Franks | E5: AA | F5: 24 | G5: 456 | H5: 192 | K5: Bellen | L5: 1298 | M5: 1254 | N5: 770 | O5: 5000 | P5: 5000 | S5: 40560 | T5: Sunshine | U5: MidWest | V5: Franks | W5: HHH | X5: 59 | Y5: 1121 | Z5: 472
A6: 40572 | B6: Bellen | C6: East | D6: Chin | E6: AST | F6: 50 | G6: 1100 | H6: 500 | K6: Carlota | L6: 1449 | M6: 460 | N6: 1219 | O6: 1380 | P6: 1449 | S6: 40561 | T6: Sunshine | U6: MidWest | V6: Chin | W6: PCC | X6: 62 | Y6: 1178 | Z6: 496
A7: 40565 | B7: Bellen | C7: West | D7: Pham | E7: AST | F7: 53 | G7: 1166 | H7: 530 | K7: Quad | L7: 1674 | M7: 1647 | N7: 1512 | O7: 1755 | P7: 1755 | S7: 40606 | T7: Sunshine | U7: MidWest | V7: Chin | W7: PCC | X7: 62 | Y7: 1178 | Z7: 496
A8: 40610 | B8: Bellen | C8: West | D8: Pham | E8: AST | F8: 53 | G8: 1166 | H8: 530 | K8: Sunset | L8: 1323 | M8: 609 | N8: 1197 | O8: 1302 | P8: 1323 | S8: 40549 | T8: Sunshine | U8: East | V8: Franks | W8: PSA | X8: 54 | Y8: 1026 | Z8: 432
A9: 40545 | B9: Quad | C9: West | D9: Pham | E9: AST | F9: 30 | G9: 810 | H9: 435 | K9: Sunshine | L9: 1026 | M9: 1216 | N9: 969 | O9: 1102 | P9: 1216 | S9: 40550 | T9: Sunset | U9: West | V9: Pham | W9: WT | X9: 53 | Y9: 1113 | Z9: 490
A10: 40558 | B10: Sunset | C10: East | D10: Gault | E10: AST | F10: 63 | G10: 1323 | H10: 583 | K10: Grand Total | L10: 1674 | M10: 1647 | N10: 1512 | O10: 5000 | P10: 5000 | S10: 40563 | T10: Sunshine | U10: West | V10: Sioux | W10: YTR | X10: 58 | Y10: 1102 | Z10: 464
A11: 40561 | B11: Sunshine | C11: West | D11: Sioux | E11: AST | F11: 8 | G11: 152 | H11: 64
A12: 40591 | B12: Sunshine | C12: West | D12: Sioux | E12: AST | F12: 8 | G12: 152 | H12: 64 | S12: 4) Copy the data whose region is East.
A13: 40567 | B13: Carlota | C13: MidWest | D13: Franks | E13: BBT | F13: 13 | G13: 299 | H13: 143 | K13: 2) Region wise percentage and average discount.
A14: 40612 | B14: Carlota | C14: MidWest | D14: Franks | E14: BBT | F14: 13 | G14: 299 | H14: 143 | S14: Date | T14: Product | U14: Region | V14: SalesRep | W14: Customer | X14: Units | Y14: sales | Z14: Discount
A15: 40554 | B15: Quad | C15: East | D15: Smith | E15: BBT | F15: 49 | G15: 1323 | H15: 711 | S15: 40553 | T15: Carlota | U15: East | V15: Pham | W15: AA | X15: 63 | Y15: 1449 | Z15: 693
A16: 40547 | B16: Sunset | C16: MidWest | D16: Sioux | E16: BBT | F16: 29 | G16: 609 | H16: 268 | K16: Region | L16: Average of Discount | M16: Sum of Discount | S16: 40544 | T16: Quad | U16: East | V16: Sioux | W16: AA | X16: 16 | Y16: 432 | Z16: 232
A17: 40561 | B17: Bellen | C17: East | D17: Franks | E17: DFGH | F17: 20 | G17: 440 | H17: 200 | K17: East | L17: 408.4359 | M17: 0.32212336 | S17: 40561 | T17: Sunshine | U17: East | V17: Franks | W17: AA | X17: 24 | Y17: 456 | Z17: 192
A18: 40566 | B18: Bellen | C18: East | D18: Gault | E18: DFGH | F18: 9 | G18: 198 | H18: 90 | K18: MidWest | L18: 293.41935 | M18: 0.18394338 | S18: 40606 | T18: Sunshine | U18: East | V18: Franks | W18: AA | X18: 24 | Y18: 456 | Z18: 192
A19: 40611 | B19: Bellen | C19: East | D19: Gault | E19: DFGH | F19: 9 | G19: 198 | H19: 90 | K19: South | L19: 356.17647 | M19: 0.24489383 | S19: 40572 | T19: Bellen | U19: East | V19: Chin | W19: AST | X19: 50 | Y19: 1100 | Z19: 500
A20: 40569 | B20: Sunset | C20: South | D20: Sioux | E20: DFGH | F20: 44 | G20: 924 | H20: 407 | K20: West | L20: 397.25806 | M20: 0.24903943 | S20: 40558 | T20: Sunset | U20: East | V20: Gault | W20: AST | X20: 63 | Y20: 1323 | Z20: 583
A21: 40561 | B21: Bellen | C21: East | D21: Pham | E21: DFR | F21: 59 | G21: 1298 | H21: 590 | K21: (blank) | M21: 0 | S21: 40554 | T21: Quad | U21: East | V21: Smith | W21: BBT | X21: 49 | Y21: 1323 | Z21: 711
A22: 40553 | B22: Quad | C22: East | D22: Smith | E22: DFR | F22: 17 | G22: 459 | H22: 247 | K22: Grand Total | L22: 366.2963 | M22: 1 | S22: 40561 | T22: Bellen | U22: East | V22: Franks | W22: DFGH | X22: 20 | Y22: 440 | Z22: 200
A23: 40564 | B23: Sunshine | C23: MidWest | D23: Pham | E23: DFR | F23: 23 | G23: 437 | H23: 184 | S23: 40566 | T23: Bellen | U23: East | V23: Gault | W23: DFGH | X23: 9 | Y23: 198 | Z23: 90
A24: 40573 | B24: Sunshine | C24: West | D24: Gault | E24: DFR | F24: 49 | G24: 931 | H24: 392 | S24: 40611 | T24: Bellen | U24: East | V24: Gault | W24: DFGH | X24: 9 | Y24: 198 | Z24: 90
A25: 40552 | B25: Bellen | C25: East | D25: Pham | E25: EPP | F25: 40 | G25: 880 | H25: 400 | S25: 40561 | T25: Bellen | U25: East | V25: Pham | W25: DFR | X25: 59 | Y25: 1298 | Z25: 590
A26: 40597 | B26: Bellen | C26: East | D26: Pham | E26: EPP | F26: 40 | G26: 880 | H26: 400 | S26: 40553 | T26: Quad | U26: East | V26: Smith | W26: DFR | X26: 17 | Y26: 459 | Z26: 247
A27: 40560 | B27: Quad | C27: MidWest | D27: Chin | E27: EPP | F27: 61 | G27: 1647 | H27: 885 | S27: 40552 | T27: Bellen | U27: East | V27: Pham | W27: EPP | X27: 40 | Y27: 880 | Z27: 400
A28: 40563 | B28: Carlota | C28: East | D28: Chin | E28: ET | F28: 59 | G28: 1357 | H28: 649 | S28: 40597 | T28: Bellen | U28: East | V28: Pham | W28: EPP | X28: 40 | Y28: 880 | Z28: 400
A29: 40593 | B29: Carlota | C29: East | D29: Chin | E29: ET | F29: 59 | G29: 1357 | H29: 649 | S29: 40563 | T29: Carlota | U29: East | V29: Chin | W29: ET | X29: 59 | Y29: 1357 | Z29: 649
A30: 40548 | B30: Sunshine | C30: West | D30: Franks | E30: ET | F30: 12 | G30: 228 | H30: 96 | S30: 40593 | T30: Carlota | U30: East | V30: Chin | W30: ET | X30: 59 | Y30: 1357 | Z30: 649
A31: 40593 | B31: Sunshine | C31: West | D31: Franks | E31: ET | F31: 12 | G31: 228 | H31: 96 | S31: 40564 | T31: Quad | U31: East | V31: Chin | W31: FM | X31: 58 | Y31: 1566 | Z31: 841
A32: 40553 | B32: Bellen | C32: MidWest | D32: Gault | E32: FM | F32: 7 | G32: 154 | H32: 70 | S32: 40546 | T32: Sunshine | U32: East | V32: Pham | W32: FM | X32: 38 | Y32: 722 | Z32: 304
A33: 40546 | B33: Carlota | C33: MidWest | D33: Chin | E33: FM | F33: 20 | G33: 460 | H33: 220 | S33: 40560 | T33: Quad | U33: East | V33: Franks | W33: HII | X33: 62 | Y33: 1674 | Z33: 899
A34: 40591 | B34: Carlota | C34: MidWest | D34: Chin | E34: FM | F34: 20 | G34: 460 | H34: 220 | S34: 40590 | T34: Quad | U34: East | V34: Franks | W34: HII | X34: 62 | Y34: 1674 | Z34: 899
... A53: 40554 | B53: Quad | C53: East | D53: Franks | E53: ITW | F53: 14 | G53: 378 | H53: 203 | S53: 40571 | T53: Sunset | U53: East | V53: Smith | W53: ZAT | X53: 36 | Y53: 756 | Z53: 333
A54: 40599 | B54: Quad | C54: East | D54: Franks | E54: ITW | F54: 14 | G54: 378 | H54: 203
A55: 40564 | B55: Quad | C55: West | D55: Gault | E55: ITW | F55: 56 | G55: 1512 | H55: 812
A56: 40555 | B56: Sunset | C56: MidWest | D56: Gault | E56: ITW | F56: 19 | G56: 399 | H56: 176
A57: 40557 | B57: Carlota | C57: East | D57: Franks | E57: JAQ | F57: 34 | G57: 782 | H57: 374
A58: 40568 | B58: Sunshine | C58: MidWest | D58: Franks | E58: JAQ | F58: 21 | G58: 399 | H58: 168
A59: 40545 | B59: Bellen | C59: South | D59: Gault | E59: KBTB | F59: 24 | G59: 528 | H59: 240
A60: 40590 | B60: Bellen | C60: South | D60: Gault | E60: KBTB | F60: 24 | G60: 528 | H60: 240
A61: 40565 | B61: Carlota | C61: South | D61: Smith | E61: KBTB | F61: 29 | G61: 667 | H61: 319
A62: 40571 | B62: Quad | C62: South | D62: Gault | E62: KBTB | F62: 56 | G62: 1512 | H62: 812
A63: 40616 | B63: Quad | C63: South | D63: Gault | E63: KBTB | F63: 56 | G63: 1512 | H63: 812
A64: 40553 | B64: Quad | C64: West | D64: Smith | E64: KBTB | F64: 65 | G64: 1755 | H64: 943
A65: 40569 | B65: Bellen | C65: East | D65: Chin | E65: KPSA | F65: 17 | G65: 374 | H65: 170
... A136: 40571 | B136: Sunset | C136: East | D136: Smith | E136: ZAT | F136: 36 | G136: 756 | H136: 333

Sheet 5,6,7,8,9
A1: Split the product column by starting 3 letters. | K1: 6) Highlight the units greater than 20 and less than 50. | T1: 7) Create data for January date. | AD1: 8)Replace AA with RAM in Customer column. | AM1: 9) Create charts for the following. | BU1: b,Percentage of Discount by Region. | CD1: c) Minimum and maximum Sales by Product and Customer.
A2: Date | B2: Product | C2: Region | D2: SalesRep | E2: Customer | F2: Units | G2: sales | H2: Discount | I2: Product 3 letter | K2: Date | L2: Product | M2: Region | N2: SalesRep | O2: Customer | P2: Units | Q2: sales | R2: Discount | T2: Date | U2: Product | V2: Region | W2: SalesRep | X2: Customer | Y2: Units | Z2: sales | AA2: Discount | AD2: Date | AE2: Product | AF2: Region | AG2: SalesRep | AH2: Customer | AI2: Units | AJ2: sales | AK2: Discount | AM2: a.Average Units by Customer and SalesRep.
A3: 40553 | B3: Carlota | C3: East | D3: Pham | E3: AA | F3: 63 | G3: 1449 | H3: 693 | I3: =LEFT(B3,3) -> Car | K3: 40553 | L3: Carlota | M3: East | N3: Pham | O3: AA | P3: 63 | Q3: 1449 | R3: 693 | T3: 40553 | U3: Carlota | V3: East | W3: Pham | X3: AA | Y3: 63 | Z3: 1449 | AA3: 693 | AD3: 40553 | AE3: Carlota | AF3: East | AG3: Pham | AH3: RAM | AI3: 63 | AJ3: 1449 | AK3: 693 | AM3: Customer | AN3: SalesRep | AO3: Average of Units | BU3: Region | BV3: percentage of Discount | CD3: Customer | CE3: Product | CF3: Min of sales | CG3: Max of sales2
A4: 40544 | B4: Quad | C4: East | D4: Sioux | E4: AA | F4: 16 | G4: 432 | H4: 232 | I4: =LEFT(B4,3) -> Qua | K4: 40544 | L4: Quad | M4: East | N4: Sioux | O4: AA | P4: 16 | Q4: 432 | R4: 232 | T4: 40544 | U4: Quad | V4: East | W4: Sioux | X4: AA | Y4: 16 | Z4: 432 | AA4: 232 | AD4: 40544 | AE4: Quad | AF4: East | AG4: Sioux | AH4: RAM | AI4: 16 | AJ4: 432 | AK4: 232 | AM4: AA | AN4: Franks | AO4: 24 | BU4: East | BV4: 0.32212336 | CD4: AA | CE4: Carlota | CF4: 1449 | CG4: 1449
A5: 40561 | B5: Sunshine | C5: East | D5: Franks | E5: AA | F5: 24 | G5: 456 | H5: 192 | I5: =LEFT(B5,3) -> Sun | K5: 40561 | L5: Sunshine | M5: East | N5: Franks | O5: AA | P5: 24 | Q5: 456 | R5: 192 | T5: 40561 | U5: Sunshine | V5: East | W5: Franks | X5: AA | Y5: 24 | Z5: 456 | AA5: 192 | AD5: 40561 | AE5: Sunshine | AF5: East | AG5: Franks | AH5: RAM | AI5: 24 | AJ5: 456 | AK5: 192 | AN5: Pham | AO5: 63 | BU5: MidWest | BV5: 0.18394338 | CE5: Quad | CF5: 432 | CG5: 432
A6: 40606 | B6: Sunshine | C6: East | D6: Franks | E6: AA | F6: 24 | G6: 456 | H6: 192 | I6: =LEFT(B6,3) -> Sun | K6: 40606 | L6: Sunshine | M6: East | N6: Franks | O6: AA | P6: 24 | Q6: 456 | R6: 192 | T6: 40606 | U6: Sunshine | V6: East | W6: Franks | X6: AA | Y6: 24 | Z6: 456 | AA6: 192 | AD6: 40606 | AE6: Sunshine | AF6: East | AG6: Franks | AH6: AA | AI6: 24 | AJ6: 456 | AK6: 192 | AN6: Sioux | AO6: 16 | BU6: South | BV6: 0.24489383 | CE6: Sunshine | CF6: 456 | CG6: 456
A7: 40572 | B7: Bellen | C7: East | D7: Chin | E7: AST | F7: 50 | G7: 1100 | H7: 500 | I7: =LEFT(B7,3) -> Bel | K7: 40572 | L7: Bellen | M7: East | N7: Chin | O7: AST | P7: 50 | Q7: 1100 | R7: 500 | T7: 40572 | U7: Bellen | V7: East | W7: Chin | X7: AST | Y7: 50 | Z7: 1100 | AA7: 500 | AD7: 40572 | AE7: Bellen | AF7: East | AG7: Chin | AH7: AST | AI7: 50 | AJ7: 1100 | AK7: 500 | AM7: AA Total | AO7: 31.75 | BU7: West | BV7: 0.24903943 | CD7: AA Total | CF7: 432 | CG7: 1449
A8: 40565 | B8: Bellen | C8: West | D8: Pham | E8: AST | F8: 53 | G8: 1166 | H8: 530 | I8: =LEFT(B8,3) -> Bel | K8: 40565 | L8: Bellen | M8: West | N8: Pham | O8: AST | P8: 53 | Q8: 1166 | R8: 530 | T8: 40565 | U8: Bellen | V8: West | W8: Pham | X8: AST | Y8: 53 | Z8: 1166 | AA8: 530 | AD8: 40565 | AE8: Bellen | AF8: West | AG8: Pham | AH8: AST | AI8: 53 | AJ8: 1166 | AK8: 530 | AM8: AST | AN8: Chin | AO8: 50 | BU8: Grand Total | BV8: 1 | CD8: AST | CE8: Bellen | CF8: 1100 | CG8: 1166
A9: 40610 | B9: Bellen | C9: West | D9: Pham | E9: AST | F9: 53 | G9: 1166 | H9: 530 | I9: =LEFT(B9,3) -> Bel | K9: 40610 | L9: Bellen | M9: West | N9: Pham | O9: AST | P9: 53 | Q9: 1166 | R9: 530 | T9: 40610 | U9: Bellen | V9: West | W9: Pham | X9: AST | Y9: 53 | Z9: 1166 | AA9: 530 | AD9: 40610 | AE9: Bellen | AF9: West | AG9: Pham | AH9: AST | AI9: 53 | AJ9: 1166 | AK9: 530 | AN9: Gault | AO9: 63 | CE9: Quad | CF9: 810 | CG9: 810
A10: 40545 | B10: Quad | C10: West | D10: Pham | E10: AST | F10: 30 | G10: 810 | H10: 435 | I10: =LEFT(B10,3) -> Qua | K10: 40545 | L10: Quad | M10: West | N10: Pham | O10: AST | P10: 30 | Q10: 810 | R10: 435 | T10: 40545 | U10: Quad | V10: West | W10: Pham | X10: AST | Y10: 30 | Z10: 810 | AA10: 435 | AD10: 40545 | AE10: Quad | AF10: West | AG10: Pham | AH10: AST | AI10: 30 | AJ10: 810 | AK10: 435 | AN10: Pham | AO10: 45.333333 | CE10: Sunset | CF10: 1323 | CG10: 1323
A11: 40558 | B11: Sunset | C11: East | D11: Gault | E11: AST | F11: 63 | G11: 1323 | H11: 583 | I11: =LEFT(B11,3) -> Sun | K11: 40558 | L11: Sunset | M11: East | N11: Gault | O11: AST | P11: 63 | Q11: 1323 | R11: 583 | T11: 40558 | U11: Sunset | V11: East | W11: Gault | X11: AST | Y11: 63 | Z11: 1323 | AA11: 583 | AD11: 40558 | AE11: Sunset | AF11: East | AG11: Gault | AH11: AST | AI11: 63 | AJ11: 1323 | AK11: 583 | AN11: Sioux | AO11: 8 | CE11: Sunshine | CF11: 152 | CG11: 152
A12: 40561 | B12: Sunshine | C12: West | D12: Sioux | E12: AST | F12: 8 | G12: 152 | H12: 64 | I12: =LEFT(B12,3) -> Sun | K12: 40561 | L12: Sunshine | M12: West | N12: Sioux | O12: AST | P12: 8 | Q12: 152 | R12: 64 | T12: 40561 | U12: Sunshine | V12: West | W12: Sioux | X12: AST | Y12: 8 | Z12: 152 | AA12: 64 | AD12: 40561 | AE12: Sunshine | AF12: West | AG12: Sioux | AH12: AST | AI12: 8 | AJ12: 152 | AK12: 64 | AM12: AST Total | AO12: 37.857143 | CD12: AST Total | CF12: 152 | CG12: 1323
A13: 40591 | B13: Sunshine | C13: West | D13: Sioux | E13: AST | F13: 8 | G13: 152 | H13: 64 | I13: =LEFT(B13,3) -> Sun | K13: 40591 | L13: Sunshine | M13: West | N13: Sioux | O13: AST | P13: 8 | Q13: 152 | R13: 64 | T13: 40591 | U13: Sunshine | V13: West | W13: Sioux | X13: AST | Y13: 8 | Z13: 152 | AA13: 64 | AD13: 40591 | AE13: Sunshine | AF13: West | AG13: Sioux | AH13: AST | AI13: 8 | AJ13: 152 | AK13: 64 | AM13: BBT | AN13: Franks | AO13: 13 | CD13: BBT | CE13: Carlota | CF13: 299 | CG13: 299
A14: 40567 | B14: Carlota | C14: MidWest | D14: Franks | E14: BBT | F14: 13 | G14: 299 | H14: 143 | I14: =LEFT(B14,3) -> Car | K14: 40567 | L14: Carlota | M14: MidWest | N14: Franks | O14: BBT | P14: 13 | Q14: 299 | R14: 143 | T14: 40567 | U14: Carlota | V14: MidWest | W14: Franks | X14: BBT | Y14: 13 | Z14: 299 | AA14: 143 | AD14: 40567 | AE14: Carlota | AF14: MidWest | AG14: Franks | AH14: BBT | AI14: 13 | AJ14: 299 | AK14: 143 | AN14: Sioux | AO14: 29 | CE14: Quad | CF14: 1323 | CG14: 1323
A15: 40612 | B15: Carlota | C15: MidWest | D15: Franks | E15: BBT | F15: 13 | G15: 299 | H15: 143 | I15: =LEFT(B15,3) -> Car | K15: 40612 | L15: Carlota | M15: MidWest | N15: Franks | O15: BBT | P15: 13 | Q15: 299 | R15: 143 | T15: 40612 | U15: Carlota | V15: MidWest | W15: Franks | X15: BBT | Y15: 13 | Z15: 299 | AA15: 143 | AD15: 40612 | AE15: Carlota | AF15: MidWest | AG15: Franks | AH15: BBT | AI15: 13 | AJ15: 299 | AK15: 143 | AN15: Smith | AO15: 49 | CE15: Sunset | CF15: 609 | CG15: 609
A16: 40554 | B16: Quad | C16: East | D16: Smith | E16: BBT | F16: 49 | G16: 1323 | H16: 711 | I16: =LEFT(B16,3) -> Qua | K16: 40554 | L16: Quad | M16: East | N16: Smith | O16: BBT | P16: 49 | Q16: 1323 | R16: 711 | T16: 40554 | U16: Quad | V16: East | W16: Smith | X16: BBT | Y16: 49 | Z16: 1323 | AA16: 711 | AD16: 40554 | AE16: Quad | AF16: East | AG16: Smith | AH16: BBT | AI16: 49 | AJ16: 1323 | AK16: 711 | AM16: BBT Total | AO16: 26 | CD16: BBT Total | CF16: 299 | CG16: 1323
A17: 40547 | B17: Sunset | C17: MidWest | D17: Sioux | E17: BBT | F17: 29 | G17: 609 | H17: 268 | I17: =LEFT(B17,3) -> Sun | K17: 40547 | L17: Sunset | M17: MidWest | N17: Sioux | O17: BBT | P17: 29 | Q17: 609 | R17: 268 | T17: 40547 | U17: Sunset | V17: MidWest | W17: Sioux | X17: BBT | Y17: 29 | Z17: 609 | AA17: 268 | AD17: 40547 | AE17: Sunset | AF17: MidWest | AG17: Sioux | AH17: BBT | AI17: 29 | AJ17: 609 | AK17: 268 | AM17: DFGH | AN17: Franks | AO17: 20 | CD17: DFGH | CE17: Bellen | CF17: 198 | CG17: 440
A18: 40561 | B18: Bellen | C18: East | D18: Franks | E18: DFGH | F18: 20 | G18: 440 | H18: 200 | I18: =LEFT(B18,3) -> Bel | K18: 40561 | L18: Bellen | M18: East | N18: Franks | O18: DFGH | P18: 20 | Q18: 440 | R18: 200 | T18: 40561 | U18: Bellen | V18: East | W18: Franks | X18: DFGH | Y18: 20 | Z18: 440 | AA18: 200 | AD18: 40561 | AE18: Bellen | AF18: East | AG18: Franks | AH18: DFGH | AI18: 20 | AJ18: 440 | AK18: 200 | AN18: Gault | AO18: 9 | CE18: Sunset | CF18: 924 | CG18: 924
A19: 40566 | B19: Bellen | C19: East | D19: Gault | E19: DFGH | F19: 9 | G19: 198 | H19: 90 | I19: =LEFT(B19,3) -> Bel | K19: 40566 | L19: Bellen | M19: East | N19: Gault | O19: DFGH | P19: 9 | Q19: 198 | R19: 90 | T19: 40566 | U19: Bellen | V19: East | W19: Gault | X19: DFGH | Y19: 9 | Z19: 198 | AA19: 90 | AD19: 40566 | AE19: Bellen | AF19: East | AG19: Gault | AH19: DFGH | AI19: 9 | AJ19: 198 | AK19: 90 | AN19: Sioux | AO19: 44 | CD19: DFGH Total | CF19: 198 | CG19: 924
A20: 40611 | B20: Bellen | C20: East | D20: Gault | E20: DFGH | F20: 9 | G20: 198 | H20: 90 | I20: =LEFT(B20,3) -> Bel | K20: 40611 | L20: Bellen | M20: East | N20: Gault | O20: DFGH | P20: 9 | Q20: 198 | R20: 90 | T20: 40611 | U20: Bellen | V20: East | W20: Gault | X20: DFGH | Y20: 9 | Z20: 198 | AA20: 90 | AD20: 40611 | AE20: Bellen | AF20: East | AG20: Gault | AH20: DFGH | AI20: 9 | AJ20: 198 | AK20: 90 | AM20: DFGH Total | AO20: 20.5 | CD20: DFR | CE20: Bellen | CF20: 1298 | CG20: 1298
A21: 40569 | B21: Sunset | C21: South | D21: Sioux | E21: DFGH | F21: 44 | G21: 924 | H21: 407 | I21: =LEFT(B21,3) -> Sun | K21: 40569 | L21: Sunset | M21: South | N21: Sioux | O21: DFGH | P21: 44 | Q21: 924 | R21: 407 | T21: 40569 | U21: Sunset | V21: South | W21: Sioux | X21: DFGH | Y21: 44 | Z21: 924 | AA21: 407 | AD21: 40569 | AE21: Sunset | AF21: South | AG21: Sioux | AH21: DFGH | AI21: 44 | AJ21: 924 | AK21: 407 | AM21: DFR | AN21: Gault | AO21: 49 | CE21: Quad | CF21: 459 | CG21: 459
A22: 40561 | B22: Bellen | C22: East | D22: Pham | E22: DFR | F22: 59 | G22: 1298 | H22: 590 | I22: =LEFT(B22,3) -> Bel | K22: 40561 | L22: Bellen | M22: East | N22: Pham | O22: DFR | P22: 59 | Q22: 1298 | R22: 590 | T22: 40561 | U22: Bellen | V22: East | W22: Pham | X22: DFR | Y22: 59 | Z22: 1298 | AA22: 590 | AD22: 40561 | AE22: Bellen | AF22: East | AG22: Pham | AH22: DFR | AI22: 59 | AJ22: 1298 | AK22: 590 | AN22: Pham | AO22: 41 | CE22: Sunshine | CF22: 437 | CG22: 931
A23: 40553 | B23: Quad | C23: East | D23: Smith | E23: DFR | F23: 17 | G23: 459 | H23: 247 | I23: =LEFT(B23,3) -> Qua | K23: 40553 | L23: Quad | M23: East | N23: Smith | O23: DFR | P23: 17 | Q23: 459 | R23: 247 | T23: 40553 | U23: Quad | V23: East | W23: Smith | X23: DFR | Y23: 17 | Z23: 459 | AA23: 247 | AD23: 40553 | AE23: Quad | AF23: East | AG23: Smith | AH23: DFR | AI23: 17 | AJ23: 459 | AK23: 247 | AN23: Smith | AO23: 17 | CD23: DFR Total | CF23: 437 | CG23: 1298
A24: 40564 | B24: Sunshine | C24: MidWest | D24: Pham | E24: DFR | F24: 23 | G24: 437 | H24: 184 | I24: =LEFT(B24,3) -> Sun | K24: 40564 | L24: Sunshine | M24: MidWest | N24: Pham | O24: DFR | P24: 23 | Q24: 437 | R24: 184 | T24: 40564 | U24: Sunshine | V24: MidWest | W24: Pham | X24: DFR | Y24: 23 | Z24: 437 | AA24: 184 | AD24: 40564 | AE24: Sunshine | AF24: MidWest | AG24: Pham | AH24: DFR | AI24: 23 | AJ24: 437 | AK24: 184 | AM24: DFR Total | AO24: 37 | CD24: EPP | CE24: Bellen | CF24: 880 | CG24: 880
A25: 40573 | B25: Sunshine | C25: West | D25: Gault | E25: DFR | F25: 49 | G25: 931 | H25: 392 | I25: =LEFT(B25,3) -> Sun | K25: 40573 | L25: Sunshine | M25: West | N25: Gault | O25: DFR | P25: 49 | Q25: 931 | R25: 392 | T25: 40573 | U25: Sunshine | V25: West | W25: Gault | X25: DFR | Y25: 49 | Z25: 931 | AA25: 392 | AD25: 40573 | AE25: Sunshine | AF25: West | AG25: Gault | AH25: DFR | AI25: 49 | AJ25: 931 | AK25: 392 | AM25: EPP | AN25: Chin | AO25: 61 | CE25: Quad | CF25: 1647 | CG25: 1647
A26: 40552 | B26: Bellen | C26: East | D26: Pham | E26: EPP | F26: 40 | G26: 880 | H26: 400 | I26: =LEFT(B26,3) -> Bel | K26: 40552 | L26: Bellen | M26: East | N26: Pham | O26: EPP | P26: 40 | Q26: 880 | R26: 400 | T26: 40552 | U26: Bellen | V26: East | W26: Pham | X26: EPP | Y26: 40 | Z26: 880 | AA26: 400 | AD26: 40552 | AE26: Bellen | AF26: East | AG26: Pham | AH26: EPP | AI26: 40 | AJ26: 880 | AK26: 400 | AN26: Pham | AO26: 40 | CD26: EPP Total | CF26: 880 | CG26: 1647
A27: 40597 | B27: Bellen | C27: East | D27: Pham | E27: EPP | F27: 40 | G27: 880 | H27: 400 | I27: =LEFT(B27,3) -> Bel | K27: 40597 | L27: Bellen | M27: East | N27: Pham | O27: EPP | P27: 40 | Q27: 880 | R27: 400 | T27: 40597 | U27: Bellen | V27: East | W27: Pham | X27: EPP | Y27: 40 | Z27: 880 | AA27: 400 | AD27: 40597 | AE27: Bellen | AF27: East | AG27: Pham | AH27: EPP | AI27: 40 | AJ27: 880 | AK27: 400 | AM27: EPP Total | AO27: 47 | CD27: ET | CE27: Carlota | CF27: 1357 | CG27: 1357
A28: 40560 | B28: Quad | C28: MidWest | D28: Chin | E28: EPP | F28: 61 | G28: 1647 | H28: 885 | I28: =LEFT(B28,3) -> Qua | K28: 40560 | L28: Quad | M28: MidWest | N28: Chin | O28: EPP | P28: 61 | Q28: 1647 | R28: 885 | T28: 40560 | U28: Quad | V28: MidWest | W28: Chin | X28: EPP | Y28: 61 | Z28: 1647 | AA28: 885 | AD28: 40560 | AE28: Quad | AF28: MidWest | AG28: Chin | AH28: EPP | AI28: 61 | AJ28: 1647 | AK28: 885 | AM28: ET | AN28: Chin | AO28: 59 | CE28: Sunshine | CF28: 228 | CG28: 228
A29: 40563 | B29: Carlota | C29: East | D29: Chin | E29: ET | F29: 59 | G29: 1357 | H29: 649 | I29: =LEFT(B29,3) -> Car | K29: 40563 | L29: Carlota | M29: East | N29: Chin | O29: ET | P29: 59 | Q29: 1357 | R29: 649 | T29: 40563 | U29: Carlota | V29: East | W29: Chin | X29: ET | Y29: 59 | Z29: 1357 | AA29: 649 | AD29: 40563 | AE29: Carlota | AF29: East | AG29: Chin | AH29: ET | AI29: 59 | AJ29: 1357 | AK29: 649 | AN29: Franks | AO29: 12 | CD29: ET Total | CF29: 228 | CG29: 1357
A30: 40593 | B30: Carlota | C30: East | D30: Chin | E30: ET | F30: 59 | G30: 1357 | H30: 649 | I30: =LEFT(B30,3) -> Car | K30: 40593 | L30: Carlota | M30: East | N30: Chin | O30: ET | P30: 59 | Q30: 1357 | R30: 649 | T30: 40593 | U30: Carlota | V30: East | W30: Chin | X30: ET | Y30: 59 | Z30: 1357 | AA30: 649 | AD30: 40593 | AE30: Carlota | AF30: East | AG30: Chin | AH30: ET | AI30: 59 | AJ30: 1357 | AK30: 649 | AM30: ET Total | AO30: 35.5 | CD30: FM | CE30: Bellen | CF30: 154 | CG30: 154
A31: 40548 | B31: Sunshine | C31: West | D31: Franks | E31: ET | F31: 12 | G31: 228 | H31: 96 | I31: =LEFT(B31,3) -> Sun | K31: 40548 | L31: Sunshine | M31: West | N31: Franks | O31: ET | P31: 12 | Q31: 228 | R31: 96 | T31: 40548 | U31: Sunshine | V31: West | W31: Franks | X31: ET | Y31: 12 | Z31: 228 | AA31: 96 | AD31: 40548 | AE31: Sunshine | AF31: West | AG31: Franks | AH31: ET | AI31: 12 | AJ31: 228 | AK31: 96 | AM31: FM | AN31: Chin | AO31: 40 | CE31: Carlota | CF31: 460 | CG31: 1196
A32: 40593 | B32: Sunshine | C32: West | D32: Franks | E32: ET | F32: 12 | G32: 228 | H32: 96 | I32: =LEFT(B32,3) -> Sun | K32: 40593 | L32: Sunshine | M32: West | N32: Franks | O32: ET | P32: 12 | Q32: 228 | R32: 96 | T32: 40593 | U32: Sunshine | V32: West | W32: Franks | X32: ET | Y32: 12 | Z32: 228 | AA32: 96 | AD32: 40593 | AE32: Sunshine | AF32: West | AG32: Franks | AH32: ET | AI32: 12 | AJ32: 228 | AK32: 96 | AN32: Franks | AO32: 29 | CE32: Quad | CF32: 783 | CG32: 1566
A33: 40553 | B33: Bellen | C33: MidWest | D33: Gault | E33: FM | F33: 7 | G33: 154 | H33: 70 | I33: =LEFT(B33,3) -> Bel | K33: 40553 | L33: Bellen | M33: MidWest | N33: Gault | O33: FM | P33: 7 | Q33: 154 | R33: 70 | T33: 40553 | U33: Bellen | V33: MidWest | W33: Gault | X33: FM | Y33: 7 | Z33: 154 | AA33: 70 | AD33: 40553 | AE33: Bellen | AF33: MidWest | AG33: Gault | AH33: FM | AI33: 7 | AJ33: 154 | AK33: 70 | AN33: Gault | AO33: 7 | CE33: Sunset | CF33: 1302 | CG33: 1302
A34: 40546 | B34: Carlota | C34: MidWest | D34: Chin | E34: FM | F34: 20 | G34: 460 | H34: 220 | I34: =LEFT(B34,3) -> Car | K34: 40546 | L34: Carlota | M34: MidWest | N34: Chin | O34: FM | P34: 20 | Q34: 460 | R34: 220 | T34: 40546 | U34: Carlota | V34: MidWest | W34: Chin | X34: FM | Y34: 20 | Z34: 460 | AA34: 220 | AD34: 40546 | AE34: Carlota | AF34: MidWest | AG34: Chin | AH34: FM | AI34: 20 | AJ34: 460 | AK34: 220 | AN34: Pham | AO34: 38 | CE34: Sunshine | CF34: 722 | CG34: 722
A35: 40591 | B35: Carlota | C35: MidWest | D35: Chin | E35: FM | F35: 20 | G35: 460 | H35: 220 | I35: =LEFT(B35,3) -> Car | K35: 40591 | L35: Carlota | M35: MidWest | N35: Chin | O35: FM | P35: 20 | Q35: 460 | R35: 220 | T35: 40591 | U35: Carlota | V35: MidWest | W35: Chin | X35: FM | Y35: 20 | Z35: 460 | AA35: 220 | AD35: 40591 | AE35: Carlota | AF35: MidWest | AG35: Chin | AH35: FM | AI35: 20 | AJ35: 460 | AK35: 220 | AN35: Smith | AO35: 52 | CD35: FM Total | CF35: 154 | CG35: 1566
A36: 40556 | B36: Carlota | C36: South | D36: Smith | E36: FM | F36: 52 | G36: 1196 | H36: 572 | I36: =LEFT(B36,3) -> Car | K36: 40556 | L36: Carlota | M36: South | N36: Smith | O36: FM | P36: 52 | Q36: 1196 | R36: 572 | T36: 40556 | U36: Carlota | V36: South | W36: Smith | X36: FM | Y36: 52 | Z36: 1196 | AA36: 572 | AD36: 40556 | AE36: Carlota | AF36: South | AG36: Smith | AH36: FM | AI36: 52 | AJ36: 1196 | AK36: 572 | AM36: FM Total | AO36: 35.75 | CD36: FRED | CE36: Bellen | CF36: 5000 | CG36: 5000
A37: 40564 | B37: Quad | C37: East | D37: Chin | E37: FM | F37: 58 | G37: 1566 | H37: 841 | I37: =LEFT(B37,3) -> Qua | K37: 40564 | L37: Quad | M37: East | N37: Chin | O37: FM | P37: 58 | Q37: 1566 | R37: 841 | T37: 40564 | U37: Quad | V37: East | W37: Chin | X37: FM | Y37: 58 | Z37: 1566 | AA37: 841 | AD37: 40564 | AE37: Quad | AF37: East | AG37: Chin | AH37: FM | AI37: 58 | AJ37: 1566 | AK37: 841 | AM37: FRED | AN37: Pham | AO37: 61 | CE37: Sunshine | CF37: 969 | CG37: 969
A38: 40565 | B38: Quad | C38: South | D38: Franks | E38: FM | F38: 29 | G38: 783 | H38: 421 | I38: =LEFT(B38,3) -> Qua | K38: 40565 | L38: Quad | M38: South | N38: Franks | O38: FM | P38: 29 | Q38: 783 | R38: 421 | T38: 40565 | U38: Quad | V38: South | W38: Franks | X38: FM | Y38: 29 | Z38: 783 | AA38: 421 | AD38: 40565 | AE38: Quad | AF38: South | AG38: Franks | AH38: FM | AI38: 29 | AJ38: 783 | AK38: 421 | AN38: Smith | AO38: 51 | CD38: FRED Total | CF38: 969 | CG38: 5000
A39: 40571 | B39: Sunset | C39: West | D39: Chin | E39: FM | F39: 62 | G39: 1302 | H39: 574 | I39: =LEFT(B39,3) -> Sun | K39: 40571 | L39: Sunset | M39: West | N39: Chin | O39: FM | P39: 62 | Q39: 1302 | R39: 574 | T39: 40571 | U39: Sunset | V39: West | W39: Chin | X39: FM | Y39: 62 | Z39: 1302 | AA39: 574 | AD39: 40571 | AE39: Sunset | AF39: West | AG39: Chin | AH39: FM | AI39: 62 | AJ39: 1302 | AK39: 574 | AM39: FRED Total | AO39: 54.333333 | CD39: HHH | CE39: Carlota | CF39: 276 | CG39: 276
A40: 40546 | B40: Sunshine | C40: East | D40: Pham | E40: FM | F40: 38 | G40: 722 | H40: 304 | I40: =LEFT(B40,3) -> Sun | K40: 40546 | L40: Sunshine | M40: East | N40: Pham | O40: FM | P40: 38 | Q40: 722 | R40: 304 | T40: 40546 | U40: Sunshine | V40: East | W40: Pham | X40: FM | Y40: 38 | Z40: 722 | AA40: 304 | AD40: 40546 | AE40: Sunshine | AF40: East | AG40: Pham | AH40: FM | AI40: 38 | AJ40: 722 | AK40: 304 | AM40: HHH | AN40: Franks | AO40: 27.666667 | CE40: Sunset | CF40: 273 | CG40: 273
A41: 40569 | B41: Bellen | C41: West | D41: Pham | E41: FRED | F41: 61 | G41: 5000 | H41: 610 | I41: =LEFT(B41,3) -> Bel | K41: 40569 | L41: Bellen | M41: West | N41: Pham | O41: FRED | P41: 61 | Q41: 5000 | R41: 610 | T41: 40569 | U41: Bellen | V41: West | W41: Pham | X41: FRED | Y41: 61 | Z41: 5000 | AA41: 610 | AD41: 40569 | AE41: Bellen | AF41: West | AG41: Pham | AH41: FRED | AI41: 61 | AJ41: 5000 | AK41: 610 | AN41: Pham | AO41: 13 | CE41: Sunshine | CF41: 1121 | CG41: 1121
A42: 40571 | B42: Sunshine | C42: South | D42: Smith | E42: FRED | F42: 51 | G42: 969 | H42: 408 | I42: =LEFT(B42,3) -> Sun | K42: 40571 | L42: Sunshine | M42: South | N42: Smith | O42: FRED | P42: 51 | Q42: 969 | R42: 408 | T42: 40571 | U42: Sunshine | V42: South | W42: Smith | X42: FRED | Y42: 51 | Z42: 969 | AA42: 408 | AD42: 40571 | AE42: Sunshine | AF42: South | AG42: Smith | AH42: FRED | AI42: 51 | AJ42: 969 | AK42: 408 | AM42: HHH Total | AO42: 24 | CD42: HHH Total | CF42: 273 | CG42: 1121
A43: 40601 | B43: Sunshine | C43: South | D43: Smith | E43: FRED | F43: 51 | G43: 969 | H43: 408 | I43: =LEFT(B43,3) -> Sun | K43: 40601 | L43: Sunshine | M43: South | N43: Smith | O43: FRED | P43: 51 | Q43: 969 | R43: 408 | T43: 40601 | U43: Sunshine | V43: South | W43: Smith | X43: FRED | Y43: 51 | Z43: 969 | AA43: 408 | AD43: 40601 | AE43: Sunshine | AF43: South | AG43: Smith | AH43: FRED | AI43: 51 | AJ43: 969 | AK43: 408 | AM43: HII | AN43: Chin | AO43: 16 | CD43: HII | CE43: Quad | CF43: 432 | CG43: 1701
A44: 40550 | B44: Carlota | C44: MidWest | D44: Franks | E44: HHH | F44: 12 | G44: 276 | H44: 132 | I44: =LEFT(B44,3) -> Car | K44: 40550 | L44: Carlota | M44: MidWest | N44: Franks | O44: HHH | P44: 12 | Q44: 276 | R44: 132 | T44: 40550 | U44: Carlota | V44: MidWest | W44: Franks | X44: HHH | Y44: 12 | Z44: 276 | AA44: 132 | AD44: 40550 | AE44: Carlota | AF44: MidWest | AG44: Franks | AH44: HHH | AI44: 12 | AJ44: 276 | AK44: 132 | AN44: Franks | AO44: 62 | CD44: HII Total | CF44: 432 | CG44: 1701
A45: 40580 | B45: Carlota | C45: MidWest | D45: Franks | E45: HHH | F45: 12 | G45: 276 | H45: 132 | I45: =LEFT(B45,3) -> Car | K45: 40580 | L45: Carlota | M45: MidWest | N45: Franks | O45: HHH | P45: 12 | Q45: 276 | R45: 132 | T45: 40580 | U45: Carlota | V45: MidWest | W45: Franks | X45: HHH | Y45: 12 | Z45: 276 | AA45: 132 | AD45: 40580 | AE45: Carlota | AF45: MidWest | AG45: Franks | AH45: HHH | AI45: 12 | AJ45: 276 | AK45: 132 | AN45: Gault | AO45: 63 | CD45: ITTW | CE45: Carlota | CF45: 1380 | CG45: 1380
A46: 40564 | B46: Sunset | C46: South | D46: Pham | E46: HHH | F46: 13 | G46: 273 | H46: 120 | I46: =LEFT(B46,3) -> Sun | K46: 40564 | L46: Sunset | M46: South | N46: Pham | O46: HHH | P46: 13 | Q46: 273 | R46: 120 | T46: 40564 | U46: Sunset | V46: South | W46: Pham | X46: HHH | Y46: 13 | Z46: 273 | AA46: 120 | AD46: 40564 | AE46: Sunset | AF46: South | AG46: Pham | AH46: HHH | AI46: 13 | AJ46: 273 | AK46: 120 | AM46: HII Total | AO46: 50.75 | CD46: ITTW Total | CF46: 1380 | CG46: 1380
A47: 40560 | B47: Sunshine | C47: MidWest | D47: Franks | E47: HHH | F47: 59 | G47: 1121 | H47: 472 | I47: =LEFT(B47,3) -> Sun | K47: 40560 | L47: Sunshine | M47: MidWest | N47: Franks | O47: HHH | P47: 59 | Q47: 1121 | R47: 472 | T47: 40560 | U47: Sunshine | V47: MidWest | W47: Franks | X47: HHH | Y47: 59 | Z47: 1121 | AA47: 472 | AD47: 40560 | AE47: Sunshine | AF47: MidWest | AG47: Franks | AH47: HHH | AI47: 59 | AJ47: 1121 | AK47: 472 | AM47: ITTW | AN47: Franks | AO47: 60 | CD47: ITW | CE47: Quad | CF47: 378 | CG47: 1512
A48: 40560 | B48: Quad | C48: East | D48: Franks | E48: HII | F48: 62 | G48: 1674 | H48: 899 | I48: =LEFT(B48,3) -> Qua | K48: 40560 | L48: Quad | M48: East | N48: Franks | O48: HII | P48: 62 | Q48: 1674 | R48: 899 | T48: 40560 | U48: Quad | V48: East | W48: Franks | X48: HII | Y48: 62 | Z48: 1674 | AA48: 899 | AD48: 40560 | AE48: Quad | AF48: East | AG48: Franks | AH48: HII | AI48: 62 | AJ48: 1674 | AK48: 899 | AM48: ITTW Total | AO48: 60 | CE48: Sunset | CF48: 399 | CG48: 399
A49: 40590 | B49: Quad | C49: East | D49: Franks | E49: HII | F49: 62 | G49: 1674 | H49: 899 | I49: =LEFT(B49,3) -> Qua | K49: 40590 | L49: Quad | M49: East | N49: Franks | O49: HII | P49: 62 | Q49: 1674 | R49: 899 | T49: 40590 | U49: Quad | V49: East | W49: Franks | X49: HII | Y49: 62 | Z49: 1674 | AA49: 899 | AD49: 40590 | AE49: Quad | AF49: East | AG49: Franks | AH49: HII | AI49: 62 | AJ49: 1674 | AK49: 899 | AM49: ITW | AN49: Franks | AO49: 14 | CD49: ITW Total | CF49: 378 | CG49: 1512
A50: 40551 | B50: Quad | C50: West | D50: Chin | E50: HII | F50: 16 | G50: 432 | H50: 232 | I50: =LEFT(B50,3) -> Qua | K50: 40551 | L50: Quad | M50: West | N50: Chin | O50: HII | P50: 16 | Q50: 432 | R50: 232 | T50: 40551 | U50: Quad | V50: West | W50: Chin | X50: HII | Y50: 16 | Z50: 432 | AA50: 232 | AD50: 40551 | AE50: Quad | AF50: West | AG50: Chin | AH50: HII | AI50: 16 | AJ50: 432 | AK50: 232 | AN50: Gault | AO50: 37.5 | CD50: JAQ | CE50: Carlota | CF50: 782 | CG50: 782
A51: 40567 | B51: Quad | C51: West | D51: Gault | E51: HII | F51: 63 | G51: 1701 | H51: 914 | I51: =LEFT(B51,3) -> Qua | K51: 40567 | L51: Quad | M51: West | N51: Gault | O51: HII | P51: 63 | Q51: 1701 | R51: 914 | T51: 40567 | U51: Quad | V51: West | W51: Gault | X51: HII | Y51: 63 | Z51: 1701 | AA51: 914 | AD51: 40567 | AE51: Quad | AF51: West | AG51: Gault | AH51: HII | AI51: 63 | AJ51: 1701 | AK51: 914 | AM51: ITW Total | AO51: 25.75 | CE51: Sunshine | CF51: 399 | CG51: 399
A52: 40548 | B52: Carlota | C52: West | D52: Franks | E52: ITTW | F52: 60 | G52: 1380 | H52: 660 | I52: =LEFT(B52,3) -> Car | K52: 40548 | L52: Carlota | M52: West | N52: Franks | O52: ITTW | P52: 60 | Q52: 1380 | R52: 660 | T52: 40548 | U52: Carlota | V52: West | W52: Franks | X52: ITTW | Y52: 60 | Z52: 1380 | AA52: 660 | AD52: 40548 | AE52: Carlota | AF52: West | AG52: Franks | AH52: ITTW | AI52: 60 | AJ52: 1380 | AK52: 660 | AM52: JAQ | AN52: Franks | AO52: 27.5 | CD52: JAQ Total | CF52: 399 | CG52: 782
A53: 40578 | B53: Carlota | C53: West | D53: Franks | E53: ITTW | F53: 60 | G53: 1380 | H53: 660 | I53: =LEFT(B53,3) -> Car | K53: 40578 | L53: Carlota | M53: West | N53: Franks | O53: ITTW | P53: 60 | Q53: 1380 | R53: 660 | T53: 40578 | U53: Carlota | V53: West | W53: Franks | X53: ITTW | Y53: 60 | Z53: 1380 | AA53: 660 | AD53: 40578 | AE53: Carlota | AF53: West | AG53: Franks | AH53: ITTW | AI53: 60 | AJ53: 1380 | AK53: 660 | AM53: JAQ Total | AO53: 27.5 | CD53: KBTB | CE53: Bellen | CF53: 528 | CG53: 528
A54: 40554 | B54: Quad | C54: East | D54: Franks | E54: ITW | F54: 14 | G54: 378 | H54: 203 | I54: =LEFT(B54,3) -> Qua | K54: 40554 | L54: Quad | M54: East | N54: Franks | O54: ITW | P54: 14 | Q54: 378 | R54: 203 | T54: 40554 | U54: Quad | V54: East | W54: Franks | X54: ITW | Y54: 14 | Z54: 378 | AA54: 203 | AD54: 40554 | AE54: Quad | AF54: East | AG54: Franks | AH54: ITW | AI54: 14 | AJ54: 378 | AK54: 203 | AM54: KBTB | AN54: Gault | AO54: 40 | CE54: Carlota | CF54: 667 | CG54: 667
A55: 40599 | B55: Quad | C55: East | D55: Franks | E55: ITW | F55: 14 | G55: 378 | H55: 203 | I55: =LEFT(B55,3) -> Qua | K55: 40599 | L55: Quad | M55: East | N55: Franks | O55: ITW | P55: 14 | Q55: 378 | R55: 203 | T55: 40599 | U55: Quad | V55: East | W55: Franks | X55: ITW | Y55: 14 | Z55: 378 | AA55: 203 | AD55: 40599 | AE55: Quad | AF55: East | AG55: Franks | AH55: ITW | AI55: 14 | AJ55: 378 | AK55: 203 | AN55: Smith | AO55: 47 | CE55: Quad | CF55: 1512 | CG55: 1755
A56: 40564 | B56: Quad | C56: West | D56: Gault | E56: ITW | F56: 56 | G56: 1512 | H56: 812 | I56: =LEFT(B56,3) -> Qua | K56: 40564 | L56: Quad | M56: West | N56: Gault | O56: ITW | P56: 56 | Q56: 1512 | R56: 812 | T56: 40564 | U56: Quad | V56: West | W56: Gault | X56: ITW | Y56: 56 | Z56: 1512 | AA56: 812 | AD56: 40564 | AE56: Quad | AF56: West | AG56: Gault | AH56: ITW | AI56: 56 | AJ56: 1512 | AK56: 812 | AM56: KBTB Total | AO56: 42.333333 | CD56: KBTB Total | CF56: 528 | CG56: 1755
A57: 40555 | B57: Sunset | C57: MidWest | D57: Gault | E57: ITW | F57: 19 | G57: 399 | H57: 176 | I57: =LEFT(B57,3) -> Sun | K57: 40555 | L57: Sunset | M57: MidWest | N57: Gault | O57: ITW | P57: 19 | Q57: 399 | R57: 176 | T57: 40555 | U57: Sunset | V57: MidWest | W57: Gault | X57: ITW | Y57: 19 | Z57: 399 | AA57: 176 | AD57: 40555 | AE57: Sunset | AF57: MidWest | AG57: Gault | AH57: ITW | AI57: 19 | AJ57: 399 | AK57: 176 | AM57: KPSA | AN57: Chin | AO57: 17 | CD57: KPSA | CE57: Bellen | CF57: 374 | CG57: 374
A58: 40557 | B58: Carlota | C58: East | D58: Franks | E58: JAQ | F58: 34 | G58: 782 | H58: 374 | I58: =LEFT(B58,3) -> Car | K58: 40557 | L58: Carlota | M58: East | N58: Franks | O58: JAQ | P58: 34 | Q58: 782 | R58: 374 | T58: 40557 | U58: Carlota | V58: East | W58: Franks | X58: JAQ | Y58: 34 | Z58: 782 | AA58: 374 | AD58: 40557 | AE58: Carlota | AF58: East | AG58: Franks | AH58: JAQ | AI58: 34 | AJ58: 782 | AK58: 374 | AN58: Sioux | AO58: 18 | CE58: Carlota | CF58: 414 | CG58: 414
A59: 40568 | B59: Sunshine | C59: MidWest | D59: Franks | E59: JAQ | F59: 21 | G59: 399 | H59: 168 | I59: =LEFT(B59,3) -> Sun | K59: 40568 | L59: Sunshine | M59: MidWest | N59: Franks | O59: JAQ | P59: 21 | Q59: 399 | R59: 168 | T59: 40568 | U59: Sunshine | V59: MidWest | W59: Franks | X59: JAQ | Y59: 21 | Z59: 399 | AA59: 168 | AD59: 40568 | AE59: Sunshine | AF59: MidWest | AG59: Franks | AH59: JAQ | AI59: 21 | AJ59: 399 | AK59: 168 | AM59: KPSA Total | AO59: 17.5 | CD59: KPSA Total | CF59: 374 | CG59: 414
A60: 40545 | B60: Bellen | C60: South | D60: Gault | E60: KBTB | F60: 24 | G60: 528 | H60: 240 | I60: =LEFT(B60,3) -> Bel | K60: 40545 | L60: Bellen | M60: South | N60: Gault | O60: KBTB | P60: 24 | Q60: 528 | R60: 240 | T60: 40545 | U60: Bellen | V60: South | W60: Gault | X60: KBTB | Y60: 24 | Z60: 528 | AA60: 240 | AD60: 40545 | AE60: Bellen | AF60: South | AG60: Gault | AH60: KBTB | AI60: 24 | AJ60: 528 | AK60: 240 | AM60: LOP | AN60: Smith | AO60: 15 | CD60: LOP | CE60: Carlota | CF60: 345 | CG60: 345
A61: 40590 | B61: Bellen | C61: South | D61: Gault | E61: KBTB | F61: 24 | G61: 528 | H61: 240 | I61: =LEFT(B61,3) -> Bel | K61: 40590 | L61: Bellen | M61: South | N61: Gault | O61: KBTB | P61: 24 | Q61: 528 | R61: 240 | T61: 40590 | U61: Bellen | V61: South | W61: Gault | X61: KBTB | Y61: 24 | Z61: 528 | AA61: 240 | AD61: 40590 | AE61: Bellen | AF61: South | AG61: Gault | AH61: KBTB | AI61: 24 | AJ61: 528 | AK61: 240 | AM61: LOP Total | AO61: 15 | CD61: LOP Total | CF61: 345 | CG61: 345
A62: 40565 | B62: Carlota | C62: South | D62: Smith | E62: KBTB | F62: 29 | G62: 667 | H62: 319 | I62: =LEFT(B62,3) -> Car | K62: 40565 | L62: Carlota | M62: South | N62: Smith | O62: KBTB | P62: 29 | Q62: 667 | R62: 319 | T62: 40565 | U62: Carlota | V62: South | W62: Smith | X62: KBTB | Y62: 29 | Z62: 667 | AA62: 319 | AD62: 40565 | AE62: Carlota | AF62: South | AG62: Smith | AH62: KBTB | AI62: 29 | AJ62: 667 | AK62: 319 | AM62: MBG | AN62: Sioux | AO62: 47 | CD62: MBG | CE62: Sunset | CF62: 357 | CG62: 987
A63: 40571 | B63: Quad | C63: South | D63: Gault | E63: KBTB | F63: 56 | G63: 1512 | H63: 812 | I63: =LEFT(B63,3) -> Qua | K63: 40571 | L63: Quad | M63: South | N63: Gault | O63: KBTB | P63: 56 | Q63: 1512 | R63: 812 | T63: 40571 | U63: Quad | V63: South | W63: Gault | X63: KBTB | Y63: 56 | Z63: 1512 | AA63: 812 | AD63: 40571 | AE63: Quad | AF63: South | AG63: Gault | AH63: KBTB | AI63: 56 | AJ63: 1512 | AK63: 812 | AN63: Smith | AO63: 17 | CD63: MBG Total | CF63: 357 | CG63: 987
A64: 40616 | B64: Quad | C64: South | D64: Gault | E64: KBTB | F64: 56 | G64: 1512 | H64: 812 | I64: =LEFT(B64,3) -> Qua | K64: 40616 | L64: Quad | M64: South | N64: Gault | O64: KBTB | P64: 56 | Q64: 1512 | R64: 812 | T64: 40616 | U64: Quad | V64: South | W64: Gault | X64: KBTB | Y64: 56 | Z64: 1512 | AA64: 812 | AD64: 40616 | AE64: Quad | AF64: South | AG64: Gault | AH64: KBTB | AI64: 56 | AJ64: 1512 | AK64: 812 | AM64: MBG Total | AO64: 37 | CD64: MNGD | CE64: Carlota | CF64: 1058 | CG64: 1058
A65: 40553 | B65: Quad | C65: West | D65: Smith | E65: KBTB | F65: 65 | G65: 1755 | H65: 943 | I65: =LEFT(B65,3) -> Qua | K65: 40553 | L65: Quad | M65: West | N65: Smith | O65: KBTB | P65: 65 | Q65: 1755 | R65: 943 | T65: 40553 | U65: Quad | V65: West | W65: Smith | X65: KBTB | Y65: 65 | Z65: 1755 | AA65: 943 | AD65: 40553 | AE65: Quad | AF65: West | AG65: Smith | AH65: KBTB | AI65: 65 | AJ65: 1755 | AK65: 943 | AM65: MNGD | AN65: Franks | AO65: 46 | CE65: Sunset | CF65: 252 | CG65: 252
A66: 40569 | B66: Bellen | C66: East | D66: Chin | E66: KPSA | F66: 17 | G66: 374 | H66: 170 | I66: =LEFT(B66,3) -> Bel | K66: 40569 | L66: Bellen | M66: East | N66: Chin | O66: KPSA | P66: 17 | Q66: 374 | R66: 170 | T66: 40569 | U66: Bellen | V66: East | W66: Chin | X66: KPSA | Y66: 17 | Z66: 374 | AA66: 170 | AD66: 40569 | AE66: Bellen | AF66: East | AG66: Chin | AH66: KPSA | AI66: 17 | AJ66: 374 | AK66: 170 | AN66: Gault | AO66: 12 | CD66: MNGD Total | CF66: 252 | CG66: 1058
A67: 40549 | B67: Carlota | C67: West | D67: Sioux | E67: KPSA | F67: 18 | G67: 414 | H67: 198 | I67: =LEFT(B67,3) -> Car | K67: 40549 | L67: Carlota | M67: West | N67: Sioux | O67: KPSA | P67: 18 | Q67: 414 | R67: 198 | T67: 40549 | U67: Carlota | V67: West | W67: Sioux | X67: KPSA | Y67: 18 | Z67: 414 | AA67: 198 | AD67: 40549 | AE67: Carlota | AF67: West | AG67: Sioux | AH67: KPSA | AI67: 18 | AJ67: 414 | AK67: 198 | AM67: MNGD Total | AO67: 29 | CD67: PCC | CE67: Bellen | CF67: 352 | CG67: 352
A68: 40571 | B68: Carlota | C68: West | D68: Smith | E68: LOP | F68: 15 | G68: 345 | H68: 165 | I68: =LEFT(B68,3) -> Car | K68: 40571 | L68: Carlota | M68: West | N68: Smith | O68: LOP | P68: 15 | Q68: 345 | R68: 165 | T68: 40571 | U68: Carlota | V68: West | W68: Smith | X68: LOP | Y68: 15 | Z68: 345 | AA68: 165 | AD68: 40571 | AE68: Carlota | AF68: West | AG68: Smith | AH68: LOP | AI68: 15 | AJ68: 345 | AK68: 165 | AM68: PCC | AN68: Chin | AO68: 36 | CE68: Carlota | CF68: 897 | CG68: 897
A69: 40553 | B69: Sunset | C69: East | D69: Smith | E69: MBG | F69: 17 | G69: 357 | H69: 157 | I69: =LEFT(B69,3) -> Sun | K69: 40553 | L69: Sunset | M69: East | N69: Smith | O69: MBG | P69: 17 | Q69: 357 | R69: 157 | T69: 40553 | U69: Sunset | V69: East | W69: Smith | X69: MBG | Y69: 17 | Z69: 357 | AA69: 157 | AD69: 40553 | AE69: Sunset | AF69: East | AG69: Smith | AH69: MBG | AI69: 17 | AJ69: 357 | AK69: 157 | AN69: Franks | AO69: 44 | CE69: Quad | CF69: 270 | CG69: 1728
A70: 40553 | B70: Sunset | C70: South | D70: Sioux | E70: MBG | F70: 47 | G70: 987 | H70: 435 | I70: =LEFT(B70,3) -> Sun | K70: 40553 | L70: Sunset | M70: South | N70: Sioux | O70: MBG | P70: 47 | Q70: 987 | R70: 435 | T70: 40553 | U70: Sunset | V70: South | W70: Sioux | X70: MBG | Y70: 47 | Z70: 987 | AA70: 435 | AD70: 40553 | AE70: Sunset | AF70: South | AG70: Sioux | AH70: MBG | AI70: 47 | AJ70: 987 | AK70: 435 | AN70: Sioux | AO70: 29.333333 | CE70: Sunset | CF70: 462 | CG70: 462
A71: 40598 | B71: Sunset | C71: South | D71: Sioux | E71: MBG | F71: 47 | G71: 987 | H71: 435 | I71: =LEFT(B71,3) -> Sun | K71: 40598 | L71: Sunset | M71: South | N71: Sioux | O71: MBG | P71: 47 | Q71: 987 | R71: 435 | T71: 40598 | U71: Sunset | V71: South | W71: Sioux | X71: MBG | Y71: 47 | Z71: 987 | AA71: 435 | AD71: 40598 | AE71: Sunset | AF71: South | AG71: Sioux | AH71: MBG | AI71: 47 | AJ71: 987 | AK71: 435 | AN71: Smith | AO71: 29 | CE71: Sunshine | CF71: 114 | CG71: 1178
A72: 40571 | B72: Carlota | C72: South | D72: Franks | E72: MNGD | F72: 46 | G72: 1058 | H72: 506 | I72: =LEFT(B72,3) -> Car | K72: 40571 | L72: Carlota | M72: South | N72: Franks | O72: MNGD | P72: 46 | Q72: 1058 | R72: 506 | T72: 40571 | U72: Carlota | V72: South | W72: Franks | X72: MNGD | Y72: 46 | Z72: 1058 | AA72: 506 | AD72: 40571 | AE72: Carlota | AF72: South | AG72: Franks | AH72: MNGD | AI72: 46 | AJ72: 1058 | AK72: 506 | AM72: PCC Total | AO72: 32.461538 | CD72: PCC Total | CF72: 114 | CG72: 1728
A73: 40561 | B73: Sunset | C73: East | D73: Gault | E73: MNGD | F73: 12 | G73: 252 | H73: 111 | I73: =LEFT(B73,3) -> Sun | K73: 40561 | L73: Sunset | M73: East | N73: Gault | O73: MNGD | P73: 12 | Q73: 252 | R73: 111 | T73: 40561 | U73: Sunset | V73: East | W73: Gault | X73: MNGD | Y73: 12 | Z73: 252 | AA73: 111 | AD73: 40561 | AE73: Sunset | AF73: East | AG73: Gault | AH73: MNGD | AI73: 12 | AJ73: 252 | AK73: 111 | AM73: PLOT | AN73: Gault | AO73: 10 | CD73: PLOT | CE73: Bellen | CF73: 1254 | CG73: 1254
A74: 40560 | B74: Bellen | C74: MidWest | D74: Smith | E74: PCC | F74: 16 | G74: 352 | H74: 160 | I74: =LEFT(B74,3) -> Bel | K74: 40560 | L74: Bellen | M74: MidWest | N74: Smith | O74: PCC | P74: 16 | Q74: 352 | R74: 160 | T74: 40560 | U74: Bellen | V74: MidWest | W74: Smith | X74: PCC | Y74: 16 | Z74: 352 | AA74: 160 | AD74: 40560 | AE74: Bellen | AF74: MidWest | AG74: Smith | AH74: PCC | AI74: 16 | AJ74: 352 | AK74: 160 | AN74: Pham | AO74: 57 | CE74: Quad | CF74: 270 | CG74: 459
A75: 40560 | B75: Carlota | C75: East | D75: Sioux | E75: PCC | F75: 39 | G75: 897 | H75: 429 | I75: =LEFT(B75,3) -> Car | K75: 40560 | L75: Carlota | M75: East | N75: Sioux | O75: PCC | P75: 39 | Q75: 897 | R75: 429 | T75: 40560 | U75: Carlota | V75: East | W75: Sioux | X75: PCC | Y75: 39 | Z75: 897 | AA75: 429 | AD75: 40560 | AE75: Carlota | AF75: East | AG75: Sioux | AH75: PCC | AI75: 39 | AJ75: 897 | AK75: 429 | AN75: Smith | AO75: 17 | CD75: PLOT Total | CF75: 270 | CG75: 1254
A76: 40605 | B76: Carlota | C76: East | D76: Sioux | E76: PCC | F76: 39 | G76: 897 | H76: 429 | I76: =LEFT(B76,3) -> Car | K76: 40605 | L76: Carlota | M76: East | N76: Sioux | O76: PCC | P76: 39 | Q76: 897 | R76: 429 | T76: 40605 | U76: Carlota | V76: East | W76: Sioux | X76: PCC | Y76: 39 | Z76: 897 | AA76: 429 | AD76: 40605 | AE76: Carlota | AF76: East | AG76: Sioux | AH76: PCC | AI76: 39 | AJ76: 897 | AK76: 429 | AM76: PLOT Total | AO76: 28 | CD76: PSA | CE76: Bellen | CF76: 220 | CG76: 880
A77: 40566 | B77: Quad | C77: East | D77: Franks | E77: PCC | F77: 44 | G77: 1188 | H77: 638 | I77: =LEFT(B77,3) -> Qua | K77: 40566 | L77: Quad | M77: East | N77: Franks | O77: PCC | P77: 44 | Q77: 1188 | R77: 638 | T77: 40566 | U77: Quad | V77: East | W77: Franks | X77: PCC | Y77: 44 | Z77: 1188 | AA77: 638 | AD77: 40566 | AE77: Quad | AF77: East | AG77: Franks | AH77: PCC | AI77: 44 | AJ77: 1188 | AK77: 638 | AM77: PSA | AN77: Franks | AO77: 54 | CE77: Sunshine | CF77: 627 | CG77: 1026
A78: 40560 | B78: Quad | C78: West | D78: Chin | E78: PCC | F78: 10 | G78: 270 | H78: 145 | I78: =LEFT(B78,3) -> Qua | K78: 40560 | L78: Quad | M78: West | N78: Chin | O78: PCC | P78: 10 | Q78: 270 | R78: 145 | T78: 40560 | U78: Quad | V78: West | W78: Chin | X78: PCC | Y78: 10 | Z78: 270 | AA78: 145 | AD78: 40560 | AE78: Quad | AF78: West | AG78: Chin | AH78: PCC | AI78: 10 | AJ78: 270 | AK78: 145 | AN78: Gault | AO78: 17.333333 | CD78: PSA Total | CF78: 220 | CG78: 1026
A79: 40605 | B79: Quad | C79: West | D79: Chin | E79: PCC | F79: 10 | G79: 270 | H79: 145 | I79: =LEFT(B79,3) -> Qua | K79: 40605 | L79: Quad | M79: West | N79: Chin | O79: PCC | P79: 10 | Q79: 270 | R79: 145 | T79: 40605 | U79: Quad | V79: West | W79: Chin | X79: PCC | Y79: 10 | Z79: 270 | AA79: 145 | AD79: 40605 | AE79: Quad | AF79: West | AG79: Chin | AH79: PCC | AI79: 10 | AJ79: 270 | AK79: 145 | AN79: Pham | AO79: 36.5 | CD79: QT | CE79: Bellen | CF79: 330 | CG79: 550
A80: 40549 | B80: Quad | C80: West | D80: Sioux | E80: PCC | F80: 64 | G80: 1728 | H80: 928 | I80: =LEFT(B80,3) -> Qua | K80: 40549 | L80: Quad | M80: West | N80: Sioux | O80: PCC | P80: 64 | Q80: 1728 | R80: 928 | T80: 40549 | U80: Quad | V80: West | W80: Sioux | X80: PCC | Y80: 64 | Z80: 1728 | AA80: 928 | AD80: 40549 | AE80: Quad | AF80: West | AG80: Sioux | AH80: PCC | AI80: 64 | AJ80: 1728 | AK80: 928 | AM80: PSA Total | AO80: 29.833333 | CE80: Carlota | CF80: 230 | CG80: 713
A81: 40550 | B81: Sunset | C81: MidWest | D81: Sioux | E81: PCC | F81: 22 | G81: 462 | H81: 204 | I81: =LEFT(B81,3) -> Sun | K81: 40550 | L81: Sunset | M81: MidWest | N81: Sioux | O81: PCC | P81: 22 | Q81: 462 | R81: 204 | T81: 40550 | U81: Sunset | V81: MidWest | W81: Sioux | X81: PCC | Y81: 22 | Z81: 462 | AA81: 204 | AD81: 40550 | AE81: Sunset | AF81: MidWest | AG81: Sioux | AH81: PCC | AI81: 22 | AJ81: 462 | AK81: 204 | AM81: QT | AN81: Gault | AO81: 10 | CE81: Sunshine | CF81: 760 | CG81: 1216
A82: 40552 | B82: Sunshine | C82: East | D82: Smith | E82: PCC | F82: 42 | G82: 798 | H82: 336 | I82: =LEFT(B82,3) -> Sun | K82: 40552 | L82: Sunshine | M82: East | N82: Smith | O82: PCC | P82: 42 | Q82: 798 | R82: 336 | T82: 40552 | U82: Sunshine | V82: East | W82: Smith | X82: PCC | Y82: 42 | Z82: 798 | AA82: 336 | AD82: 40552 | AE82: Sunshine | AF82: East | AG82: Smith | AH82: PCC | AI82: 42 | AJ82: 798 | AK82: 336 | AN82: Sioux | AO82: 21.666667 | CD82: QT Total | CF82: 230 | CG82: 1216
A83: 40561 | B83: Sunshine | C83: MidWest | D83: Chin | E83: PCC | F83: 62 | G83: 1178 | H83: 496 | I83: =LEFT(B83,3) -> Sun | K83: 40561 | L83: Sunshine | M83: MidWest | N83: Chin | O83: PCC | P83: 62 | Q83: 1178 | R83: 496 | T83: 40561 | U83: Sunshine | V83: MidWest | W83: Chin | X83: PCC | Y83: 62 | Z83: 1178 | AA83: 496 | AD83: 40561 | AE83: Sunshine | AF83: MidWest | AG83: Chin | AH83: PCC | AI83: 62 | AJ83: 1178 | AK83: 496 | AN83: Smith | AO83: 45 | CD83: SFWK | CE83: Bellen | CF83: 418 | CG83: 418
A84: 40606 | B84: Sunshine | C84: MidWest | D84: Chin | E84: PCC | F84: 62 | G84: 1178 | H84: 496 | I84: =LEFT(B84,3) -> Sun | K84: 40606 | L84: Sunshine | M84: MidWest | N84: Chin | O84: PCC | P84: 62 | Q84: 1178 | R84: 496 | T84: 40606 | U84: Sunshine | V84: MidWest | W84: Chin | X84: PCC | Y84: 62 | Z84: 1178 | AA84: 496 | AD84: 40606 | AE84: Sunshine | AF84: MidWest | AG84: Chin | AH84: PCC | AI84: 62 | AJ84: 1178 | AK84: 496 | AM84: QT Total | AO84: 30 | CE84: Quad | CF84: 1161 | CG84: 1161
A85: 40546 | B85: Sunshine | C85: South | D85: Sioux | E85: PCC | F85: 6 | G85: 114 | H85: 48 | I85: =LEFT(B85,3) -> Sun | K85: 40546 | L85: Sunshine | M85: South | N85: Sioux | O85: PCC | P85: 6 | Q85: 114 | R85: 48 | T85: 40546 | U85: Sunshine | V85: South | W85: Sioux | X85: PCC | Y85: 6 | Z85: 114 | AA85: 48 | AD85: 40546 | AE85: Sunshine | AF85: South | AG85: Sioux | AH85: PCC | AI85: 6 | AJ85: 114 | AK85: 48 | AM85: SFWK | AN85: Gault | AO85: 43 | CD85: SFWK Total | CF85: 418 | CG85: 1161
A86: 40576 | B86: Sunshine | C86: South | D86: Sioux | E86: PCC | F86: 6 | G86: 114 | H86: 48 | I86: =LEFT(B86,3) -> Sun | K86: 40576 | L86: Sunshine | M86: South | N86: Sioux | O86: PCC | P86: 6 | Q86: 114 | R86: 48 | T86: 40576 | U86: Sunshine | V86: South | W86: Sioux | X86: PCC | Y86: 6 | Z86: 114 | AA86: 48 | AD86: 40576 | AE86: Sunshine | AF86: South | AG86: Sioux | AH86: PCC | AI86: 6 | AJ86: 114 | AK86: 48 | AN86: Pham | AO86: 19 | CD86: T | CE86: Bellen | CF86: 594 | CG86: 770
A87: 40556 | B87: Bellen | C87: MidWest | D87: Pham | E87: PLOT | F87: 57 | G87: 1254 | H87: 570 | I87: =LEFT(B87,3) -> Bel | K87: 40556 | L87: Bellen | M87: MidWest | N87: Pham | O87: PLOT | P87: 57 | Q87: 1254 | R87: 570 | T87: 40556 | U87: Bellen | V87: MidWest | W87: Pham | X87: PLOT | Y87: 57 | Z87: 1254 | AA87: 570 | AD87: 40556 | AE87: Bellen | AF87: MidWest | AG87: Pham | AH87: PLOT | AI87: 57 | AJ87: 1254 | AK87: 570 | AM87: SFWK Total | AO87: 35 | CE87: Sunset | CF87: 1281 | CG87: 1281
A88: 40572 | B88: Quad | C88: MidWest | D88: Gault | E88: PLOT | F88: 10 | G88: 270 | H88: 145 | I88: =LEFT(B88,3) -> Qua | K88: 40572 | L88: Quad | M88: MidWest | N88: Gault | O88: PLOT | P88: 10 | Q88: 270 | R88: 145 | T88: 40572 | U88: Quad | V88: MidWest | W88: Gault | X88: PLOT | Y88: 10 | Z88: 270 | AA88: 145 | AD88: 40572 | AE88: Quad | AF88: MidWest | AG88: Gault | AH88: PLOT | AI88: 10 | AJ88: 270 | AK88: 145 | AM88: T | AN88: Chin | AO88: 49 | CE88: Sunshine | CF88: 931 | CG88: 931
A89: 40561 | B89: Quad | C89: MidWest | D89: Smith | E89: PLOT | F89: 17 | G89: 459 | H89: 247 | I89: =LEFT(B89,3) -> Qua | K89: 40561 | L89: Quad | M89: MidWest | N89: Smith | O89: PLOT | P89: 17 | Q89: 459 | R89: 247 | T89: 40561 | U89: Quad | V89: MidWest | W89: Smith | X89: PLOT | Y89: 17 | Z89: 459 | AA89: 247 | AD89: 40561 | AE89: Quad | AF89: MidWest | AG89: Smith | AH89: PLOT | AI89: 17 | AJ89: 459 | AK89: 247 | AN89: Pham | AO89: 61 | CD89: T Total | CF89: 594 | CG89: 1281
A90: 40563 | B90: Bellen | C90: East | D90: Gault | E90: PSA | F90: 10 | G90: 220 | H90: 100 | I90: =LEFT(B90,3) -> Bel | K90: 40563 | L90: Bellen | M90: East | N90: Gault | O90: PSA | P90: 10 | Q90: 220 | R90: 100 | T90: 40563 | U90: Bellen | V90: East | W90: Gault | X90: PSA | Y90: 10 | Z90: 220 | AA90: 100 | AD90: 40563 | AE90: Bellen | AF90: East | AG90: Gault | AH90: PSA | AI90: 10 | AJ90: 220 | AK90: 100 | AN90: Sioux | AO90: 35 | CD90: TRU | CE90: Bellen | CF90: 242 | CG90: 242
A91: 40569 | B91: Bellen | C91: MidWest | D91: Gault | E91: PSA | F91: 21 | G91: 462 | H91: 210 | I91: =LEFT(B91,3) -> Bel | K91: 40569 | L91: Bellen | M91: MidWest | N91: Gault | O91: PSA | P91: 21 | Q91: 462 | R91: 210 | T91: 40569 | U91: Bellen | V91: MidWest | W91: Gault | X91: PSA | Y91: 21 | Z91: 462 | AA91: 210 | AD91: 40569 | AE91: Bellen | AF91: MidWest | AG91: Gault | AH91: PSA | AI91: 21 | AJ91: 462 | AK91: 210 | AN91: Smith | AO91: 27 | CE91: Sunset | CF91: 567 | CG91: 567
A92: 40599 | B92: Bellen | C92: MidWest | D92: Gault | E92: PSA | F92: 21 | G92: 462 | H92: 210 | I92: =LEFT(B92,3) -> Bel | K92: 40599 | L92: Bellen | M92: MidWest | N92: Gault | O92: PSA | P92: 21 | Q92: 462 | R92: 210 | T92: 40599 | U92: Bellen | V92: MidWest | W92: Gault | X92: PSA | Y92: 21 | Z92: 462 | AA92: 210 | AD92: 40599 | AE92: Bellen | AF92: MidWest | AG92: Gault | AH92: PSA | AI92: 21 | AJ92: 462 | AK92: 210 | AM92: T Total | AO92: 46.6 | CE92: Sunshine | CF92: 570 | CG92: 570
A93: 40556 | B93: Bellen | C93: MidWest | D93: Pham | E93: PSA | F93: 40 | G93: 880 | H93: 400 | I93: =LEFT(B93,3) -> Bel | K93: 40556 | L93: Bellen | M93: MidWest | N93: Pham | O93: PSA | P93: 40 | Q93: 880 | R93: 400 | T93: 40556 | U93: Bellen | V93: MidWest | W93: Pham | X93: PSA | Y93: 40 | Z93: 880 | AA93: 400 | AD93: 40556 | AE93: Bellen | AF93: MidWest | AG93: Pham | AH93: PSA | AI93: 40 | AJ93: 880 | AK93: 400 | AM93: TRU | AN93: Chin | AO93: 30 | CD93: TRU Total | CF93: 242 | CG93: 570
A94: 40549 | B94: Sunshine | C94: East | D94: Franks | E94: PSA | F94: 54 | G94: 1026 | H94: 432 | I94: =LEFT(B94,3) -> Sun | K94: 40549 | L94: Sunshine | M94: East | N94: Franks | O94: PSA | P94: 54 | Q94: 1026 | R94: 432 | T94: 40549 | U94: Sunshine | V94: East | W94: Franks | X94: PSA | Y94: 54 | Z94: 1026 | AA94: 432 | AD94: 40549 | AE94: Sunshine | AF94: East | AG94: Franks | AH94: PSA | AI94: 54 | AJ94: 1026 | AK94: 432 | AN94: Gault | AO94: 27 | CD94: TTT | CE94: Quad | CF94: 675 | CG94: 675
A95: 40556 | B95: Sunshine | C95: MidWest | D95: Pham | E95: PSA | F95: 33 | G95: 627 | H95: 264 | I95: =LEFT(B95,3) -> Sun | K95: 40556 | L95: Sunshine | M95: MidWest | N95: Pham | O95: PSA | P95: 33 | Q95: 627 | R95: 264 | T95: 40556 | U95: Sunshine | V95: MidWest | W95: Pham | X95: PSA | Y95: 33 | Z95: 627 | AA95: 264 | AD95: 40556 | AE95: Sunshine | AF95: MidWest | AG95: Pham | AH95: PSA | AI95: 33 | AJ95: 627 | AK95: 264 | AN95: Smith | AO95: 11 | CE95: Sunset | CF95: 1197 | CG95: 1197
A96: 40552 | B96: Bellen | C96: South | D96: Sioux | E96: QT | F96: 15 | G96: 330 | H96: 150 | I96: =LEFT(B96,3) -> Bel | K96: 40552 | L96: Bellen | M96: South | N96: Sioux | O96: QT | P96: 15 | Q96: 330 | R96: 150 | T96: 40552 | U96: Bellen | V96: South | W96: Sioux | X96: QT | Y96: 15 | Z96: 330 | AA96: 150 | AD96: 40552 | AE96: Bellen | AF96: South | AG96: Sioux | AH96: QT | AI96: 15 | AJ96: 330 | AK96: 150 | AM96: TRU Total | AO96: 22.666667 | CE96: Sunshine | CF96: 152 | CG96: 437
A97: 40571 | B97: Bellen | C97: South | D97: Sioux | E97: QT | F97: 25 | G97: 550 | H97: 250 | I97: =LEFT(B97,3) -> Bel | K97: 40571 | L97: Bellen | M97: South | N97: Sioux | O97: QT | P97: 25 | Q97: 550 | R97: 250 | T97: 40571 | U97: Bellen | V97: South | W97: Sioux | X97: QT | Y97: 25 | Z97: 550 | AA97: 250 | AD97: 40571 | AE97: Bellen | AF97: South | AG97: Sioux | AH97: QT | AI97: 25 | AJ97: 550 | AK97: 250 | AM97: TTT | AN97: Pham | AO97: 57 | CD97: TTT Total | CF97: 152 | CG97: 1197
A98: 40616 | B98: Bellen | C98: South | D98: Sioux | E98: QT | F98: 25 | G98: 550 | H98: 250 | I98: =LEFT(B98,3) -> Bel | K98: 40616 | L98: Bellen | M98: South | N98: Sioux | O98: QT | P98: 25 | Q98: 550 | R98: 250 | T98: 40616 | U98: Bellen | V98: South | W98: Sioux | X98: QT | Y98: 25 | Z98: 550 | AA98: 250 | AD98: 40616 | AE98: Bellen | AF98: South | AG98: Sioux | AH98: QT | AI98: 25 | AJ98: 550 | AK98: 250 | AN98: Sioux | AO98: 24 | CD98: WSD | CE98: Bellen | CF98: 572 | CG98: 572
A99: 40559 | B99: Carlota | C99: South | D99: Smith | E99: QT | F99: 31 | G99: 713 | H99: 341 | I99: =LEFT(B99,3) -> Car | K99: 40559 | L99: Carlota | M99: South | N99: Smith | O99: QT | P99: 31 | Q99: 713 | R99: 341 | T99: 40559 | U99: Carlota | V99: South | W99: Smith | X99: QT | Y99: 31 | Z99: 713 | AA99: 341 | AD99: 40559 | AE99: Carlota | AF99: South | AG99: Smith | AH99: QT | AI99: 31 | AJ99: 713 | AK99: 341 | AN99: Smith | AO99: 8 | CE99: Carlota | CF99: 874 | CG99: 874
A100: 40570 | B100: Carlota | C100: West | D100: Gault | E100: QT | F100: 10 | G100: 230 | H100: 110 | I100: =LEFT(B100,3) -> Car | K100: 40570 | L100: Carlota | M100: West | N100: Gault | O100: QT | P100: 10 | Q100: 230 | R100: 110 | T100: 40570 | U100: Carlota | V100: West | W100: Gault | X100: QT | Y100: 10 | Z100: 230 | AA100: 110 | AD100: 40570 | AE100: Carlota | AF100: West | AG100: Gault | AH100: QT | AI100: 10 | AJ100: 230 | AK100: 110 | AM100: TTT Total | AO100: 28.25 | CE100: Sunset | CF100: 483 | CG100: 483
...

Sheet Q2
A3: Telugu | B3: English | C3: Hindi | D3: Maths | E3: Total | F3: Gender | G3: PASS/FAIL
A4: 72 | B4: 70 | C4: 60 | D4: 61 | E4: 263 | F4: M | G4: =IF(AND(A4>=40,B4>=40,C4>=40,D4>=40),"PASS","FAIL") -> PASS
A5: 97 | B5: 65 | C5: 87 | D5: 92 | E5: 341 | F5: M | G5: =IF(AND(A5>=40,B5>=40,C5>=40,D5>=40),"PASS","FAIL") -> PASS | J5: All students are Each subjects above =40 then pass either fail.
A6: 95 | B6: 95 | C6: 100 | D6: 86 | E6: 376 | F6: M | G6: =IF(AND(A6>=40,B6>=40,C6>=40,D6>=40),"PASS","FAIL") -> PASS
A7: 81 | B7: 74 | C7: 89 | D7: 81 | E7: 325 | F7: F | G7: =IF(AND(A7>=40,B7>=40,C7>=40,D7>=40),"PASS","FAIL") -> PASS
A8: 81 | B8: 68 | C8: 63 | D8: 82 | E8: 294 | F8: F | G8: =IF(AND(A8>=40,B8>=40,C8>=40,D8>=40),"PASS","FAIL") -> PASS
A9: 91 | B9: 65 | C9: 66 | D9: 61 | E9: 283 | F9: M | G9: =IF(AND(A9>=40,B9>=40,C9>=40,D9>=40),"PASS","FAIL") -> PASS
A10: 92 | B10: 79 | C10: 98 | D10: 61 | E10: 330 | F10: F | G10: =IF(AND(A10>=40,B10>=40,C10>=40,D10>=40),"PASS","FAIL") -> PASS
A11: 74 | B11: 60 | C11: 94 | D11: 97 | E11: 325 | F11: M | G11: =IF(AND(A11>=40,B11>=40,C11>=40,D11>=40),"PASS","FAIL") -> PASS
A12: 81 | B12: 70 | C12: 67 | D12: 85 | E12: 303 | F12: M | G12: =IF(AND(A12>=40,B12>=40,C12>=40,D12>=40),"PASS","FAIL") -> PASS
A13: 83 | B13: 62 | C13: 93 | D13: 100 | E13: 338 | F13: M | G13: =IF(AND(A13>=40,B13>=40,C13>=40,D13>=40),"PASS","FAIL") -> PASS
A14: 76 | B14: 70 | C14: 89 | D14: 60 | E14: 295 | F14: F | G14: =IF(AND(A14>=40,B14>=40,C14>=40,D14>=40),"PASS","FAIL") -> PASS
A15: 67 | B15: 60 | C15: 69 | D15: 68 | E15: 264 | F15: F | G15: =IF(AND(A15>=40,B15>=40,C15>=40,D15>=40),"PASS","FAIL") -> PASS
A16: 100 | B16: 68 | C16: 74 | D16: 100 | E16: 342 | F16: M | G16: =IF(AND(A16>=40,B16>=40,C16>=40,D16>=40),"PASS","FAIL") -> PASS
A17: 82 | B17: 70 | C17: 70 | D17: 94 | E17: 316 | F17: F | G17: =IF(AND(A17>=40,B17>=40,C17>=40,D17>=40),"PASS","FAIL") -> PASS
A18: 89 | B18: 61 | C18: 83 | D18: 99 | E18: 332 | F18: M | G18: =IF(AND(A18>=40,B18>=40,C18>=40,D18>=40),"PASS","FAIL") -> PASS

Sheet Q3
A1: Q) Below 250 failor grade D,250 to 300 grade C,301 to 350 grade Band above 350 Grade A it's based on total marks
M2: USING NESTED FORMULA
A4: Telugu | B4: English | C4: Hindi | D4: Maths | E4: Total | F4: Gender | G4: GRADE
A5: 72 | B5: 70 | C5: 60 | D5: 61 | E5: 263 | F5: M | G5: =IF(E5<=250,"D",IF(E5<=300,"C",IF(E5<=350,"B","A"))) -> C
A6: 97 | B6: 65 | C6: 87 | D6: 92 | E6: 341 | F6: M | G6: =IF(E6<=250,"D",IF(E6<=300,"C",IF(E6<=350,"B","A"))) -> B | L6: 250 | M6: d
A7: 95 | B7: 95 | C7: 100 | D7: 86 | E7: 376 | F7: M | G7: =IF(E7<=250,"D",IF(E7<=300,"C",IF(E7<=350,"B","A"))) -> A | L7: 251-300 | M7: c
A8: 81 | B8: 74 | C8: 89 | D8: 81 | E8: 325 | F8: F | G8: =IF(E8<=250,"D",IF(E8<=300,"C",IF(E8<=350,"B","A"))) -> B | L8: 301-350 | M8: b
A9: 81 | B9: 68 | C9: 63 | D9: 82 | E9: 294 | F9: F | G9: =IF(E9<=250,"D",IF(E9<=300,"C",IF(E9<=350,"B","A"))) -> C | L9: >350 | M9: a
A10: 91 | B10: 65 | C10: 66 | D10: 61 | E10: 283 | F10: M | G10: =IF(E10<=250,"D",IF(E10<=300,"C",IF(E10<=350,"B","A"))) -> C
A11: 92 | B11: 79 | C11: 98 | D11: 61 | E11: 330 | F11: F | G11: =IF(E11<=250,"D",IF(E11<=300,"C",IF(E11<=350,"B","A"))) -> B
A12: 74 | B12: 60 | C12: 94 | D12: 97 | E12: 325 | F12: M | G12: =IF(E12<=250,"D",IF(E12<=300,"C",IF(E12<=350,"B","A"))) -> B
A13: 81 | B13: 70 | C13: 67 | D13: 85 | E13: 303 | F13: M | G13: =IF(E13<=250,"D",IF(E13<=300,"C",IF(E13<=350,"B","A"))) -> B
A14: 83 | B14: 62 | C14: 93 | D14: 100 | E14: 338 | F14: M | G14: =IF(E14<=250,"D",IF(E14<=300,"C",IF(E14<=350,"B","A"))) -> B
A15: 76 | B15: 70 | C15: 89 | D15: 60 | E15: 295 | F15: F | G15: =IF(E15<=250,"D",IF(E15<=300,"C",IF(E15<=350,"B","A"))) -> C
A16: 67 | B16: 60 | C16: 69 | D16: 68 | E16: 264 | F16: F | G16: =IF(E16<=250,"D",IF(E16<=300,"C",IF(E16<=350,"B","A"))) -> C
A17: 100 | B17: 68 | C17: 74 | D17: 100 | E17: 342 | F17: M | G17: =IF(E17<=250,"D",IF(E17<=300,"C",IF(E17<=350,"B","A"))) -> B
A18: 82 | B18: 70 | C18: 70 | D18: 94 | E18: 316 | F18: F | G18: =IF(E18<=250,"D",IF(E18<=300,"C",IF(E18<=350,"B","A"))) -> B
A19: 89 | B19: 61 | C19: 83 | D19: 99 | E19: 332 | F19: M | G19: =IF(E19<=250,"D",IF(E19<=300,"C",IF(E19<=350,"B","A"))) -> B
A20: 93 | B20: 87 | C20: 78 | D20: 75 | E20: 333 | F20: F | G20: =IF(E20<=250,"D",IF(E20<=300,"C",IF(E20<=350,"B","A"))) -> B
A21: 71 | B21: 71 | C21: 88 | D21: 77 | E21: 307 | F21: F | G21: =IF(E21<=250,"D",IF(E21<=300,"C",IF(E21<=350,"B","A"))) -> B
... A30: 89 | B30: 72 | C30: 73 | D30: 81 | E30: 315 | F30: M | G30: =IF(E30<=250,"D",IF(E30<=300,"C",IF(E30<=350,"B","A"))) -> B

Sheet Q4
A2: Q1) how many records are there in Date column
A3: Q2) how many records are there in Region column
A4: Q3) how many records are there in Salesrep column
A5: Q4) total sales
A7: Date | B7: Product | C7: Region | D7: Nationality | E7: SalesRep | F7: Customer | G7: Sales | I7: count | J7: counta | K7: count blank | L7: sum
A8: 40553 | B8: Carlota | C8: East | D8: Indian | E8: Pham | F8: Anirudh | G8: 1449 | H8: Date | I8: =COUNT(A8:A142) -> 135 | J8: =COUNTA(A8:A142) -> 135 | K8: =COUNTBLANK(A8:A142) -> 0
A9: 40544 | B9: Quad | C9: East | D9: Indian | F9: Abishek | G9: 432 | H9: Region | I9: =COUNT(C8:C142) -> 0 | J9: =COUNTA(C8:C142) -> 135 | K9: =COUNTBLANK(C8:C142) -> 0
A10: 40561 | B10: Sunshine | C10: East | D10: Indian | E10: Franks | F10: RAGHAV | G10: 456 | H10: salesrep | I10: =COUNT(E8:E142) -> 0 | J10: =COUNTA(E8:E1048576) -> 132
A11: 40606 | B11: Sunshine | C11: East | D11: Indian | E11: Franks | F11: SEETHA | G11: 456 | H11: total sales | I11: =COUNT(G8:G142) -> 135 | J11: =COUNTA(G8:G142) -> 135 | K11: =COUNTBLANK(G8:G142) -> 0 | L11: =SUM(G8:G142) -> 107605
A12: 40572 | B12: Bellen | C12: East | D12: Indian | E12: Chin | F12: Kavitha | G12: 1100 | J12: count calculate only text number in selected range
A13: 40565 | B13: Bellen | C13: West | D13: Indian | E13: Pham | F13: AST | G13: 1166 | J13: counta Acalculated both text and numeric values in selected range
A14: 40610 | B14: Bellen | C14: West | D14: Indian | E14: Pham | F14: AST | G14: 1166 | J14: countblanks count only blanks in selected range
A15: 40545 | B15: Quad | C15: West | D15: Indian | E15: Pham | F15: Santhosh | G15: 810
A16: 40558 | B16: Sunset | C16: East | D16: Indian | E16: Gault | F16: AST | G16: 1323
A17: 40561 | B17: Sunshine | C17: West | D17: Indian | F17: Yasvanth | G17: 152
A18: 40591 | B18: Sunshine | C18: West | D18: Indian | E18: Sioux | F18: AST | G18: 152
A19: 40567 | B19: Carlota | C19: MidWest | D19: Foreigner | E19: Franks | F19: BBT | G19: 299
A20: 40612 | B20: Carlota | C20: MidWest | D20: Foreigner | E20: Franks | F20: BBT | G20: 299
A21: 40554 | B21: Quad | C21: East | D21: Indian | E21: Smith | F21: BBT | G21: 1323
A22: 40547 | B22: Sunset | C22: MidWest | D22: Foreigner | E22: Sioux | F22: BBT | G22: 609
A23: 40561 | B23: Bellen | C23: East | D23: Indian | F23: DFGH | G23: 440
A24: 40566 | B24: Bellen | C24: East | D24: Indian | E24: Gault | F24: DFGH | G24: 198
A25: 40611 | B25: Bellen | C25: East | D25: Indian | E25: Gault | F25: DFGH | G25: 198
A26: 40569 | B26: Sunset | C26: South | D26: Foreigner | E26: Sioux | F26: DFGH | G26: 924
A27: 40561 | B27: Bellen | C27: East | D27: Indian | E27: Pham | F27: DFR | G27: 1298
A28: 40553 | B28: Quad | C28: East | D28: Indian | E28: Smith | F28: DFR | G28: 459
A29: 40564 | B29: Sunshine | C29: MidWest | D29: Foreigner | E29: Pham | F29: DFR | G29: 437
A30: 40573 | B30: Sunshine | C30: West | D30: Indian | E30: Gault | F30: DFR | G30: 931
A31: 40552 | B31: Bellen | C31: East | D31: Indian | E31: Pham | F31: EPP | G31: 880
A32: 40597 | B32: Bellen | C32: East | D32: Indian | E32: Pham | F32: EPP | G32: 880
A33: 40560 | B33: Quad | C33: MidWest | D33: Foreigner | E33: Chin | F33: EPP | G33: 1647
A34: 40563 | B34: Carlota | C34: East | D34: Indian | E34: Chin | F34: ET | G34: 1357
A35: 40593 | B35: Carlota | C35: East | D35: Indian | E35: Chin | F35: ET | G35: 1357
... A142: 40571 | B142: Sunset | C142: East | D142: Indian | E142: Smith | F142: ZAT | G142: 756

Sheet Q5
B2: 1st | C2: Last
B3: 2 Letters | C3: 3 Letters
A4: Customer | B4: Left | C4: Right | D4: Upper | E4: Lower | F4: Proper
A5: Anirudh | B5: =LEFT(A5,2) -> An | C5: =RIGHT(A5,3) -> udh | D5: =UPPER(A5) -> ANIRUDH | E5: =LOWER(A5) -> anirudh | F5: =PROPER(A5) -> Anirudh
A6: Abishek | B6: =LEFT(A6,2) -> Ab | C6: =RIGHT(A6,3) -> hek | D6: =UPPER(A6) -> ABISHEK | E6: =LOWER(A6) -> abishek | F6: =PROPER(A6) -> Abishek
A7: RAGHAV | B7: =LEFT(A7,2) -> RA | C7: =RIGHT(A7,3) -> HAV | D7: =UPPER(A7) -> RAGHAV | E7: =LOWER(A7) -> raghav | F7: =PROPER(A7) -> Raghav
A8: SEETHA | B8: =LEFT(A8,2) -> SE | C8: =RIGHT(A8,3) -> THA | D8: =UPPER(A8) -> SEETHA | E8: =LOWER(A8) -> seetha | F8: =PROPER(A8) -> Seetha | J8: it will depend functions all in customer ID
A9: Kavitha | B9: =LEFT(A9,2) -> Ka | C9: =RIGHT(A9,3) -> tha | D9: =UPPER(A9) -> KAVITHA | E9: =LOWER(A9) -> kavitha | F9: =PROPER(A9) -> Kavitha
A10: AST | B10: =LEFT(A10,2) -> AS | C10: =RIGHT(A10,3) -> AST | D10: =UPPER(A10) -> AST | E10: =LOWER(A10) -> ast | F10: =PROPER(A10) -> Ast
A11: AST | B11: =LEFT(A11,2) -> AS | C11: =RIGHT(A11,3) -> AST | D11: =UPPER(A11) -> AST | E11: =LOWER(A11) -> ast | F11: =PROPER(A11) -> Ast
A12: Santhosh | B12: =LEFT(A12,2) -> Sa | C12: =RIGHT(A12,3) -> osh | D12: =UPPER(A12) -> SANTHOSH | E12: =LOWER(A12) -> santhosh | F12: =PROPER(A12) -> Santhosh
A13: AST | B13: =LEFT(A13,2) -> AS | C13: =RIGHT(A13,3) -> AST | D13: =UPPER(A13) -> AST | E13: =LOWER(A13) -> ast | F13: =PROPER(A13) -> Ast
A14: Yasvanth | B14: =LEFT(A14,2) -> Ya | C14: =RIGHT(A14,3) -> nth | D14: =UPPER(A14) -> YASVANTH | E14: =LOWER(A14) -> yasvanth | F14: =PROPER(A14) -> Yasvanth
A15: AST | B15: =LEFT(A15,2) -> AS | C15: =RIGHT(A15,3) -> AST | D15: =UPPER(A15) -> AST | E15: =LOWER(A15) -> ast | F15: =PROPER(A15) -> Ast
A16: BBT | B16: =LEFT(A16,2) -> BB | C16: =RIGHT(A16,3) -> BBT | D16: =UPPER(A16) -> BBT | E16: =LOWER(A16) -> bbt | F16: =PROPER(A16) -> Bbt
A17: BBT | B17: =LEFT(A17,2) -> BB | C17: =RIGHT(A17,3) -> BBT | D17: =UPPER(A17) -> BBT | E17: =LOWER(A17) -> bbt | F17: =PROPER(A17) -> Bbt
A18: BBT | B18: =LEFT(A18,2) -> BB | C18: =RIGHT(A18,3) -> BBT | D18: =UPPER(A18) -> BBT | E18: =LOWER(A18) -> bbt | F18: =PROPER(A18) -> Bbt
A19: BBT | B19: =LEFT(A19,2) -> BB | C19: =RIGHT(A19,3) -> BBT | D19: =UPPER(A19) -> BBT | E19: =LOWER(A19) -> bbt | F19: =PROPER(A19) -> Bbt
A20: DFGH | B20: =LEFT(A20,2) -> DF | C20: =RIGHT(A20,3) -> FGH | D20: =UPPER(A20) -> DFGH | E20: =LOWER(A20) -> dfgh | F20: =PROPER(A20) -> Dfgh
... A139: ZAT | B139: =LEFT(A139,2) -> ZA | C139: =RIGHT(A139,3) -> ZAT | D139: =UPPER(A139) -> ZAT | E139: =LOWER(A139) -> zat | F139: =PROPER(A139) -> Zat

Sheet Q6
A1: Date | B1: Product | C1: Region | D1: SalesRep | E1: Customer | F1: Units | G1: Sales | H1: Discount | I1: UNIQUE LIST | K1: Average | M1: 1) | T1: 3) | X1: 5) | AC1: Date | AD1: Product | AE1: Region | AF1: SalesRep | AG1: Customer | AH1: Units | AI1: Sales | AJ1: Discount | AK1: UNIQUE LIST
A2: 40553 | B2: Carlota | C2: East | D2: Pham | E2: AA | F2: 63 | G2: 1449 | H2: 693 | I2: {=_xlfn.UNIQUE(E2:E136)} -> AA | K2: =AVERAGE(H2:H136) -> 366.2963 | M2: Product | N2: Sum of Sales | T2: Customer | U2: Average of Sales | X2: Product | Y2: Min of Sales | Z2: Max of Sales2 | AC2: 40553 | AD2: Bellen | AE2: West | AF2: Pham | AG2: AA | AH2: 63 | AI2: 114 | AJ2: 693 | AK2: {=_xlfn.UNIQUE(AG2:AG136)} -> AA
A3: 40544 | B3: Quad | C3: East | D3: Sioux | E3: AA | F3: 16 | G3: 432 | H3: 232 | I3: AST | M3: Bellen | N3: 25218 | T3: AA | U3: 698.25 | X3: Bellen | Y3: 132 | Z3: 5000 | AC3: 40544 | AD3: Bellen | AE3: West | AF3: Sioux | AG3: AA | AH3: 16 | AI3: 114 | AJ3: 232 | AK3: AST
A4: 40561 | B4: Sunshine | C4: East | D4: Franks | E4: AA | F4: 24 | G4: 456 | H4: 192 | I4: BBT | K4: 1 | L4: PRODUCT WISE TOTAL SALES | M4: Carlota | N4: 19159 | T4: AST | U4: 838.42857 | X4: Carlota | Y4: 230 | Z4: 1449 | AC4: 40561 | AD4: Bellen | AE4: West | AF4: Franks | AG4: AA | AH4: 24 | AI4: 132 | AJ4: 192 | AK4: BBT
A5: 40606 | B5: Sunshine | C5: East | D5: Franks | E5: AA | F5: 24 | G5: 456 | H5: 192 | I5: DFGH | K5: 2 | L5: REGION WISE SALES REP, TOTAL UNITS | M5: Quad | N5: 30834 | T5: BBT | U5: 632.5 | X5: Quad | Y5: 270 | Z5: 1755 | AC5: 40606 | AD5: Bellen | AE5: West | AF5: Franks | AG5: AA | AH5: 24 | AI5: 132 | AJ5: 192 | AK5: DFGH
A6: 40572 | B6: Bellen | C6: East | D6: Chin | E6: AST | F6: 50 | G6: 1100 | H6: 500 | I6: DFR | K6: 3 | L6: CUSTOMER WISE AVERAGE SALES | M6: Sunset | N6: 14553 | T6: DFGH | U6: 440 | X6: Sunset | Y6: 252 | Z6: 1323 | AC6: 40572 | AD6: Bellen | AE6: West | AF6: Chin | AG6: AST | AH6: 50 | AI6: 152 | AJ6: 500 | AK6: DFR
A7: 40565 | B7: Bellen | C7: West | D7: Pham | E7: AST | F7: 53 | G7: 1166 | H7: 530 | I7: EPP | K7: 4 | L7: PERCENTAGE OF DISCOUNT BY REGION | M7: Sunshine | N7: 17841 | T7: DFR | U7: 781.25 | X7: Sunshine | Y7: 114 | Z7: 1216 | AC7: 40565 | AD7: Bellen | AE7: West | AF7: Pham | AG7: AST | AH7: 53 | AI7: 152 | AJ7: 530 | AK7: EPP
A8: 40610 | B8: Bellen | C8: West | D8: Pham | E8: AST | F8: 53 | G8: 1166 | H8: 530 | I8: ET | K8: 5 | L8: MIN SALES AMOUNT,MAX SALES AMOUNT BY PRODUCT | M8: (blank) | T8: EPP | U8: 1135.6667 | X8: (blank) | AC8: 40610 | AD8: Bellen | AE8: West | AF8: Pham | AG8: AST | AH8: 53 | AI8: 152 | AJ8: 530 | AK8: ET
A9: 40545 | B9: Quad | C9: West | D9: Pham | E9: AST | F9: 30 | G9: 810 | H9: 435 | I9: FM | K9: 6 | L9: CREATE UNIQUE LIST OF COUSTOMERS | M9: Grand Total | N9: 107605 | T9: ET | U9: 792.5 | X9: Grand Total | Y9: 114 | Z9: 5000 | AC9: 40545 | AD9: Bellen | AE9: West | AF9: Pham | AG9: AST | AH9: 30 | AI9: 154 | AJ9: 435 | AK9: FM
A10: 40558 | B10: Sunset | C10: East | D10: Gault | E10: AST | F10: 63 | G10: 1323 | H10: 583 | I10: FRED | K10: 7 | L10: HIGHLIGHT THE ALL EAST REGION | T10: FM | U10: 830.375 | AC10: 40558 | AD10: Bellen | AE10: West | AF10: Gault | AG10: AST | AH10: 63 | AI10: 154 | AJ10: 583 | AK10: FRED
A11: 40561 | B11: Sunshine | C11: West | D11: Sioux | E11: AST | F11: 8 | G11: 152 | H11: 64 | I11: HHH | K11: 8 | L11: HIGHLIGHT THE DUPLICATE DATES | M11: 2) | T11: FRED | U11: 2312.6667 | X11: 4) | AC11: 40561 | AD11: Bellen | AE11: West | AF11: Sioux | AG11: AST | AH11: 8 | AI11: 198 | AJ11: 64 | AK11: HHH
A12: 40591 | B12: Sunshine | C12: West | D12: Sioux | E12: AST | F12: 8 | G12: 152 | H12: 64 | I12: HII | K12: 9 | L12: HIGHLIGHTS ABOVE AVERAGE DISCOUNT COLUMN | M12: Sum of Units | N12: Region | T12: HHH | U12: 486.5 | X12: Region | Y12: PERCENTAGE OF DISCOUNT | AC12: 40591 | AD12: Bellen | AE12: West | AF12: Sioux | AG12: AST | AH12: 8 | AI12: 198 | AJ12: 64 | AK12: HII
A13: 40567 | B13: Carlota | C13: MidWest | D13: Franks | E13: BBT | F13: 13 | G13: 299 | H13: 143 | I13: ITTW | K13: 10 | L13: REGION Z to A,PRODUCT A to Z,SALES INCREASING ORDERS | M13: SalesRep | N13: East | O13: MidWest | P13: South | Q13: West | R13: (blank) | S13: Grand Total | T13: HII | U13: 1370.25 | X13: East | Y13: 0.32212336 | AC13: 40567 | AD13: Bellen | AE13: West | AF13: Franks | AG13: BBT | AH13: 13 | AI13: 209 | AJ13: 143 | AK13: ITTW
A14: 40612 | B14: Carlota | C14: MidWest | D14: Franks | E14: BBT | F14: 13 | G14: 299 | H14: 143 | I14: ITW | M14: Chin | N14: 243 | O14: 247 | P14: 112 | Q14: 98 | S14: 700 | T14: ITTW | U14: 1380 | X14: MidWest | Y14: 0.18394338 | AC14: 40612 | AD14: Bellen | AE14: West | AF14: Franks | AG14: BBT | AH14: 13 | AI14: 209 | AJ14: 143 | AK14: ITW
A15: 40554 | B15: Quad | C15: East | D15: Smith | E15: BBT | F15: 49 | G15: 1323 | H15: 711 | I15: JAQ | M15: Franks | N15: 428 | O15: 130 | P15: 163 | Q15: 144 | S15: 865 | T15: ITW | U15: 666.75 | X15: South | Y15: 0.24489383 | AC15: 40554 | AD15: Bellen | AE15: West | AF15: Smith | AG15: BBT | AH15: 49 | AI15: 220 | AJ15: 711 | AK15: JAQ
A16: 40547 | B16: Sunset | C16: MidWest | D16: Sioux | E16: BBT | F16: 29 | G16: 609 | H16: 268 | I16: KBTB | M16: Gault | N16: 216 | O16: 78 | P16: 160 | Q16: 178 | S16: 632 | T16: JAQ | U16: 590.5 | X16: West | Y16: 0.24903943 | AC16: 40547 | AD16: Bellen | AE16: West | AF16: Sioux | AG16: BBT | AH16: 29 | AI16: 228 | AJ16: 268 | AK16: KBTB
A17: 40561 | B17: Bellen | C17: East | D17: Franks | E17: DFGH | F17: 20 | G17: 440 | H17: 200 | I17: KPSA | M17: Pham | N17: 262 | O17: 153 | P17: 93 | Q17: 391 | S17: 899 | T17: KBTB | U17: 1083.6667 | X17: (blank) | Y17: 0 | AC17: 40561 | AD17: Bellen | AE17: West | AF17: Franks | AG17: DFGH | AH17: 20 | AI17: 228 | AJ17: 200 | AK17: KPSA
A18: 40566 | B18: Bellen | C18: East | D18: Gault | E18: DFGH | F18: 9 | G18: 198 | H18: 90 | I18: LOP | M18: Sioux | N18: 94 | O18: 163 | P18: 298 | Q18: 191 | S18: 746 | T18: KPSA | U18: 394 | X18: Grand Total | Y18: 1 | AC18: 40566 | AD18: Bellen | AE18: West | AF18: Gault | AG18: DFGH | AH18: 9 | AI18: 230 | AJ18: 90 | AK18: LOP
A19: 40611 | B19: Bellen | C19: East | D19: Gault | E19: DFGH | F19: 9 | G19: 198 | H19: 90 | I19: MBG | M19: Smith | N19: 161 | O19: 147 | P19: 318 | Q19: 119 | S19: 745 | T19: LOP | U19: 345 | AC19: 40611 | AD19: Bellen | AE19: West | AF19: Gault | AG19: DFGH | AH19: 9 | AI19: 242 | AJ19: 90 | AK19: MBG
A20: 40569 | B20: Sunset | C20: South | D20: Sioux | E20: DFGH | F20: 44 | G20: 924 | H20: 407 | I20: MNGD | M20: (blank) | T20: MBG | U20: 777 | AC20: 40569 | AD20: Bellen | AE20: West | AF20: Sioux | AG20: DFGH | AH20: 44 | AI20: 252 | AJ20: 407 | AK20: MNGD
A21: 40561 | B21: Bellen | C21: East | D21: Pham | E21: DFR | F21: 59 | G21: 1298 | H21: 590 | I21: PCC | M21: Grand Total | N21: 1404 | O21: 918 | P21: 1144 | Q21: 1121 | S21: 4587 | T21: MNGD | U21: 655 | AC21: 40561 | AD21: Bellen | AE21: West | AF21: Pham | AG21: DFR | AH21: 59 | AI21: 270 | AJ21: 590 | AK21: PCC
A22: 40553 | B22: Quad | C22: East | D22: Smith | E22: DFR | F22: 17 | G22: 459 | H22: 247 | I22: PLOT | T22: PCC | U22: 726.61538 | AC22: 40553 | AD22: Bellen | AE22: West | AF22: Smith | AG22: DFR | AH22: 17 | AI22: 270 | AJ22: 247 | AK22: PLOT
A23: 40564 | B23: Sunshine | C23: MidWest | D23: Pham | E23: DFR | F23: 23 | G23: 437 | H23: 184 | I23: PSA | T23: PLOT | U23: 661 | AC23: 40564 | AD23: Bellen | AE23: West | AF23: Pham | AG23: DFR | AH23: 23 | AI23: 270 | AJ23: 184 | AK23: PSA
A24: 40573 | B24: Sunshine | C24: West | D24: Gault | E24: DFR | F24: 49 | G24: 931 | H24: 392 | I24: QT | T24: PSA | U24: 612.83333 | AC24: 40573 | AD24: Bellen | AE24: West | AF24: Gault | AG24: DFR | AH24: 49 | AI24: 273 | AJ24: 392 | AK24: QT
A25: 40552 | B25: Bellen | C25: East | D25: Pham | E25: EPP | F25: 40 | G25: 880 | H25: 400 | I25: SFWK | T25: QT | U25: 621.28571 | AC25: 40552 | AD25: Bellen | AE25: West | AF25: Pham | AG25: EPP | AH25: 40 | AI25: 276 | AJ25: 400 | AK25: SFWK
A26: 40597 | B26: Bellen | C26: East | D26: Pham | E26: EPP | F26: 40 | G26: 880 | H26: 400 | I26: T | T26: SFWK | U26: 913.33333 | AC26: 40597 | AD26: Bellen | AE26: West | AF26: Pham | AG26: EPP | AH26: 40 | AI26: 276 | AJ26: 400 | AK26: T
A27: 40560 | B27: Quad | C27: MidWest | D27: Chin | E27: EPP | F27: 61 | G27: 1647 | H27: 885 | I27: TRU | T27: T | U27: 971.4 | AC27: 40560 | AD27: Bellen | AE27: West | AF27: Chin | AG27: EPP | AH27: 61 | AI27: 299 | AJ27: 885 | AK27: TRU
A28: 40563 | B28: Carlota | C28: East | D28: Chin | E28: ET | F28: 59 | G28: 1357 | H28: 649 | I28: TTT | T28: TRU | U28: 459.66667 | AC28: 40563 | AD28: Bellen | AE28: West | AF28: Chin | AG28: ET | AH28: 59 | AI28: 299 | AJ28: 649 | AK28: TTT
A29: 40593 | B29: Carlota | C29: East | D29: Chin | E29: ET | F29: 59 | G29: 1357 | H29: 649 | I29: WSD | T29: TTT | U29: 615.25 | AC29: 40593 | AD29: Bellen | AE29: West | AF29: Chin | AG29: ET | AH29: 59 | AI29: 330 | AJ29: 649 | AK29: WSD
A30: 40548 | B30: Sunshine | C30: West | D30: Franks | E30: ET | F30: 12 | G30: 228 | H30: 96 | I30: WT | T30: WSD | U30: 700.75 | AC30: 40548 | AD30: Bellen | AE30: West | AF30: Franks | AG30: ET | AH30: 12 | AI30: 345 | AJ30: 96 | AK30: WT
A31: 40593 | B31: Sunshine | C31: West | D31: Franks | E31: ET | F31: 12 | G31: 228 | H31: 96 | I31: YTR | T31: WT | U31: 425 | AC31: 40593 | AD31: Bellen | AE31: West | AF31: Franks | AG31: ET | AH31: 12 | AI31: 352 | AJ31: 96 | AK31: YTR
A32: 40553 | B32: Bellen | C32: MidWest | D32: Gault | E32: FM | F32: 7 | G32: 154 | H32: 70 | I32: ZAT | T32: YTR | U32: 948.3 | AC32: 40553 | AD32: Bellen | AE32: West | AF32: Gault | AG32: FM | AH32: 7 | AI32: 357 | AJ32: 70 | AK32: ZAT
A33: 40546 | B33: Carlota | C33: MidWest | D33: Chin | E33: FM | F33: 20 | G33: 460 | H33: 220 | T33: ZAT | U33: 756 | AC33: 40546 | AD33: Bellen | AE33: South | AF33: Chin | AG33: FM | AH33: 20 | AI33: 374 | AJ33: 220
A34: 40591 | B34: Carlota | C34: MidWest | D34: Chin | E34: FM | F34: 20 | G34: 460 | H34: 220 | T34: (blank) | AC34: 40591 | AD34: Bellen | AE34: South | AF34: Chin | AG34: FM | AH34: 20 | AI34: 378 | AJ34: 220
A35: 40556 | B35: Carlota | C35: South | D35: Smith | E35: FM | F35: 52 | G35: 1196 | H35: 572 | T35: Grand Total | U35: 797.07407 | AC35: 40556 | AD35: Bellen | AE35: South | AF35: Smith | AG35: FM | AH35: 52 | AI35: 378 | AJ35: 572
A36: 40564 | B36: Quad | C36: East | D36: Chin | E36: FM | F36: 58 | G36: 1566 | H36: 841 | AC36: 40564 | AD36: Carlota | AE36: South | AF36: Chin | AG36: FM | AH36: 58 | AI36: 399 | AJ36: 841
A37: 40565 | B37: Quad | C37: South | D37: Franks | E37: FM | F37: 29 | G37: 783 | H37: 421 | AC37: 40565 | AD37: Carlota | AE37: South | AF37: Franks | AG37: FM | AH37: 29 | AI37: 399 | AJ37: 421
A38: 40571 | B38: Sunset | C38: West | D38: Chin | E38: FM | F38: 62 | G38: 1302 | H38: 574 | AC38: 40571 | AD38: Carlota | AE38: South | AF38: Chin | AG38: FM | AH38: 62 | AI38: 414 | AJ38: 574
A39: 40546 | B39: Sunshine | C39: East | D39: Pham | E39: FM | F39: 38 | G39: 722 | H39: 304 | AC39: 40546 | AD39: Carlota | AE39: South | AF39: Pham | AG39: FM | AH39: 38 | AI39: 418 | AJ39: 304
A40: 40569 | B40: Bellen | C40: West | D40: Pham | E40: FRED | F40: 61 | G40: 5000 | H40: 610 | AC40: 40569 | AD40: Carlota | AE40: South | AF40: Pham | AG40: FRED | AH40: 61 | AI40: 432 | AJ40: 610
A41: 40571 | B41: Sunshine | C41: South | D41: Smith | E41: FRED | F41: 51 | G41: 969 | H41: 408 | AC41: 40571 | AD41: Carlota | AE41: South | AF41: Smith | AG41: FRED | AH41: 51 | AI41: 432 | AJ41: 408
A42: 40601 | B42: Sunshine | C42: South | D42: Smith | E42: FRED | F42: 51 | G42: 969 | H42: 408 | AC42: 40601 | AD42: Carlota | AE42: South | AF42: Smith | AG42: FRED | AH42: 51 | AI42: 437 | AJ42: 408
A43: 40550 | B43: Carlota | C43: MidWest | D43: Franks | E43: HHH | F43: 12 | G43: 276 | H43: 132 | AC43: 40550 | AD43: Carlota | AE43: South | AF43: Franks | AG43: HHH | AH43: 12 | AI43: 437 | AJ43: 132
A44: 40580 | B44: Carlota | C44: MidWest | D44: Franks | E44: HHH | F44: 12 | G44: 276 | H44: 132 | AC44: 40580 | AD44: Carlota | AE44: South | AF44: Franks | AG44: HHH | AH44: 12 | AI44: 440 | AJ44: 132
A45: 40564 | B45: Sunset | C45: South | D45: Pham | E45: HHH | F45: 13 | G45: 273 | H45: 120 | AC45: 40564 | AD45: Carlota | AE45: South | AF45: Pham | AG45: HHH | AH45: 13 | AI45: 456 | AJ45: 120
A46: 40560 | B46: Sunshine | C46: MidWest | D46: Franks | E46: HHH | F46: 59 | G46: 1121 | H46: 472 | AC46: 40560 | AD46: Carlota | AE46: South | AF46: Franks | AG46: HHH | AH46: 59 | AI46: 456 | AJ46: 472
A47: 40560 | B47: Quad | C47: East | D47: Franks | E47: HII | F47: 62 | G47: 1674 | H47: 899 | AC47: 40560 | AD47: Carlota | AE47: South | AF47: Franks | AG47: HII | AH47: 62 | AI47: 459 | AJ47: 899
... A136: 40571 | B136: Sunset | C136: East | D136: Smith | E136: ZAT | F136: 36 | G136: 756 | H136: 333 | AC136: 40571 | AD136: Sunshine | AE136: East | AF136: Smith | AG136: ZAT | AH136: 36 | AI136: 5000 | AJ136: 333

Sheet Q7
A1: Filter the data set to show records that or for the West or MidWest Region and For Product Carlota
A3: Date | B3: Product | C3: Region | D3: SalesRep | E3: Customer | F3: Units | G3: Sales | H3: COGS
A4: 40563 | B4: Sunshine | C4: West | D4: Sioux | E4: YTR | F4: 58 | G4: 1102 | H4: 464
A5: 40573 | B5: Sunshine | C5: West | D5: Gault | E5: DFR | F5: 49 | G5: 931 | H5: 392
A6: 40548 | B6: Sunshine | C6: West | D6: Franks | E6: ET | F6: 12 | G6: 228 | H6: 96
A7: 40561 | B7: Sunshine | C7: West | D7: Sioux | E7: AST | F7: 8 | G7: 152 | H7: 64
A8: 40571 | B8: Sunset | C8: West | D8: Chin | E8: FM | F8: 62 | G8: 1302 | H8: 573.5
A9: 40550 | B9: Sunset | C9: West | D9: Pham | E9: T | F9: 61 | G9: 1281 | H9: 564.25
A10: 40550 | B10: Sunset | C10: West | D10: Pham | E10: WT | F10: 53 | G10: 1113 | H10: 490.25
A11: 40553 | B11: Quad | C11: West | D11: Smith | E11: KBTB | F11: 65 | G11: 1755 | H11: 942.5
A12: 40549 | B12: Quad | C12: West | D12: Sioux | E12: PCC | F12: 64 | G12: 1728 | H12: 928
A13: 40567 | B13: Quad | C13: West | D13: Gault | E13: HII | F13: 63 | G13: 1701 | H13: 913.5
A14: 40564 | B14: Quad | C14: West | D14: Gault | E14: ITW | F14: 56 | G14: 1512 | H14: 812
A15: 40545 | B15: Quad | C15: West | D15: Pham | E15: AST | F15: 30 | G15: 810 | H15: 435
... A108: 40566 | B108: Bellen | C108: East | D108: Gault | E108: DFGH | F108: 9 | G108: 198 | H108: 90

Sheet Q8
A1: Create A PivotTable that sums sales for each Month.
A3: Date | B3: SalesRep | C3: Sales | D3: Month
A4: 40255 | B4: Fred | C4: 73 | D4: =TEXT(A4,"mmmm yyyy") -> March 2010
A5: 40256 | B5: Jo | C5: 121 | D5: =TEXT(A5,"mmmm yyyy") -> March 2010
A6: 40257 | B6: Fred | C6: 167 | D6: =TEXT(A6,"mmmm yyyy") -> March 2010 | G6: Month | H6: Sum of Sales
A7: 40258 | B7: Joe | C7: 167 | D7: =TEXT(A7,"mmmm yyyy") -> March 2010 | G7: April 2010 | H7: 3003
A8: 40259 | B8: Sue | C8: 75 | D8: =TEXT(A8,"mmmm yyyy") -> March 2010 | G8: August 2010 | H8: 3468
A9: 40260 | B9: Fred | C9: 157 | D9: =TEXT(A9,"mmmm yyyy") -> March 2010 | G9: July 2010 | H9: 3515
A10: 40261 | B10: Sue | C10: 61 | D10: =TEXT(A10,"mmmm yyyy") -> March 2010 | G10: June 2010 | H10: 3664
A11: 40262 | B11: Fred | C11: 108 | D11: =TEXT(A11,"mmmm yyyy") -> March 2010 | G11: March 2010 | H11: 1522
A12: 40263 | B12: Jo | C12: 139 | D12: =TEXT(A12,"mmmm yyyy") -> March 2010 | G12: May 2010 | H12: 3365
A13: 40264 | B13: Sioux | C13: 130 | D13: =TEXT(A13,"mmmm yyyy") -> March 2010 | G13: October 2010 | H13: 968
A14: 40265 | B14: Sue | C14: 66 | D14: =TEXT(A14,"mmmm yyyy") -> March 2010 | G14: September 2010 | H14: 3240
A15: 40266 | B15: Sioux | C15: 86 | D15: =TEXT(A15,"mmmm yyyy") -> March 2010 | G15: Grand Total | H15: 22745
A16: 40267 | B16: Joe | C16: 122 | D16: =TEXT(A16,"mmmm yyyy") -> March 2010
A17: 40268 | B17: Sioux | C17: 50 | D17: =TEXT(A17,"mmmm yyyy") -> March 2010
A18: 40269 | B18: Sue | C18: 77 | D18: =TEXT(A18,"mmmm yyyy") -> April 2010
A19: 40270 | B19: Fred | C19: 140 | D19: =TEXT(A19,"mmmm yyyy") -> April 2010
A20: 40271 | B20: Sue | C20: 107 | D20: =TEXT(A20,"mmmm yyyy") -> April 2010
A21: 40272 | B21: Sioux | C21: 109 | D21: =TEXT(A21,"mmmm yyyy") -> April 2010
A22: 40273 | B22: Joe | C22: 121 | D22: =TEXT(A22,"mmmm yyyy") -> April 2010
A23: 40274 | B23: Fred | C23: 78 | D23: =TEXT(A23,"mmmm yyyy") -> April 2010
A24: 40275 | B24: Sioux | C24: 168 | D24: =TEXT(A24,"mmmm yyyy") -> April 2010
A25: 40276 | B25: Jo | C25: 88 | D25: =TEXT(A25,"mmmm yyyy") -> April 2010
A26: 40277 | B26: Chin | C26: 110 | D26: =TEXT(A26,"mmmm yyyy") -> April 2010
A27: 40278 | B27: Chin | C27: 132 | D27: =TEXT(A27,"mmmm yyyy") -> April 2010
... A208: 40459 | B208: Sue | C208: 146 | D208: =TEXT(A208,"mmmm yyyy") -> October 2010

Sheet Q9
A1: S.No | B1: Name | C1: fill short cuts | D1: marks 20M
A2: 1 | B2: Insert column | C2: ctrl+sift++
A3: 2 | B3: Delete Column | C3: ctrl+-
A4: 3 | B4: Print | C4: ctrl+p
A5: 4 | B5: Redo | C5: ctrl+y
A6: 5 | B6: bold font | C6: ctrl+b
A7: 6 | B7: Find | C7: ctrl+f
A8: 7 | B8: Open File | C8: ctrl+o
A9: 8 | B9: Freeze panes | C9: alt+w+F+f
A10: 9 | B10: Replace | C10: ctrl+h
A11: 10 | B11: Change Number to date | C11: ctrl+shift+#
A12: 11 | B12: Change date to Number | C12: ctrl+shift+~
A13: 12 | B13: select entire column | C13: ctrl+space
... A21: 20 | B21: Selet entire row | C21: ctrl+shift

Sheet Q10
A1: Q2. Use excel functions with the below conditions and derive the Person Status
K2: IF(A2>=90,"A",IF(A2>=75,"B",IF(A2>=60,"C",IF(A2>=40,"D","Fail"))))
C3: Condition
C4: >=60 | D4: Old
C5: >=30 & <=59 | D5: Middle
C6: >=18 & <=29 | D6: Young
C7: <18 | D7: Child
B9: SL.No | C9: Age | D9: Name | E9: Person Status
B10: 1 | C10: 65 | D10: RASIKLAL JETHALAL CHHAPAN | E10: =IF(C10>=60,"old",IF(AND(C10>=30,C10<=59),"middle",IF(AND(C10>=18,C10<=29),"young",IF(C10<18,"child")))) -> old
B11: 2 | C11: 67 | D11: SAROJ RASIKLAL CHHAPAN | E11: =IF(C11>=60,"old",IF(AND(C11>=30,C11<=59),"middle",IF(AND(C11>=18,C11<=29),"young",IF(C11<18,"child")))) -> old
B12: 3 | C12: 25 | D12: MAULIK VINODCHANDRA JADAWALA | E12: =IF(C12>=60,"old",IF(AND(C12>=30,C12<=59),"middle",IF(AND(C12>=18,C12<=29),"young",IF(C12<18,"child")))) -> young
B13: 4 | C13: 45 | D13: JIGAR BHUPESH CHHAPAN | E13: =IF(C13>=60,"old",IF(AND(C13>=30,C13<=59),"middle",IF(AND(C13>=18,C13<=29),"young",IF(C13<18,"child")))) -> middle
B14: 5 | C14: 15 | D14: HIMANSHU JOSHI | E14: =IF(C14>=60,"old",IF(AND(C14>=30,C14<=59),"middle",IF(AND(C14>=18,C14<=29),"young",IF(C14<18,"child")))) -> child
B15: 6 | C15: 80 | D15: GEETA VASHISHTHA DESAI | E15: =IF(C15>=60,"old",IF(AND(C15>=30,C15<=59),"middle",IF(AND(C15>=18,C15<=29),"young",IF(C15<18,"child")))) -> old
B16: 7 | C16: 40 | D16: HITENDRA RAJNIKANT DAVE | E16: =IF(C16>=60,"old",IF(AND(C16>=30,C16<=59),"middle",IF(AND(C16>=18,C16<=29),"young",IF(C16<18,"child")))) -> middle
B17: 8 | C17: 17 | D17: ARUNA V GARG | E17: =IF(C17>=60,"old",IF(AND(C17>=30,C17<=59),"middle",IF(AND(C17>=18,C17<=29),"young",IF(C17<18,"child")))) -> child
B18: 9 | C18: 95 | D18: DHAVAL NATVARLAL SHAH | E18: =IF(C18>=60,"old",IF(AND(C18>=30,C18<=59),"middle",IF(AND(C18>=18,C18<=29),"young",IF(C18<18,"child")))) -> old
B19: 10 | C19: 22 | D19: NATVARLAL HIRALAL SHAH | E19: =IF(C19>=60,"old",IF(AND(C19>=30,C19<=59),"middle",IF(AND(C19>=18,C19<=29),"young",IF(C19<18,"child")))) -> young

Sheet Q11
A1: :
B4: Raw Data | F4: Area | G4: Total Amount | H4: Total Count
B5: Area | C5: Sub Area | D5: grossamt | F5: No Area Given | G5: =SUMIF(B5:B303,F5,D5:D303) -> 50000 | H5: =COUNTIF(B6:B303,F5) -> 1
B6: Hardware | C6: Damaged-Malfunctioned | D6: 50000 | F6: AirWatch | G6: =SUMIF(B6:B304,F6,D6:D304) -> 500000 | H6: =COUNTIF(B7:B304,F6) -> 1
B7: Hardware | C7: Complete System | D7: 195000 | F7: Client Specific | G7: =SUMIF(B7:B305,F7,D7:D305) -> 9964844 | H7: =COUNTIF(B8:B305,F7) -> 18
B8: Hardware | C8: Usage | D8: 50000 | F8: Connectivity | G8: =SUMIF(B8:B306,F8,D8:D306) -> 9825000 | H8: =COUNTIF(B9:B306,F8) -> 13
B9: Off the Shelf | C9: Windows 7 | D9: 1000000 | F9: Email | G9: =SUMIF(B9:B307,F9,D9:D307) -> 1300000 | H9: =COUNTIF(B10:B307,F9) -> 3
B10: No Area Given | C10: No Sub Area Given | D10: 50000 | F10: Field Planning | G10: =SUMIF(B10:B308,F10,D10:D308) -> 440000 | H10: =COUNTIF(B11:B308,F10) -> 4
B11: iPad - Hardware | C11: Lost/Stolen | D11: 100100 | F11: Hardware | G11: =SUMIF(B11:B309,F11,D11:D309) -> 25274300 | H11: =COUNTIF(B12:B309,F11) -> 38
B12: Veeva | C12: Calls | D12: 50000 | F12: Hardware - iPad | G12: =SUMIF(B12:B310,F12,D12:D310) -> 1220000 | H12: =COUNTIF(B13:B310,F12) -> 3
B13: iPad - Hardware | C13: Request | D13: 450000 | F13: iPad | G13: =SUMIF(B13:B311,F13,D13:D311) -> 20191282 | H13: =COUNTIF(B14:B311,F13) -> 15
B14: Veeva | C14: Calls | D14: 20000000 | F14: iPad - Connectivity | G14: =SUMIF(B14:B312,F14,D14:D312) -> 6000 | H14: =COUNTIF(B15:B312,F14) -> 1
B15: Veeva | C15: Calls | D15: 10300 | F15: iPad - Hardware | G15: =SUMIF(B15:B313,F15,D15:D313) -> 65000 | H15: =COUNTIF(B16:B313,F15) -> 4
B16: Veeva | C16: Accounts | D16: 225000 | F16: iPad - Software | G16: =SUMIF(B16:B314,F16,D16:D314) -> 350000 | H16: =COUNTIF(B17:B314,F16) -> 2
B17: iPad - Hardware | C17: Damaged/Malfunctioned | D17: 25000 | F17: iPhone | G17: =SUMIF(B17:B315,F17,D17:D315) -> 2050000 | H17: =COUNTIF(B18:B315,F17) -> 7
... B22: iPad - Hardware | C22: Damaged/Malfunctioned | D22: 25000 | F22: Vmobile | G22: =SUMIF(B22:B320,F22,D22:D320) -> 6412789 | H22: =COUNTIF(B23:B320,F22) -> 16
B23: iPad - Software | C23: Application | D23: 50000 | F23: Total | G23: =SUM(G5:G22) -> 175703471 | H23: =SUM(H5:H22) -> 286
B24: iPad - Hardware | C24: Lost/Stolen | D24: 5000
B25: iPad - Connectivity | C25: Wireless | D25: 6000
B26: Veeva | C26: Calls | D26: 6000
B27: AirWatch | C27: Applications | D27: 500000
B28: iPad - Hardware | C28: Damaged/Malfunctioned | D28: 10000
B29: Veeva | C29: Events | D29: 60000
B30: Hardware | C30: Damaged-Malfunctioned | D30: 100000
B31: Veeva | C31: Samples | D31: 400000
B32: Veeva | C32: Reports | D32: 195000
B33: Email | C33: Configuration | D33: 400000
B34: Veeva | C34: Accounts | D34: 250000
B35: Hardware | C35: Damaged-Malfunctioned | D35: 220000
... B303: Off the Shelf | C303: Internet Browser | D303: 1000000

Sheet Q12
A1: Q5. Concatenate Category, Area, Sub Area with and separate with '/' (slash)
B3: Example
B4: Category | C4: Area | D4: Sub Area | E4: CONCATENATE WITH SLASH ( / )
B5: Hardware | C5: Damaged-Malfunctioned | D5: Printer | E5: Hardware/Damaged-Malfunctioned/Printer
B7: Category | C7: Area | D7: Sub Area | E7: CONCATENATE WITH SLASH ( / )
B8: Hardware | C8: Damaged-Malfunctioned | D8: Printer | E8: =CONCATENATE(B8,"/",C8,"/",D8,"/") -> Hardware/Damaged-Malfunctioned/Printer/
B9: Hardware | C9: Complete System | D9: Return to Inventory | E9: =CONCATENATE(B9,"/",C9,"/",D9,"/") -> Hardware/Complete System/Return to Inventory/
B10: Hardware | C10: Usage | D10: iPad | E10: =CONCATENATE(B10,"/",C10,"/",D10,"/") -> Hardware/Usage/iPad/
B11: Off the Shelf | C11: Windows 7 | D11: Logon | E11: =CONCATENATE(B11,"/",C11,"/",D11,"/") -> Off the Shelf/Windows 7/Logon/
B12: No Area Given | C12: No Sub Area Given | D12: No SubSubArea Given | E12: =CONCATENATE(B12,"/",C12,"/",D12,"/") -> No Area Given/No Sub Area Given/No SubSubArea Given/
B13: iPad - Hardware | C13: Lost/Stolen | D13: Miscellaneous Items | E13: =CONCATENATE(B13,"/",C13,"/",D13,"/") -> iPad - Hardware/Lost/Stolen/Miscellaneous Items/
B14: Veeva | C14: Calls | D14: Missing | E14: =CONCATENATE(B14,"/",C14,"/",D14,"/") -> Veeva/Calls/Missing/
B15: iPad - Hardware | C15: Request | D15: iPad | E15: =CONCATENATE(B15,"/",C15,"/",D15,"/") -> iPad - Hardware/Request/iPad/
B16: Veeva | C16: Calls | D16: Expenses | E16: =CONCATENATE(B16,"/",C16,"/",D16,"/") -> Veeva/Calls/Expenses/

Sheet Q13
C1: Highlight the cells greather than 25000 salary by green colour
B5: Empolyee name | C5: Emp .ID | D5: Gender | E5: DOB | F5: Work Location | G5: Date Of Joing | H5: Date Of Resignation | I5: Salary | J5: Total Experience | K5: Emergency Contact Details | L5: Address
B6: suresh | C6: 112 | D6: Male | E6: 37084 | F6: Kol | G6: 44571 | H6: 44958 | I6: 42000 | J6: 8 | K6: 9821934908 | L6: amerpet
B7: naresh | C7: 113 | D7: Female | E7: 35354 | F7: Hyd | G7: 44507 | H7: 45224 | I7: 35000 | J7: 1 | K7: 9543693808 | L7: suncity
B8: mahesh | C8: 114 | D8: Male | E8: 33266 | F8: Blr | G8: 44407 | H8: 44558 | I8: 35000 | J8: 3 | K8: 9493205498 | L8: amerpet
B9: naveen | C9: 115 | D9: Female | E9: 37111 | F9: Blr | G9: 44492 | H9: 44598 | I9: 18000 | J9: 5 | K9: 9136087980 | L9: amerpet
B10: linga reddy | C10: 116 | D10: Female | E10: 35151 | F10: Chn | G10: 44571 | H10: 45048 | I10: 35000 | J10: 9 | K10: 9726733882 | L10: suncity
B11: sam reddy | C11: 117 | D11: Male | E11: 36885 | F11: Blr | G11: 44577 | H11: 45304 | I11: 42000 | J11: 9 | K11: 9669292876 | L11: panjagutta
B12: pavan | C12: 118 | D12: Male | E12: 34319 | F12: Chn | G12: 44424 | H12: 45054 | I12: 10000 | J12: 9 | K12: 9315204195 | L12: begumpet
B13: kishan | C13: 119 | D13: Female | E13: 36250 | F13: Hyd | G13: 44504 | H13: 44707 | I13: 18000 | J13: 3 | K13: 9285113634 | L13: suncity
B14: harish | C14: 110 | D14: Male | E14: 36109 | F14: Chn | G14: 44556 | H14: 44992 | I14: 35000 | J14: 8 | K14: 9511890959 | L14: hitechcity
B15: chandrashekr | C15: 111 | D15: Female | E15: 34701 | F15: Kol | G15: 44372 | H15: 44835 | I15: 18000 | J15: 2 | K15: 9178537741 | L15: amerpet
B16: chintu | C16: 112 | D16: Male | E16: 35642 | F16: Chn | G16: 44308 | H16: 44677 | I16: 10000 | J16: 7 | K16: 9563258827 | L16: hitechcity
B17: banti | C17: 113 | D17: Male | E17: 35710 | F17: Blr | G17: 44382 | H17: 44681 | I17: 20000 | J17: 1 | K17: 9903668284 | L17: hitechcity
... B45: vikas | C45: 121 | D45: Male | E45: 35680 | F45: Hyd | G45: 44565 | H45: 45215 | I45: 18000 | J45: 3 | K45: 9659532373 | L45: panjagutta

Sheet DATA
A1: Customer Name | B1: Phone | C1: City | D1: Source | E1: Pickup Date | F1: Operator | G1: Service type | H1: Customer bill | I1: Operator bill | J1: Car Number
A2: Akshat Trivedi | B2: 9819086125 | C2: mumbai | D2: Call center | E2: 41218.292 | F2: Soham tours and travels | G2: P2P | H2: 734 | I2: 365 | J2: MH04ES6585
A3: Ms. Preeti Mehta | B3: 9819065905 | C3: mumbai | D3: Call center | E3: 41218.354 | F3: Soham tours and travels | G3: P2P | H3: 480 | I3: 365 | J3: MH04ES6585
A4: Pumpa Hijli | B4: 8655585851 | C4: mumbai | D4: Justdial | E4: 41218.458 | F4: Soham tours and travels | G4: P2P | H4: 170 | I4: 365 | J4: MH04ES6585
A5: Sonika | B5: 9967759001 | C5: mumbai | D5: Call center | E5: 41219.333 | F5: Soham tours and travels | G5: P2P | H5: 195 | I5: 229 | J5: MH04ES6585
A6: Smita Chaturvedi | B6: 9769632275 | C6: mumbai | D6: Call center | E6: 41219.385 | F6: Soham tours and travels | G6: P2P | H6: 100 | I6: 229 | J6: MH04ES6585
A7: Vishit Trivedi | B7: 9867524419 | C7: mumbai | D7: Other sources | E7: 41584.448 | F7: Soham tours and travels | G7: P2P | H7: 100 | I7: 229 | J7: MH04ES6585
A8: Pushkar | B8: 9619932740 | C8: mumbai | D8: Call center | E8: 41584.448 | F8: Soham tours and travels | G8: P2P | H8: 283 | I8: 229 | J8: MH04ES6585
A9: Rituparno | B9: 9167980446 | C9: mumbai | D9: Call center | E9: 41584.448 | F9: Soham tours and travels | G9: P2P | H9: 244 | I9: 229 | J9: MH04ES6585
A10: Hanisha Desai | B10: 9987781593 | C10: mumbai | D10: Call center | E10: 41584.448 | F10: Soham tours and travels | G10: P2P | H10: 277 | I10: 229 | J10: MH04ES6585
A11: Atul Phull | B11: 9820346445 | C11: mumbai | D11: Call center | E11: 41584.448 | F11: Wasim Travels | G11: P2P | H11: 435 | I11: 415 | J11: MH04ES2628
A12: Ashwin Ramanathan | B12: 9820187763 | C12: mumbai | D12: Call center | E12: 41584.448 | F12: Wasim Travels | G12: P2P | H12: 220 | I12: 210 | J12: MH04ES2628
A13: Zenovia Pardiwalla | B13: 9820944920 | C13: mumbai | D13: Call center | E13: 41584.448 | F13: Wasim Travels | G13: P2P | H13: 100 | I13: 52 | J13: MH04ES2628
... A4324: Pankaj Chhaparwal | B4324: 9886072278 | C4324: delhi | D4324: Call center | E4324: 41218.417 | F4324: Shree Krishna Travel | G4324: Local Full Day | H4324: 1160 | I4324: 1000 | J4324: HR66A1626
A4325: Tushar Banode(Cordyfsoftwareindiapvtltd) | B4325: 9820043309 | C4325: delhi | D4325: Call center | E4325: 41218.573 | F4325: Shree Krishna Travel | G4325: Local Full Day | H4325: 1032 | I4325: 928
A4326: Charu Bohra | B4326: 9739912223 | C4326: delhi | D4326: Other sources | E4326: 41219.51 | F4326: Shree Krishna Travel | G4326: Local Full Day | H4326: 2587 | I4326: 2278 | J4326: HR66A1626
A4327: Surma Daf | B4327: 9830401482 | C4327: delhi | D4327: Call center | E4327: 41219.562 | F4327: Shree Krishna Travel | G4327: Local Full Day | H4327: 1100 | I4327: 950 | J4327: DL1YC8110
A4328: Kumaravel | B4328: 9940082205 | C4328: delhi | D4328: Other sources | E4328: 41220.385 | F4328: Shree Krishna Travel | G4328: Local Full Day | H4328: 1340 | I4328: 1150
A4329: Sanjay Khandkar | B4329: 9892179801 | C4329: delhi | D4329: Web | E4329: 41216.354 | F4329: Sandeep kumar | G4329: Local Full Day | H4329: 1326 | I4329: 1124 | J4329: UP14CT8505
A4330: Vikas Kumar | B4330: 9716371765 | C4330: delhi | D4330: Call center | E4330: 41220.042 | F4330: Rakesh Kapoor | G4330: P2P | H4330: 644 | I4330: 709 | J4330: DL1YC9578
A4331: Mr Aman Agarwal | B4331: 9818941100 | C4331: delhi | D4331: Call center | E4331: 41220.125 | F4331: Rakesh Kapoor | G4331: P2P | H4331: 500 | I4331: 639 | J4331: DL1YC9578
A4332: Yai Khomba | B4332: 8447099810 | C4332: delhi | D4332: Call center | E4332: 41220.208 | F4332: Rakesh Kapoor | G4332: P2P | H4332: 330 | I4332: 369 | J4332: DL1YC9578
A4333: Naseem Alam | B4333: 8130788996 | C4333: delhi | D4333: Call center | E4333: 41214.208 | F4333: Bharat Tour & Travels | G4333: P2P | H4333: 487 | I4333: 568 | J4333: UP16AT9415
A4334: SWETA SINGH | B4334: 9999720606 | C4334: delhi | D4334: Justdial | E4334: 41214.25 | F4334: Bharat Tour & Travels | G4334: P2P | H4334: 235 | I4334: 272 | J4334: UP16AT9415
A4335: Ainul Mazumdar | B4335: 9560886392 | C4335: delhi | D4335: Other sources | E4335: 41214.385 | F4335: Bharat Tour & Travels | G4335: P2P | H4335: 135 | I4335: 456 | J4335: DL1YC6449
A4336: Dilip Kumar | B4336: 9790974477 | C4336: delhi | D4336: Call center | E4336: 41214.458 | F4336: Bharat Tour & Travels | G4336: Local Half Day | H4336: 600 | I4336: 500 | J4336: DL1YC6449
A4337: Tushar | B4337: 9810555248 | C4337: delhi | D4337: Call center | E4337: 41214.719 | F4337: Bharat Tour & Travels | G4337: P2P | H4337: 100 | I4337: 161 | J4337: UP16BT2302
A4338: Atul Gupta | B4338: 9717287654 | C4338: delhi | D4338: Other sources | E4338: 41214.74 | F4338: Bharat Tour & Travels | G4338: P2P | H4338: 607 | I4338: 1242 | J4338: UP16BT2302
A4339: GURBAKSH | B4339: 9717393099 | C4339: delhi | D4339: Justdial | E4339: 41214.792 | F4339: Bharat Tour & Travels | G4339: P2P | H4339: 240 | I4339: 842 | J4339: DL1YC6449
A4340: Joy Sain | B4340: 9871914175 | C4340: delhi | D4340: Call center | E4340: 41214.823 | F4340: Bharat Tour & Travels | G4340: P2P | H4340: 227 | I4340: 798 | J4340: DL1YC6449
... A4481: Priti Karia | B4481: 9582214979 | C4481: delhi | D4481: Call center | E4481: 41217.5 | F4481: BKN Tour and Travels | G4481: Local Full Day | H4481: 1008 | I4481: 857 | J4481: HR55HT8984
A4482: Saurebh Gupta | B4482: 9823006673 | C4482: delhi | D4482: Call center | E4482: 41215.792 | F4482: Shyam Tourist Taxi Service | G4482: Outstation | H4482: 2700 | I4482: 2125
A4483: Rajesh Ahuja | B4483: 9167993517 | C4483: delhi | D4483: Call center | E4483: 41216.344 | F4483: Shyam Tourist Taxi Service | G4483: Local Full Day | H4483: 1280 | I4483: 1100 | J4483: DL1YC2617
A4484: propoyz event solution | B4484: 9313987345 | C4484: delhi | D4484: Justdial | E4484: 41217.083 | F4484: Shyam Tourist Taxi Service | G4484: Local Full Day | H4484: 1700 | I4484: 1430 | J4484: DL1ZZ1024
A4485: Sahil Khurmi | B4485: 9899119711 | C4485: delhi | D4485: Call center | E4485: 41219.521 | F4485: Shyam Tourist Taxi Service | G4485: Local Full Day | H4485: 1100 | I4485: 950
A4486: RADHIKA MALHOTRA | B4486: 9560055177 | C4486: delhi | D4486: Other sources | E4486: 41219.583 | F4486: Shyam Tourist Taxi Service | G4486: Local Full Day | H4486: 1100 | I4486: 900 | J4486: DL1YC2617
A4487: Sanjay Basak | B4487: 9650806289 | C4487: delhi | D4487: Other sources | E4487: 41220.396 | F4487: Shyam Tourist Taxi Service | G4487: Local Full Day | H4487: 1640 | I4487: 1407 | J4487: DL1YC2617
A4488: Amarpreet Singh | B4488: 9899116116 | C4488: delhi | D4488: Other sources | E4488: 41220.583 | F4488: Shyam Tourist Taxi Service | G4488: Local Full Day | H4488: 1340 | I4488: 1150
A4489: Ashutosh Joshi | B4489: 9769141942 | C4489: delhi | D4489: Mobile App | E4489: 41215.458 | F4489: Gopal Singh | G4489: P2P | H4489: 111 | I4489: 263 | J4489: HR55PT3788
A4490: dharme4nder | B4490: 9953217479 | C4490: delhi | D4490: Call center | E4490: 41215.542 | F4490: Gopal Singh | G4490: P2P | H4490: 348 | I4490: 790 | J4490: HR55PT3788
A4491: Charul | B4491: 9711210177 | C4491: delhi | D4491: Web | E4491: 41215.625 | F4491: Gopal Singh | G4491: P2P | H4491: 109 | I4491: 259 | J4491: HR55PT3788
A4492: Rinku sing | B4492: 9699457477 | C4492: delhi | D4492: Call center | E4492: 41215.802 | F4492: Gopal Singh | G4492: P2P | H4492: 472 | I4492: 1114 | J4492: HR55PT3788
A4493: arthy | B4493: 7838338456 | C4493: delhi | D4493: Call center | E4493: 41216.333 | F4493: Gopal Singh | G4493: P2P | H4493: 414 | I4493: 962 | J4493: HR55PT3788
A4494: Jaswinder Gandhi | B4494: 9871116862 | C4494: delhi | D4494: Call center | E4494: 41216.562 | F4494: Gopal Singh | G4494: P2P | H4494: 112 | I4494: 263 | J4494: HR55PT3788
A4495: Vivek Arora | B4495: 9958004834 | C4495: delhi | D4495: Mobile App | E4495: 41216.771 | F4495: Gopal Singh | G4495: P2P | H4495: 110 | I4495: 259 | J4495: HR55PT3788
A4496: Shabdraaj | B4496: 9949997612 | C4496: delhi | D4496: Call center | E4496: 41216.875 | F4496: Gopal Singh | G4496: P2P | H4496: 135 | I4496: 324 | J4496: HR55PT3788
A4497: Divesh Sethy | B4497: 9582279814 | C4497: delhi | D4497: Call center | E4497: 41217.708 | F4497: Gopal Singh | G4497: P2P | H4497: 367 | I4497: 868 | J4497: HR55PT3788
A4498: TUHINA | B4498: 9810684808 | C4498: delhi | D4498: Justdial | E4498: 41218.292 | F4498: Gopal Singh | G4498: P2P | H4498: 415 | I4498: 967 | J4498: HR55PT3788
A4499: Dr Ashok Duggal | B4499: 9815183593 | C4499: delhi | D4499: Other sources | E4499: 41218.427 | F4499: Gopal Singh | G4499: Local Half Day | H4499: 600 | I4499: 500 | J4499: HR55PT3788
A4500: Mrs Santosh Khanna | B4500: 9818468658 | C4500: delhi | D4500: Other sources | E4500: 41218.729 | F4500: Gopal Singh | G4500: P2P | H4500: 608 | I4500: 1368 | J4500: HR55PT3788
... A4618: ananya tandon | B4618: 9953483966 | C4618: delhi | D4618: Justdial | E4618: 41215.583 | F4618: Harish Nawani | G4618: Local Full Day | H4618: 1080 | I4618: 1095 | J4618: UP16T0546
A4619: NITIN BAJAJ | B4619: 9810201602 | C4619: delhi | D4619: Justdial | E4619: 41215.771 | F4619: Harish Nawani | G4619: Local Half Day | H4619: 1000 | I4619: 1095
A4620: nasr khan | B4620: 9899259696 | C4620: delhi | D4620: Justdial | E4620: 41218.458 | F4620: Harish Nawani | G4620: Local Full Day | H4620: 1000 | I4620: 900
A4621: RAHUL | B4621: 9999448937 | C4621: delhi | D4621: Justdial | E4621: 41214.198 | F4621: Narender Travels | G4621: P2P | H4621: 288 | I4621: 575 | J4621: HR669817
A4622: Mr. Bharat Jain | B4622: 9810203728 | C4622: delhi | D4622: Web | E4622: 41214.292 | F4622: Narender Travels | G4622: P2P | H4622: 264 | I4622: 528 | J4622: HR669817
A4623: Jaswinder Gandhi | B4623: 9871116862 | C4623: delhi | D4623: Call center | E4623: 41214.375 | F4623: Narender Travels | G4623: P2P | H4623: 116 | I4623: 241 | J4623: HR669337
A4624: Samrat Yadav | B4624: 9910048147 | C4624: delhi | D4624: Call center | E4624: 41214.458 | F4624: Narender Travels | G4624: P2P | H4624: 283 | I4624: 565 | J4624: HR669337
A4625: Ainul Mazumdar | B4625: 9560886392 | C4625: delhi | D4625: Other sources | E4625: 41214.76 | F4625: Narender Travels | G4625: P2P | H4625: 124 | I4625: 357 | J4625: HR669818
A4626: Shweta Chhagani | B4626: 9910128100 | C4626: delhi | D4626: Call center | E4626: 41214.833 | F4626: Narender Travels | G4626: P2P | H4626: 162 | I4626: 342 | J4626: HR669817
A4627: Mausam Ghosh | B4627: 9971811600 | C4627: delhi | D4627: Other sources | E4627: 41215.354 | F4627: Narender Travels | G4627: P2P | H4627: 148 | I4627: 451 | J4627: HR669818
A4628: Shweta Chhagani | B4628: 9910128100 | C4628: delhi | D4628: Call center | E4628: 41215.417 | F4628: Narender Travels | G4628: P2P | H4628: 131 | I4628: 407 | J4628: HR669818
A4629: Priya Shukla | B4629: 8527925777 | C4629: delhi | D4629: Web | E4629: 41215.729 | F4629: Narender Travels | G4629: P2P | H4629: 130 | I4629: 280 | J4629: HR669337
A4630: Vibhu Rastogi | B4630: 9650192452 | C4630: delhi | D4630: Other sources | E4630: 41215.75 | F4630: Narender Travels | G4630: P2P | H4630: 481 | I4630: 1443 | J4630: HR669818
A4631: Shabdraaj | B4631: 9949997612 | C4631: delhi | D4631: Call center | E4631: 41215.792 | F4631: Narender Travels | G4631: P2P | H4631: 632 | I4631: 1327 | J4631: HR669337
A4632: Rahul singh | B4632: 9911421751 | C4632: delhi | D4632: Other sources | E4632: 41215.885 | F4632: Narender Travels | G4632: P2P | H4632: 378 | I4632: 755 | J4632: HR669817
... A4735: Manish Sharma | B4735: 9811661373 | C4735: delhi | D4735: Call center | E4735: 41218.542 | F4735: Sanju Tour & Travels | G4735: Local Full Day | H4735: 1220 | I4735: 1000 | J4735: DL1YC8259
A4736: Sumeer Bedi | B4736: 9899102117 | C4736: delhi | D4736: Other sources | E4736: 41220.5 | F4736: Sanju Tour & Travels | G4736: Local Full Day | H4736: 13595 | I4736: 9733
A4737: Rahul Singh | B4737: 9911421751 | C4737: delhi | D4737: Other sources | E4737: 41214.208 | F4737: Ghanshyam Gupta | G4737: P2P | H4737: 462 | I4737: 1234 | J4737: DL1YD0500
A4738: Navdeep chehal | B4738: 9560071615 | C4738: delhi | D4738: Call center | E4738: 41214.708 | F4738: Ghanshyam Gupta | G4738: P2P | H4738: 261 | I4738: 768 | J4738: DL1YD0500
A4739: N Choudhary | B4739: 7667384007 | C4739: delhi | D4739: Call center | E4739: 41215.333 | F4739: Ghanshyam Gupta | G4739: P2P | H4739: 323 | I4739: 1004 | J4739: DL1YD0500
A4740: Shruti Kapoor | B4740: 9820079978 | C4740: delhi | D4740: Call center | E4740: 41215.438 | F4740: Ghanshyam Gupta | G4740: P2P | H4740: 180 | I4740: 561 | J4740: DL1YD0500
A4741: Karan Nayak | B4741: 9930606234 | C4741: delhi | D4741: Mobile App | E4741: 41215.667 | F4741: Ghanshyam Gupta | G4741: P2P | H4741: 162 | I4741: 494 | J4741: DL1YD0500
A4742: RAKESH KUMAR | B4742: 9999598853 | C4742: delhi | D4742: Justdial | E4742: 41215.76 | F4742: Ghanshyam Gupta | G4742: P2P | H4742: 375 | I4742: 1083 | J4742: DL1YD0500
A4743: Ainul Mazumdar | B4743: 9560886392 | C4743: delhi | D4743: Other sources | E4743: 41216.385 | F4743: Ghanshyam Gupta | G4743: P2P | H4743: 132 | I4743: 404 | J4743: DL1YD0500
A4744: Kaushaik ganish | B4744: 9717200419 | C4744: delhi | D4744: Call center | E4744: 41216.458 | F4744: Ghanshyam Gupta | G4744: P2P | H4744: 270 | I4744: 841 | J4744: DL1YD0500
A4745: vijay | B4745: 9916298918 | C4745: delhi | D4745: Web | E4745: 41216.594 | F4745: Ghanshyam Gupta | G4745: P2P | H4745: 125 | I4745: 370 | J4745: DL1YD0500
A4746: Isha | B4746: 9810302677 | C4746: delhi | D4746: Call center | E4746: 41216.677 | F4746: Ghanshyam Gupta | G4746: P2P | H4746: 100 | I4746: 292 | J4746: DL1YD0500
A4747: Himanshu | B4747: 9999997058 | C4747: delhi | D4747: Call center | E4747: 41216.74 | F4747: Ghanshyam Gupta | G4747: P2P | H4747: 401 | I4747: 1195 | J4747: DL1YD0500
A4748: Ashok kumar | B4748: 9818808556 | C4748: delhi | D4748: Justdial | E4748: 41217.385 | F4748: Ghanshyam Gupta | G4748: P2P | H4748: 220 | I4748: 684 | J4748: DL1YD0500
... A4846: NEETESHPALIYA | B4846: 9650447765 | C4846: delhi | D4846: Other sources | E4846: 41220.917 | F4846: Onkar Tour & Travels | G4846: Local Full Day | H4846: 1600 | I4846: 1350 | J4846: DL01ZZ0357
A4847: Satyam | B4847: 9818997046 | C4847: delhi | D4847: Call center | E4847: 41215.812 | F4847: Ajit singh | G4847: Local Full Day | H4847: 1250 | I4847: 1085
A4848: Praful Panchal | B4848: 9967504596 | C4848: delhi | D4848: Call center | E4848: 41220.375 | F4848: Ajit singh | G4848: Local Full Day | H4848: 1100 | I4848: 900 | J4848: DL01YC5331
A4849: Dr. Santosh Pancholi | B4849: 9560406970 | C4849: delhi | D4849: Call center | E4849: 41215.438 | F4849: Jasbir Singh | G4849: Local Full Day | H4849: 1200 | I4849: 1035
A4850: madhu sharma | B4850: 9910062527 | C4850: delhi | D4850: Justdial | E4850: 41217.208 | F4850: Amit Sharma | G4850: Outstation | H4850: 10434 | I4850: 9308 | J4850: DL01BA8609
A4851: Vivek | B4851: 9811454594 | C4851: delhi | D4851: Call center | E4851: 41220.167 | F4851: Amit Sharma | G4851: Outstation | H4851: 20082 | I4851: 21184 | J4851: DL01BA8609
A4852: Jaswinder Gandhi | B4852: 9871116862 | C4852: delhi | D4852: Call center | E4852: 41214.833 | F4852: R & R Resource Management Service | G4852: P2P | H4852: 108 | I4852: 175 | J4852: HR66T8285
A4853: Amitesh Sinha | B4853: 9711843005 | C4853: delhi | D4853: Call center | E4853: 41214.938 | F4853: R & R Resource Management Service | G4853: P2P | H4853: 288 | I4853: 483 | J4853: HR73T3164
A4854: Ankita goel | B4854: 9878997121 | C4854: delhi | D4854: Call center | E4854: 41214.969 | F4854: R & R Resource Management Service | G4854: P2P | H4854: 548 | I4854: 887 | J4854: HR66T8285
A4855: Abhishek Mahanty | B4855: 9711722788 | C4855: delhi | D4855: Call center | E4855: 41215.042 | F4855: R & R Resource Management Service | G4855: P2P | H4855: 100 | I4855: 166 | J4855: HR73T3164
A4856: Joy Sain | B4856: 9871914175 | C4856: delhi | D4856: Call center | E4856: 41215.25 | F4856: R & R Resource Management Service | G4856: P2P | H4856: 307 | I4856: 513 | J4856: HR66T8285
A4857: Jaswinder Gandhi | B4857: 9871116862 | C4857: delhi | D4857: Call center | E4857: 41215.812 | F4857: R & R Resource Management Service | G4857: P2P | H4857: 106 | I4857: 175 | J4857: HR66T8285
A4858: Ananya | B4858: 8010629707 | C4858: delhi | D4858: Justdial | E4858: 41215.99 | F4858: R & R Resource Management Service | G4858: P2P | H4858: 411 | I4858: 673 | J4858: HR66T8285
A4859: Vikram Bahure | B4859: 9650929951 | C4859: delhi | D4859: Web | E4859: 41216.188 | F4859: R & R Resource Management Service | G4859: P2P | H4859: 219 | I4859: 368 | J4859: HR66T8285
A4860: Raghav | B4860: 9811502027 | C4860: delhi | D4860: Call center | E4860: 41216.875 | F4860: R & R Resource Management Service | G4860: P2P | H4860: 191 | I4860: 317 | J4860: HR66T8285
A4861: Nidhi G | B4861: 9619564123 | C4861: delhi | D4861: Call center | E4861: 41216.958 | F4861: R & R Resource Management Service | G4861: P2P | H4861: 321 | I4861: 534 | J4861: HR66T8285
... A4954: s singh | B4954: 9179488408 | C4954: delhi | D4954: Justdial | E4954: 41219.396 | F4954: Yogesh Travels | G4954: Local Full Day | H4954: 1900 | I4954: 1590 | J4954: DL01YB6492
A4955: M.P.Chugh | B4955: 9498732822 | C4955: delhi | D4955: Other sources | E4955: 41219.417 | F4955: Yogesh Travels | G4955: Local Full Day | H4955: 1600 | I4955: 1350
A4956: M.P.Chugh | B4956: 9498732822 | C4956: delhi | D4956: Other sources | E4956: 41220.354 | F4956: Yogesh Travels | G4956: Local Full Day | H4956: 1600 | I4956: 1350 | J4956: HR55T9888
A4957: Arun Kholi | B4957: 9873429612 | C4957: delhi | D4957: Other sources | E4957: 41220.396 | F4957: Yogesh Travels | G4957: Local Full Day | H4957: 2667 | I4957: 2249 | J4957: DL01YB6492
A4958: Gaurav Varshney | B4958: 9560170101 | C4958: delhi | D4958: Other sources | E4958: 41220.917 | F4958: Sunil Kumar Singh | G4958: Local Full Day | H4958: 1622 | I4958: 1372 | J4958: UP16BT0698
...

Sheet QUESTIONS 
A1: Customer Name | B1: Phone | C1: City | D1: Source | E1: Pickup Date | F1: Operator | G1: Service type | H1: Customer bill | I1: Operator bill | J1: Car Number | K1: 1 | L1: Average customer bill by Source and Service type | N1: 1) | S1: 2) | X1: 5)
A2: Akshat Trivedi | B2: 9819086125 | C2: mumbai | D2: Call center | E2: 41218.292 | F2: Soham tours and travels | G2: P2P | H2: 734 | I2: 365 | J2: MH04ES6585 | K2: 2 | L2: Sum of cutomer bill and count of customers by Source | N2: Service type | O2: Source | P2: Average of Customer bill | S2: Source | T2: Sum of Customer bill | U2: Count of Customer bill2 | X2: City | Y2: Average of Customer bill
A3: Ms. Preeti Mehta | B3: 9819065905 | C3: mumbai | D3: Call center | E3: 41218.354 | F3: Soham tours and travels | G3: P2P | H3: 480 | I3: 365 | J3: MH04ES6585 | K3: 3 | L3: Citywise total,min, max, average operator bill | N3: Local Full Day | O3: Call center | P3: 1593.0915 | S3: Call center | T3: 2871660.1 | U3: 5907 | X3: bangalore | Y3: 541.58631
A4: Pumpa Hijli | B4: 8655585851 | C4: mumbai | D4: Justdial | E4: 41218.458 | F4: Soham tours and travels | G4: P2P | H4: 170 | I4: 365 | J4: MH04ES6585 | K4: 4 | L4: Keep City in Fiter and create Operator wise Avg Customer bill | O4: Justdial | P4: 1415.75 | S4: Justdial | T4: 94282 | U4: 139 | X4: delhi | Y4: 649.67485 | AH4: .
A5: Sonika | B5: 9967759001 | C5: mumbai | D5: Call center | E5: 41219.333 | F5: Soham tours and travels | G5: P2P | H5: 195 | I5: 229 | J5: MH04ES6585 | K5: 5 | L5: Create Average customer bill by City | O5: Mobile (Web) | P5: 1457 | S5: Mobile (Web) | T5: 26359 | U5: 69 | X5: mumbai | Y5: 450.46543
A6: Smita Chaturvedi | B6: 9769632275 | C6: mumbai | D6: Call center | E6: 41219.385 | F6: Soham tours and travels | G6: P2P | H6: 100 | I6: 229 | J6: MH04ES6585 | K6: 6 | L6: Create Min,Max Operator bill by City | O6: Other sources | P6: 1905.8582 | S6: Mobile App | T6: 134833.6 | U6: 492 | X6: (blank)
A7: Vishit Trivedi | B7: 9867524419 | C7: mumbai | D7: Other sources | E7: 41584.448 | F7: Soham tours and travels | G7: P2P | H7: 100 | I7: 229 | J7: MH04ES6585 | K7: 7 | L7: Highest salary Operator wise | O7: Web | P7: 1532.9444 | S7: Other sources | T7: 428566.22 | U7: 605 | X7: Grand Total | Y7: 502.12803
A8: Pushkar | B8: 9619932740 | C8: mumbai | D8: Call center | E8: 41584.448 | F8: Soham tours and travels | G8: P2P | H8: 283 | I8: 229 | J8: MH04ES6585 | K8: 8 | L8: Average Customer bill where city mumbai and wasim travels | N8: Local Full Day Total | P8: 1646.7787 | S8: Web | T8: 467851 | U8: 801
A9: Rituparno | B9: 9167980446 | C9: mumbai | D9: Call center | E9: 41584.448 | F9: Soham tours and travels | G9: P2P | H9: 244 | I9: 229 | J9: MH04ES6585 | K9: 9 | L9: Create suitable charts for above 8 questions. If not, then ignore | N9: Local Half Day | O9: Call center | P9: 880.55797 | S9: (blank)
A10: Hanisha Desai | B10: 9987781593 | C10: mumbai | D10: Call center | E10: 41584.448 | F10: Soham tours and travels | G10: P2P | H10: 277 | I10: 229 | J10: MH04ES6585 | K10: 10 | L10: Count of operators by source by city | O10: Justdial | P10: 818.33333 | S10: Grand Total | T10: 4023551.9 | U10: 8013 | X10: 6)
A11: Atul Phull | B11: 9820346445 | C11: mumbai | D11: Call center | E11: 41584.448 | F11: Wasim Travels | G11: P2P | H11: 435 | I11: 415 | J11: MH04ES2628 | O11: Mobile (Web) | P11: 900 | R11: rows > coums | X11: City | Y11: Min of Operator bill | Z11: Max of Operator bill2
A12: Ashwin Ramanathan | B12: 9820187763 | C12: mumbai | D12: Call center | E12: 41584.448 | F12: Wasim Travels | G12: P2P | H12: 220 | I12: 210 | J12: MH04ES2628 | O12: Other sources | P12: 760.09615 | X12: bangalore | Y12: 15 | Z12: 11574
A13: Zenovia Pardiwalla | B13: 9820944920 | C13: mumbai | D13: Call center | E13: 41584.448 | F13: Wasim Travels | G13: P2P | H13: 100 | I13: 52 | J13: MH04ES2628 | O13: Web | P13: 757.08333 | S13: 3) | X13: delhi | Y13: 24 | Z13: 26222
A14: Namrata varma | B14: 9920309925 | C14: mumbai | D14: Call center | E14: 41584.448 | F14: Wasim Travels | G14: P2P | H14: 183 | I14: 153 | J14: MH04ES2628 | N14: Local Half Day Total | P14: 839.43953 | S14: City | T14: Min of Operator bill | U14: Max of Operator bill2 | V14: Average of Operator bill3 | X14: mumbai | Y14: 21 | Z14: 22045
A15: Vyas | B15: 9833720552 | C15: mumbai | D15: Call center | E15: 41584.448 | F15: Wasim Travels | G15: P2P | H15: 249 | I15: 236 | J15: MH04ES2628 | N15: Outstation | O15: Call center | P15: 4645.4225 | S15: bangalore | T15: 15 | U15: 11574 | V15: 645.872 | X15: Grand Total | Y15: 15 | Z15: 26222
A16: Ms.Malika | B16: 9820088016 | C16: mumbai | D16: Call center | E16: 41584.448 | F16: Wasim Travels | G16: P2P | H16: 450 | I16: 292 | J16: MH04ES2628 | O16: Justdial | P16: 7583.5 | S16: delhi | T16: 24 | U16: 26222 | V16: 843.6875
A17: Bhavish Aggarwal | B17: 9321069756 | C17: mumbai | D17: Mobile App | E17: 41215.302 | F17: Wasim Travels | G17: P2P | H17: 299 | I17: 284 | J17: MH04ES2628 | O17: Other sources | P17: 7778.6923 | S17: mumbai | T17: 21 | U17: 22045 | V17: 411.71115
A18: Nihar | B18: 9820814890 | C18: mumbai | D18: Call center | E18: 41215.375 | F18: Wasim Travels | G18: P2P | H18: 417 | I18: 400 | J18: MH04ES2628 | O18: Web | P18: 5296.1429 | S18: (blank) | X18: 8)
A19: Kalyani | B19: 9821327568 | C19: mumbai | D19: Call center | E19: 41215.427 | F19: Wasim Travels | G19: P2P | H19: 182 | I19: 164 | J19: MH04ES2628 | N19: Outstation Total | P19: 5254.9483 | S19: Grand Total | T19: 15 | U19: 26222 | V19: 537.60839
A20: Gauri | B20: 9930009874 | C20: mumbai | D20: Call center | E20: 41215.5 | F20: Wasim Travels | G20: P2P | H20: 525 | I20: 486 | J20: MH04ES2628 | N20: P2P | O20: Call center | P20: 390.14295 | S20: City | T20: (All) | X20: Average of Customer bill | Y20: Operator
A21: Anita paswani | B21: 9821634883 | C21: mumbai | D21: Call center | E21: 41215.635 | F21: Wasim Travels | G21: P2P | H21: 226 | I21: 181 | J21: MH04ES2628 | O21: Justdial | P21: 322 | S21: 4) | X21: City | Y21: Wasim Travels | Z21: Grand Total
A22: Arindam Sarkar | B22: 9833934713 | C22: mumbai | D22: Call center | E22: 41215.75 | F22: Wasim Travels | G22: P2P | H22: 312 | I22: 263 | J22: MH04ES2628 | O22: Mobile (Web) | P22: 306.73438 | S22: Operator | T22: Average of Customer bill | X22: mumbai | Y22: 275.09091 | Z22: 275.09091
A23: Mr.Manav | B23: 9930461609 | C23: mumbai | D23: Call center | E23: 41216.521 | F23: Wasim Travels | G23: P2P | H23: 146 | I23: 137 | J23: MH04ES2628 | O23: Mobile App | P23: 274.05203 | S23: A Q Tours & Travels | T23: 833.5 | X23: Grand Total | Y23: 275.09091 | Z23: 275.09091
A24: Ms.Vandita | B24: 9820571311 | C24: mumbai | D24: Call center | E24: 41216.646 | F24: Wasim Travels | G24: P2P | H24: 305 | I24: 280 | J24: MH04ES2628 | O24: Other sources | P24: 338.74359 | S24: Aastha Tours & Travels | T24: 295.41579
A25: Smita Chaturvedi | B25: 9769632275 | C25: mumbai | D25: Call center | E25: 41216.74 | F25: Wasim Travels | G25: P2P | H25: 104 | I25: 94 | J25: MH04ES2628 | O25: Web | P25: 348.742 | S25: Abdul Jabbar | T25: 799.52174 | X25: 10)
A26: Sanjiv Golani | B26: 9930900748 | C26: mumbai | D26: Call center | E26: 41216.792 | F26: Wasim Travels | G26: P2P | H26: 416 | I26: 345 | J26: MH04ES2628 | N26: P2P Total | P26: 373.34319 | S26: Abhay Singh | T26: 348.17949 | X26: Count of Operator | Y26: City
A27: Ms Sanjukta | B27: 8800799022 | C27: mumbai | D27: Call center | E27: 41217.365 | F27: Wasim Travels | G27: P2P | H27: 572 | I27: 551 | J27: MH04ES2628 | N27: Grand Total | P27: 502.12803 | S27: Abhuti Tours & Travels | T27: 2472.5 | X27: Source | Y27: bangalore | Z27: delhi | AA27: mumbai | AB27: (blank) | AC27: Grand Total
A28: Panchaki | B28: 9819827228 | C28: mumbai | D28: Call center | E28: 41217.5 | F28: Wasim Travels | G28: P2P | H28: 530 | I28: 511 | J28: MH04ES2628 | S28: Adi Shakthi Travels | T28: 731.17073 | X28: Call center | Y28: 2358 | Z28: 353 | AA28: 3196 | AC28: 5907
A29: Mansi mittal | B29: 9769853670 | C29: mumbai | D29: Call center | E29: 41217.677 | F29: Wasim Travels | G29: P2P | H29: 238 | I29: 177 | J29: MH04ES2628 | S29: Aditya Tours & Travels | T29: 348.02 | X29: Justdial | Y29: 8 | Z29: 91 | AA29: 40 | AC29: 139
A30: Vikas Kavatur | B30: 9819435396 | C30: mumbai | D30: Call center | E30: 41217.792 | F30: Wasim Travels | G30: P2P | H30: 154 | I30: 137 | J30: MH04ES2628 | S30: Adnan Travels | T30: 2825.1429 | X30: Mobile (Web) | Y30: 41 | Z30: 1 | AA30: 27 | AC30: 69
A31: Sarafaraz | B31: 7208008001 | C31: mumbai | D31: Other sources | E31: 41218.323 | F31: Wasim Travels | G31: P2P | H31: 451 | I31: 440 | J31: MH04ES2628 | S31: Ajit singh | T31: 1175 | X31: Mobile App | Y31: 192 | Z31: 27 | AA31: 273 | AC31: 492
A32: Zeenal | B32: 9820493002 | C32: mumbai | D32: Mobile App | E32: 41218.396 | F32: Wasim Travels | G32: P2P | H32: 317 | I32: 288 | J32: MH04ES2628 | S32: Akash Travels | T32: 244.66154 | X32: Other sources | Y32: 4 | Z32: 150 | AA32: 451 | AC32: 605
A33: Ms.Saeeda | B33: 9820027484 | C33: mumbai | D33: Call center | E33: 41218.521 | F33: Wasim Travels | G33: P2P | H33: 129 | I33: 113 | J33: MH04ES2628 | S33: Amit Sharma | T33: 15258 | X33: Web | Y33: 436 | Z33: 66 | AA33: 299 | AC33: 801
A34: P J shah | B34: 9820350790 | C34: mumbai | D34: Call center | E34: 41218.562 | F34: Wasim Travels | G34: P2P | H34: 100 | I34: 44 | J34: MH04ES2628 | S34: Anand | T34: 3133.3333 | X34: (blank)
A35: Shefali Shah | B35: 9820003087 | C35: mumbai | D35: Other sources | E35: 41218.729 | F35: Wasim Travels | G35: P2P | H35: 485 | I35: 450 | J35: MH04ES2628 | S35: Ananth | T35: 1478.3333 | X35: Grand Total | Y35: 3039 | Z35: 688 | AA35: 4286 | AC35: 8013
A36: Lakshmy Subramanian | B36: 9833095492 | C36: mumbai | D36: Call center | E36: 41218.812 | F36: Wasim Travels | G36: P2P | H36: 352 | I36: 339 | J36: MH04ES2628 | S36: Anas Travels | T36: 227.72222
A37: Sarfaraz | B37: 7208008001 | C37: mumbai | D37: Other sources | E37: 41220.333 | F37: Wasim Travels | G37: P2P | H37: 157 | I37: 149 | J37: MH04ES2628 | S37: Anil kumar | T37: 436.37931
A38: Beelal Qureshi | B38: 9004388128 | C38: mumbai | D38: Call center | E38: 41220.385 | F38: Wasim Travels | G38: P2P | H38: 122 | I38: 88 | J38: MH04ES2628 | S38: Anjanappa J | T38: 429.38095
A39: Jayant Shetty | B39: 9820083842 | C39: mumbai | D39: Call center | E39: 41220.458 | F39: Wasim Travels | G39: P2P | H39: 259 | I39: 219 | J39: MH04ES2628 | S39: Armaan Tours and Travels | T39: 1500
A40: Siddhi Gaunekar | B40: 9819784663 | C40: mumbai | D40: Call center | E40: 41220.521 | F40: Wasim Travels | G40: P2P | H40: 246 | I40: 219 | J40: MH04ES2628 | S40: Arnav Travels | T40: 338.5
A41: Lovina Noronha | B41: 9769744023 | C41: mumbai | D41: Call center | E41: 41220.667 | F41: Wasim Travels | G41: P2P | H41: 153 | I41: 143 | J41: MH04ES2628 | S41: Arvind Kumar | T41: 317.4375
A42: Ravi Mathur | B42: 9930144578 | C42: mumbai | D42: Web | E42: 41220.75 | F42: Wasim Travels | G42: P2P | H42: 144 | I42: 134 | J42: MH04ES2628 | S42: Ashish Travels (Fxied) | T42: 380.62581
A43: Marlon Mangabat | B43: 9029921350 | C43: mumbai | D43: Call center | E43: 41220.812 | F43: Wasim Travels | G43: P2P | H43: 100 | I43: 67 | J43: MH04ES2628 | S43: Ashok R | T43: 1169
A44: Bhavish Aggarwal | B44: 9321069756 | C44: mumbai | D44: Mobile (Web) | E44: 41214.01 | F44: Samiksha Travels | G44: P2P | H44: 111 | I44: 117 | J44: MH01AM4767 | S44: Ashraf Travels | T44: 289.31429
A45: Hitesh Chawla | B45: 9820385131 | C45: mumbai | D45: Call center | E45: 41214.01 | F45: Samiksha Travels | G45: P2P | H45: 814.8 | I45: 827 | J45: MH02WA7879 | S45: Ashtavinayak Cars | T45: 311.83364
A46: Nilesh Petkar | B46: 9867788062 | C46: mumbai | D46: Call center | E46: 41214.177 | F46: Samiksha Travels | G46: P2P | H46: 462 | I46: 510 | J46: MH01AM4767 | S46: Asma Tours & Travels | T46: 352.05205
A47: Ms. Khushnum Patel | B47: 9920639905 | C47: mumbai | D47: Web | E47: 41214.229 | F47: Samiksha Travels | G47: P2P | H47: 247 | I47: 271 | J47: MH02WA7878 | S47: Atharva Tours and Travels | T47: 3053.5
... A337: Pragya | B337: 9886599067 | C337: mumbai | D337: Call center | E337: 41215.333 | F337: Rent N Travels | G337: P2P | H337: 245 | I337: 255 | J337: MH02WA7842 | S337: Yogesh Travels | T337: 1793.7
A338: Choudhary | B338: 9819115248 | C338: mumbai | D338: Call center | E338: 41215.344 | F338: Rent N Travels | G338: P2P | H338: 354 | I338: 390 | J338: MH04ES5746 | S338: (blank)
A339: Daraius Fraser | B339: 9821127980 | C339: mumbai | D339: Call center | E339: 41215.365 | F339: Rent N Travels | G339: P2P | H339: 175 | I339: 159 | J339: MH04ES6271 | S339: Grand Total | T339: 502.12803
A340: Santosh Verma | B340: 9820069776 | C340: mumbai | D340: Web | E340: 41215.375 | F340: Rent N Travels | G340: P2P | H340: 148 | I340: 147 | J340: MH04ES5294
A341: Ms.Sheetal | B341: 9820277568 | C341: mumbai | D341: Other sources | E341: 41215.396 | F341: Rent N Travels | G341: P2P | H341: 275 | I341: 254 | J341: MH02WA7843
A342: Mr. Sarafaraz | B342: 7208008001 | C342: mumbai | D342: Other sources | E342: 41215.396 | F342: Rent N Travels | G342: P2P | H342: 378 | I342: 416 | J342: MH02WA7842
A343: Marlon Mangabat | B343: 9029921350 | C343: mumbai | D343: Call center | E343: 41215.438 | F343: Rent N Travels | G343: P2P | H343: 215 | I343: 236 | J343: MH04ES5746
A344: Ms patel | B344: 9819158749 | C344: mumbai | D344: Call center | E344: 41215.438 | F344: Rent N Travels | G344: P2P | H344: 406 | I344: 314 | J344: MH04ES6271
A345: Azina Rajan | B345: 9820040628 | C345: mumbai | D345: Call center | E345: 41215.438 | F345: Rent N Travels | G345: P2P | H345: 179 | I345: 173 | J345: MH04ES5294
A346: Shan Mundo | B346: 9768175597 | C346: mumbai | D346: Call center | E346: 41215.458 | F346: Rent N Travels | G346: P2P | H346: 1128.4 | I346: 740 | J346: MH02WA7843
A347: Jatin Jain | B347: 9867064274 | C347: mumbai | D347: Call center | E347: 41215.521 | F347: Rent N Travels | G347: P2P | H347: 162.4 | I347: 130 | J347: MH02WA7754
A348: Nidhi Batavia | B348: 9820642946 | C348: mumbai | D348: Call center | E348: 41215.542 | F348: Rent N Travels | G348: P2P | H348: 271 | I348: 280 | J348: MH04ES5746
A349: punit vicxxi | B349: 9820395431 | C349: mumbai | D349: Call center | E349: 41215.583 | F349: Rent N Travels | G349: P2P | H349: 1009 | I349: 1118 | J349: MH04ES5294
A350: Hameed Manyar | B350: 9373712567 | C350: mumbai | D350: Call center | E350: 41215.583 | F350: Rent N Travels | G350: P2P | H350: 408.8 | I350: 413 | J350: MH04ES6271
A351: Nidhi Choudhary | B351: 9930440991 | C351: mumbai | D351: Call center | E351: 41215.615 | F351: Rent N Travels | G351: P2P | H351: 253 | I351: 225 | J351: MH02WA7754
... A4324: Pankaj Chhaparwal | B4324: 9886072278 | C4324: delhi | D4324: Call center | E4324: 41218.417 | F4324: Shree Krishna Travel | G4324: Local Full Day | H4324: 1160 | I4324: 1000 | J4324: HR66A1626
A4325: Tushar Banode(Cordyfsoftwareindiapvtltd) | B4325: 9820043309 | C4325: delhi | D4325: Call center | E4325: 41218.573 | F4325: Shree Krishna Travel | G4325: Local Full Day | H4325: 1032 | I4325: 928
A4326: Charu Bohra | B4326: 9739912223 | C4326: delhi | D4326: Other sources | E4326: 41219.51 | F4326: Shree Krishna Travel | G4326: Local Full Day | H4326: 2587 | I4326: 2278 | J4326: HR66A1626
A4327: Surma Daf | B4327: 9830401482 | C4327: delhi | D4327: Call center | E4327: 41219.562 | F4327: Shree Krishna Travel | G4327: Local Full Day | H4327: 1100 | I4327: 950 | J4327: DL1YC8110
A4328: Kumaravel | B4328: 9940082205 | C4328: delhi | D4328: Other sources | E4328: 41220.385 | F4328: Shree Krishna Travel | G4328: Local Full Day | H4328: 1340 | I4328: 1150
A4329: Sanjay Khandkar | B4329: 9892179801 | C4329: delhi | D4329: Web | E4329: 41216.354 | F4329: Sandeep kumar | G4329: Local Full Day | H4329: 1326 | I4329: 1124 | J4329: UP14CT8505
A4330: Vikas Kumar | B4330: 9716371765 | C4330: delhi | D4330: Call center | E4330: 41220.042 | F4330: Rakesh Kapoor | G4330: P2P | H4330: 644 | I4330: 709 | J4330: DL1YC9578
A4331: Mr Aman Agarwal | B4331: 9818941100 | C4331: delhi | D4331: Call center | E4331: 41220.125 | F4331: Rakesh Kapoor | G4331: P2P | H4331: 500 | I4331: 639 | J4331: DL1YC9578
A4332: Yai Khomba | B4332: 8447099810 | C4332: delhi | D4332: Call center | E4332: 41220.208 | F4332: Rakesh Kapoor | G4332: P2P | H4332: 330 | I4332: 369 | J4332: DL1YC9578
A4333: Naseem Alam | B4333: 8130788996 | C4333: delhi | D4333: Call center | E4333: 41214.208 | F4333: Bharat Tour & Travels | G4333: P2P | H4333: 487 | I4333: 568 | J4333: UP16AT9415
A4334: SWETA SINGH | B4334: 9999720606 | C4334: delhi | D4334: Justdial | E4334: 41214.25 | F4334: Bharat Tour & Travels | G4334: P2P | H4334: 235 | I4334: 272 | J4334: UP16AT9415
A4335: Ainul Mazumdar | B4335: 9560886392 | C4335: delhi | D4335: Other sources | E4335: 41214.385 | F4335: Bharat Tour & Travels | G4335: P2P | H4335: 135 | I4335: 456 | J4335: DL1YC6449
A4336: Dilip Kumar | B4336: 9790974477 | C4336: delhi | D4336: Call center | E4336: 41214.458 | F4336: Bharat Tour & Travels | G4336: Local Half Day | H4336: 600 | I4336: 500 | J4336: DL1YC6449
A4337: Tushar | B4337: 9810555248 | C4337: delhi | D4337: Call center | E4337: 41214.719 | F4337: Bharat Tour & Travels | G4337: P2P | H4337: 100 | I4337: 161 | J4337: UP16BT2302
A4338: Atul Gupta | B4338: 9717287654 | C4338: delhi | D4338: Other sources | E4338: 41214.74 | F4338: Bharat Tour & Travels | G4338: P2P | H4338: 607 | I4338: 1242 | J4338: UP16BT2302
A4339: GURBAKSH | B4339: 9717393099 | C4339: delhi | D4339: Justdial | E4339: 41214.792 | F4339: Bharat Tour & Travels | G4339: P2P | H4339: 240 | I4339: 842 | J4339: DL1YC6449
A4340: Joy Sain | B4340: 9871914175 | C4340: delhi | D4340: Call center | E4340: 41214.823 | F4340: Bharat Tour & Travels | G4340: P2P | H4340: 227 | I4340: 798 | J4340: DL1YC6449
... A4481: Priti Karia | B4481: 9582214979 | C4481: delhi | D4481: Call center | E4481: 41217.5 | F4481: BKN Tour and Travels | G4481: Local Full Day | H4481: 1008 | I4481: 857 | J4481: HR55HT8984
A4482: Saurebh Gupta | B4482: 9823006673 | C4482: delhi | D4482: Call center | E4482: 41215.792 | F4482: Shyam Tourist Taxi Service | G4482: Outstation | H4482: 2700 | I4482: 2125
A4483: Rajesh Ahuja | B4483: 9167993517 | C4483: delhi | D4483: Call center | E4483: 41216.344 | F4483: Shyam Tourist Taxi Service | G4483: Local Full Day | H4483: 1280 | I4483: 1100 | J4483: DL1YC2617
A4484: propoyz event solution | B4484: 9313987345 | C4484: delhi | D4484: Justdial | E4484: 41217.083 | F4484: Shyam Tourist Taxi Service | G4484: Local Full Day | H4484: 1700 | I4484: 1430 | J4484: DL1ZZ1024
A4485: Sahil Khurmi | B4485: 9899119711 | C4485: delhi | D4485: Call center | E4485: 41219.521 | F4485: Shyam Tourist Taxi Service | G4485: Local Full Day | H4485: 1100 | I4485: 950
A4486: RADHIKA MALHOTRA | B4486: 9560055177 | C4486: delhi | D4486: Other sources | E4486: 41219.583 | F4486: Shyam Tourist Taxi Service | G4486: Local Full Day | H4486: 1100 | I4486: 900 | J4486: DL1YC2617
A4487: Sanjay Basak | B4487: 9650806289 | C4487: delhi | D4487: Other sources | E4487: 41220.396 | F4487: Shyam Tourist Taxi Service | G4487: Local Full Day | H4487: 1640 | I4487: 1407 | J4487: DL1YC2617
A4488: Amarpreet Singh | B4488: 9899116116 | C4488: delhi | D4488: Other sources | E4488: 41220.583 | F4488: Shyam Tourist Taxi Service | G4488: Local Full Day | H4488: 1340 | I4488: 1150
A4489: Ashutosh Joshi | B4489: 9769141942 | C4489: delhi | D4489: Mobile App | E4489: 41215.458 | F4489: Gopal Singh | G4489: P2P | H4489: 111 | I4489: 263 | J4489: HR55PT3788
A4490: dharme4nder | B4490: 9953217479 | C4490: delhi | D4490: Call center | E4490: 41215.542 | F4490: Gopal Singh | G4490: P2P | H4490: 348 | I4490: 790 | J4490: HR55PT3788
A4491: Charul | B4491: 9711210177 | C4491: delhi | D4491: Web | E4491: 41215.625 | F4491: Gopal Singh | G4491: P2P | H4491: 109 | I4491: 259 | J4491: HR55PT3788
A4492: Rinku sing | B4492: 9699457477 | C4492: delhi | D4492: Call center | E4492: 41215.802 | F4492: Gopal Singh | G4492: P2P | H4492: 472 | I4492: 1114 | J4492: HR55PT3788
A4493: arthy | B4493: 7838338456 | C4493: delhi | D4493: Call center | E4493: 41216.333 | F4493: Gopal Singh | G4493: P2P | H4493: 414 | I4493: 962 | J4493: HR55PT3788
A4494: Jaswinder Gandhi | B4494: 9871116862 | C4494: delhi | D4494: Call center | E4494: 41216.562 | F4494: Gopal Singh | G4494: P2P | H4494: 112 | I4494: 263 | J4494: HR55PT3788
A4495: Vivek Arora | B4495: 9958004834 | C4495: delhi | D4495: Mobile App | E4495: 41216.771 | F4495: Gopal Singh | G4495: P2P | H4495: 110 | I4495: 259 | J4495: HR55PT3788
A4496: Shabdraaj | B4496: 9949997612 | C4496: delhi | D4496: Call center | E4496: 41216.875 | F4496: Gopal Singh | G4496: P2P | H4496: 135 | I4496: 324 | J4496: HR55PT3788
A4497: Divesh Sethy | B4497: 9582279814 | C4497: delhi | D4497: Call center | E4497: 41217.708 | F4497: Gopal Singh | G4497: P2P | H4497: 367 | I4497: 868 | J4497: HR55PT3788
A4498: TUHINA | B4498: 9810684808 | C4498: delhi | D4498: Justdial | E4498: 41218.292 | F4498: Gopal Singh | G4498: P2P | H4498: 415 | I4498: 967 | J4498: HR55PT3788
A4499: Dr Ashok Duggal | B4499: 9815183593 | C4499: delhi | D4499: Other sources | E4499: 41218.427 | F4499: Gopal Singh | G4499: Local Half Day | H4499: 600 | I4499: 500 | J4499: HR55PT3788
A4500: Mrs Santosh Khanna | B4500: 9818468658 | C4500: delhi | D4500: Other sources | E4500: 41218.729 | F4500: Gopal Singh | G4500: P2P | H4500: 608 | I4500: 1368 | J4500: HR55PT3788
... A4618: ananya tandon | B4618: 9953483966 | C4618: delhi | D4618: Justdial | E4618: 41215.583 | F4618: Harish Nawani | G4618: Local Full Day | H4618: 1080 | I4618: 1095 | J4618: UP16T0546
...

Sheet vlookup
A1: Customer Name | B1: Phone | C1: City | D1: Source | E1: Pickup Date | F1: Operator | G1: Service type | H1: Customer bill | I1: Operator bill | J1: Car Number
A2: Akshat Trivedi | B2: =VLOOKUP(A2,DATA!A1:J8014,2,0) -> 9819086125 | C2: =VLOOKUP(B2,DATA!B1:K8014,2,0) -> mumbai | D2: =VLOOKUP(C2,DATA!C1:L8014,2,0) -> Call center | E2: =VLOOKUP(D2,DATA!D1:M8014,2,0) -> 41218.292 | F2: =VLOOKUP(E2,DATA!E1:N8014,2,0) -> Soham tours and travels | G2: =VLOOKUP(F2,DATA!F1:O8014,2,0) -> P2P | H2: =VLOOKUP(G2,DATA!G1:P8014,2,0) -> 734 | I2: =VLOOKUP(H2,DATA!H1:Q8014,2,0) -> 365 | J2: =VLOOKUP(I2,DATA!I1:R8014,2,0) -> MH04ES6585
A3: Ms. Preeti Mehta | B3: =VLOOKUP(A3,DATA!A2:J8015,2,0) -> 9819065905 | C3: =VLOOKUP(B3,DATA!B2:K8015,2,0) -> mumbai | D3: =VLOOKUP(C3,DATA!C2:L8015,2,0) -> Call center | E3: =VLOOKUP(D3,DATA!D2:M8015,2,0) -> 41218.292 | F3: =VLOOKUP(E3,DATA!E2:N8015,2,0) -> Soham tours and travels | G3: =VLOOKUP(F3,DATA!F2:O8015,2,0) -> P2P | H3: =VLOOKUP(G3,DATA!G2:P8015,2,0) -> 734 | I3: =VLOOKUP(H3,DATA!H2:Q8015,2,0) -> 365 | J3: =VLOOKUP(I3,DATA!I2:R8015,2,0) -> MH04ES6585
A4: Pumpa Hijli | B4: =VLOOKUP(A4,DATA!A3:J8016,2,0) -> 8655585851 | C4: =VLOOKUP(B4,DATA!B3:K8016,2,0) -> mumbai | D4: =VLOOKUP(C4,DATA!C3:L8016,2,0) -> Call center | E4: =VLOOKUP(D4,DATA!D3:M8016,2,0) -> 41218.354 | F4: =VLOOKUP(E4,DATA!E3:N8016,2,0) -> Soham tours and travels | G4: =VLOOKUP(F4,DATA!F3:O8016,2,0) -> P2P | H4: =VLOOKUP(G4,DATA!G3:P8016,2,0) -> 480 | I4: =VLOOKUP(H4,DATA!H3:Q8016,2,0) -> 365 | J4: =VLOOKUP(I4,DATA!I3:R8016,2,0) -> MH04ES6585
A5: Sonika | B5: =VLOOKUP(A5,DATA!A4:J8017,2,0) -> 9967759001 | C5: =VLOOKUP(B5,DATA!B4:K8017,2,0) -> mumbai | D5: =VLOOKUP(C5,DATA!C4:L8017,2,0) -> Justdial | E5: =VLOOKUP(D5,DATA!D4:M8017,2,0) -> 41218.458 | F5: =VLOOKUP(E5,DATA!E4:N8017,2,0) -> Soham tours and travels | G5: =VLOOKUP(F5,DATA!F4:O8017,2,0) -> P2P | H5: =VLOOKUP(G5,DATA!G4:P8017,2,0) -> 170 | I5: =VLOOKUP(H5,DATA!H4:Q8017,2,0) -> 365 | J5: =VLOOKUP(I5,DATA!I4:R8017,2,0) -> MH04ES6585
A6: Smita Chaturvedi | B6: =VLOOKUP(A6,DATA!A5:J8018,2,0) -> 9769632275 | C6: =VLOOKUP(B6,DATA!B5:K8018,2,0) -> mumbai | D6: =VLOOKUP(C6,DATA!C5:L8018,2,0) -> Call center | E6: =VLOOKUP(D6,DATA!D5:M8018,2,0) -> 41219.333 | F6: =VLOOKUP(E6,DATA!E5:N8018,2,0) -> Soham tours and travels | G6: =VLOOKUP(F6,DATA!F5:O8018,2,0) -> P2P | H6: =VLOOKUP(G6,DATA!G5:P8018,2,0) -> 195 | I6: =VLOOKUP(H6,DATA!H5:Q8018,2,0) -> 229 | J6: =VLOOKUP(I6,DATA!I5:R8018,2,0) -> MH04ES6585
A7: Vishit Trivedi | B7: =VLOOKUP(A7,DATA!A6:J8019,2,0) -> 9867524419 | C7: =VLOOKUP(B7,DATA!B6:K8019,2,0) -> mumbai | D7: =VLOOKUP(C7,DATA!C6:L8019,2,0) -> Call center | E7: =VLOOKUP(D7,DATA!D6:M8019,2,0) -> 41219.385 | F7: =VLOOKUP(E7,DATA!E6:N8019,2,0) -> Soham tours and travels | G7: =VLOOKUP(F7,DATA!F6:O8019,2,0) -> P2P | H7: =VLOOKUP(G7,DATA!G6:P8019,2,0) -> 100 | I7: =VLOOKUP(H7,DATA!H6:Q8019,2,0) -> 229 | J7: =VLOOKUP(I7,DATA!I6:R8019,2,0) -> MH04ES6585
A8: Pushkar | B8: =VLOOKUP(A8,DATA!A7:J8020,2,0) -> 9619932740 | C8: =VLOOKUP(B8,DATA!B7:K8020,2,0) -> mumbai | D8: =VLOOKUP(C8,DATA!C7:L8020,2,0) -> Other sources | E8: =VLOOKUP(D8,DATA!D7:M8020,2,0) -> 41584.448 | F8: =VLOOKUP(E8,DATA!E7:N8020,2,0) -> Soham tours and travels | G8: =VLOOKUP(F8,DATA!F7:O8020,2,0) -> P2P | H8: =VLOOKUP(G8,DATA!G7:P8020,2,0) -> 100 | I8: =VLOOKUP(H8,DATA!H7:Q8020,2,0) -> 229 | J8: =VLOOKUP(I8,DATA!I7:R8020,2,0) -> MH04ES6585
A9: Rituparno | B9: =VLOOKUP(A9,DATA!A8:J8021,2,0) -> 9167980446 | C9: =VLOOKUP(B9,DATA!B8:K8021,2,0) -> mumbai | D9: =VLOOKUP(C9,DATA!C8:L8021,2,0) -> Call center | E9: =VLOOKUP(D9,DATA!D8:M8021,2,0) -> 41584.448 | F9: =VLOOKUP(E9,DATA!E8:N8021,2,0) -> Soham tours and travels | G9: =VLOOKUP(F9,DATA!F8:O8021,2,0) -> P2P | H9: =VLOOKUP(G9,DATA!G8:P8021,2,0) -> 283 | I9: =VLOOKUP(H9,DATA!H8:Q8021,2,0) -> 229 | J9: =VLOOKUP(I9,DATA!I8:R8021,2,0) -> MH04ES6585
A10: Hanisha Desai | B10: =VLOOKUP(A10,DATA!A9:J8022,2,0) -> 9987781593 | C10: =VLOOKUP(B10,DATA!B9:K8022,2,0) -> mumbai | D10: =VLOOKUP(C10,DATA!C9:L8022,2,0) -> Call center | E10: =VLOOKUP(D10,DATA!D9:M8022,2,0) -> 41584.448 | F10: =VLOOKUP(E10,DATA!E9:N8022,2,0) -> Soham tours and travels | G10: =VLOOKUP(F10,DATA!F9:O8022,2,0) -> P2P | H10: =VLOOKUP(G10,DATA!G9:P8022,2,0) -> 244 | I10: =VLOOKUP(H10,DATA!H9:Q8022,2,0) -> 229 | J10: =VLOOKUP(I10,DATA!I9:R8022,2,0) -> MH04ES6585
B13: City | C13: Source
A14: Atul Phull | B14: =VLOOKUP(A14,DATA!A2:J8014,3,TRUE) -> mumbai | C14: =VLOOKUP(A14,DATA!$A$1:$J$8014,4,FALSE) -> Call center
A15: Zenovia Pardiwalla | B15: =VLOOKUP(A15,DATA!A3:J8015,3,TRUE) -> bangalore | C15: =VLOOKUP(A15,DATA!$A$1:$J$8014,4,FALSE) -> Call center
A16: Namrata varma | B16: =VLOOKUP(A16,DATA!A4:J8016,3,TRUE) -> mumbai | C16: =VLOOKUP(A16,DATA!$A$1:$J$8014,4,FALSE) -> Call center
A17: Bhavish Aggarwal | B17: =VLOOKUP(A17,DATA!A5:J8017,3,TRUE) -> mumbai | C17: =VLOOKUP(A17,DATA!$A$1:$J$8014,4,FALSE) -> Mobile App
A18: Pumpa Hijli | B18: =VLOOKUP(A18,DATA!A6:J8018,3,TRUE) -> bangalore | C18: =VLOOKUP(A18,DATA!$A$1:$J$8014,4,FALSE) -> Justdial
A19: Rituparno | B19: =VLOOKUP(A19,DATA!A7:J8019,3,TRUE) -> bangalore | C19: =VLOOKUP(A19,DATA!$A$1:$J$8014,4,FALSE) -> Call center
